Workbook
Name Acronym: Instructions!$E$33
Name COFINPERCENT: Instructions!$E$35
Name CofinRate: 'Proposal Budget'!$J$6
Name ColumnForWPNumber: Referential!$B$15
Name CurrentFileName: Referential!$B$6
Name CurrentVersion: Referential!$D$1
Name EMP_OTHER: Instructions!$C$49
Name EMP_TYPE1: Instructions!$C$45
Name EMP_TYPE2: Instructions!$C$46
Name EMP_TYPE3: Instructions!$C$47
Name EMP_TYPE4: Instructions!$C$48
Name equipment: 'Depreciation Costs'!$A$3:$L$210
Name EURequestedAmount: 'Proposal Budget'!$J$7
Name FILESTATUS: Referential!$B$17
Name LastIDBeneficiaire: Referential!$B$7
Name LastIDWorkPackages: Referential!$B$8
Name ListOfCountries: 'Country List'!$B$2:$B$249
Name MAXSUB: Instructions!$E$34
Name MFF: Referential!$B$18
Name MyRequetedEUContribution: Referential!$B$13
Name NbrColForWP: Referential!$B$11
Name PRORATA: Referential!$B$14
Name ProtectionMode: Referential!$B$16
Name SheetBEBenCell: Referential!$B$10
Name SheetBEBenNumCell: Referential!$B$9
Name StatusBudget: 'BE-WP Overview'!$D$4
Name TotalBudget: Referential!$B$12

Sheet Instructions
A1: XXXX | B1: XXXX | C1: =CurrentVersion -> [ Version LUMP SUM II - ERASMUS - v4.4_001, of 04/10/2023 10:55 ] | F1: XXXX | G1: XXXX | H1: XXXX | I1: XXXX
C2: ANNEX 1 to Part B Detailed Estimation of Costs for Lump Sums
B4: Instructions
B6: 1 | C6: This workbook for Lump Sum calculation must be uploaded in the Submission system as a mandatory document in annex to the application. Please note that if you do not upload the fully completed Excel workbook as an annex, the application cannot be submitted (the system will not allow you to submit).
B7: 2 | C7: According to the Lump sum scheme, the lump sum for a Work Package (WP) will normally be paid only when the entire Work Package has been completed. Please take this into consideration while structuring your proposal. Work Packages should be designed in a way that enables the evaluator to clearly identify whether the action has been completed.
B8: 3 | C8: We recommend using Excel 2010 or more recent.
B9: 4 | C9: The only currency used in this worksheet is EURO.
B10: 5 | C10: The first thing you need to do is to set the relevant Maximum Grant Amount (in row 34 of this sheet), and the maximum co-financing rate (in row 35, both in column E) applicable for the call. This data can be found on the Portal under Topic Conditions and in the Call document.
B11: 6 | C11: You then have to fill in only the following sheets: ‘Beneficiaries List' – ‘Work Package list’ – ‘BE XXX’ (one sheet per Participating Organisation) – ‘Depreciation costs’ (if your budget includes the purchase of equipment). The final tab "Any comments" must be used to provide key information required for a full evaluation of your detailed budget (see point 18 below).
B12: 7 | C12: You first need to start filling in the sheet 'Beneficiaries list' where you are asked to enter all participants in the project including any Affiliated Entities. To add beneficiaries, please double-click on 'Add a Beneficiary'; to add an affiliated entity, please, double-click on 'Add an Affiliated Entity'. NOTE: the costs of Associated Partners cannot appear in any part of this budget.
B13: 8 | C13: Then you can fill in the sheet 'Work Packages list', where you are asked to enter all the Work Packages. To add a work package, please double-click on 'Add a Work Package'.
B14: 9 | C14: Once you have completed the ‘Beneficiaries List' and ‘Work Package list’ sheets, or each time you add or remove a beneficiary or a work-package, you must double-click on one of the “Apply changes” buttons to generate the related sheets in the Excel workbook. At this stage your spreadsheet is ready to be edited Beneficiary by Beneficiary (BE XXX) for all the workpackages concerned. You are requested to enter for each Beneficiary Spreadsheet, all the related costs of each WorkPackage.
B15: 10 | C15: You have to complete a ‘BE XXX’ sheet per Beneficiary. This sheet includes separate sections for the various costs categories for each Work Package of the project. Complete only the number of units and the cost per unit for each cost category. The total cost per cost category will be automatically calculated. If the Beneficiary does not contribute to a specific WP or cost category, then leave it blank.
B16: 11 | C16: You have to estimate the eligible costs of your proposal using the same methodology as if these costs were declared under an actual cost-based grant agreement. Make sure the budget table is consistent with the work packages described in application form part B. For additional information, please refer to the Annotated Model Grant Agreement.
C17: Annotaded Grant Agreement in Reference-documents section of Erasmus
B18: 12 | C18: In each ‘BE XXX’ sheet, for section “A. DIRECT PERSONNEL COSTS”, you have to encode your costs using the following unit: 1 unit is 1 person-month You can customize the categories of Employees that correspond to your organisation in rows 45 to 49 below.
B19: 13 | C19: In each ‘BE XXX’ sheet, for section 'C2. Equipment', use the ‘Depreciation costs’ sheet as a tool to calculate the depreciation costs to be charged for the whole duration of the project. This amount is NOT automatically transferred to the respective ‘BE XXX’ sheet. You have to add manually the depreciation costs in the dedicated section of the ‘BE XXX’ sheet. If you have several items in the ‘Depreciation costs’ sheet for one single section (same Beneficiary, same Work Package and same “Resource type”), you must add only the total of these items to the relevant cell in the ‘BE XXX’ sheet.
B20: 14 | C20: Indirect costs will be calculated automatically in each 'BE XXX' sheet.
B21: 15 | C21: The summary tables ‘BE-WP Overview’, 'Estim costs of the project’, ‘Proposal Budget’, and ‘BE-WP Person Months' will be produced automatically.
B24: 16 | C24: The amount calculated in the 'BE-WP Overview' sheet of this Excel workbook under the heading 'Max TOTAL EU Contribution' must be copied exactly into the Requested Grant Amount in the “Section 3 - Budget”, of the application form.
B25: 17 | C25: The ‘Estim costs of the project’, Proposal Budget' and ‘BE-WP person months' sheets are there for your information and will be used during evaluation of your application.
B26: 18 | C26: If you have any comment, you can use the ‘Any comments’ sheet. If you use the category 'other' in sections ‘A.1 Staff costs’ and / or 'C.3 Other goods, works and services', you should specify the breakdown of the cost, in the 'Any comments' sheet.
B27: 19 | C27: The format of this Excel workbook is .xlsm because it uses macros. Make sure you do not disable them when filling in the different sections. However, this format cannot be uploaded to the submission system for security reasons. Only XLSX format is allowed. Therefore, please save a copy as an .xlsx document to upload it to the proposal submission tool. To save this workbook as .xlsx document: - double-click on the button 'Create XLSX Document' in cell E37 of this Instructions sheet. OR - in Excel, click on “File” and then “Save as”; in the “Save as” dialog box, choose “.xlsx” from the “Save as type” dropdown list.
E28: XXXXXXXXXXXXXXXXXXXXXXXXXXX
D31: FILL IN THE VALUES BELOW BEFORE STARTING:
C32: Insert the name of your call | D32: :
C33: Insert the acronym of your project | D33: :
C34: Maximum grant amount as stipulated in the call | D34: : | E34: TYPE HERE THE MAXIMUM GRANT AMOUNT
C35: Maximum co-financing rate as stipulated in the call | D35: : | E35: TYPE HERE THE MAXIMUM CO-FINANCING RATE
B37: X X X | C37: The document which will be created with format .XLSX will be saved in the same folder where this workbook .XLSM is currently placed. | E37: Create XLSX document
E38: Double-Click to activate
A42: You can customize here the categories of Employees that correspond to your organisation (example: Senior Staff, Junior Staff, …). Please, note that this definition is common to all Work Packages for all Beneficiaries. | D42: X X X
A43: A. DIRECT PERSONNEL COSTS
B44: A1. Employees (or equivalent) person months (you can change the types based on your structure)
C45: Type 1
C46: Type 2
C47: Type 3
C48: Type 4
C49: Type 5

Sheet Beneficiaries List
A1: XXX | B1: XXXXXXXXXXXXXXXXXXXXXXXXXXXXXXXXXXXXXXXX | C1: XXXXXXXXXXXXXXX | D1: XXXX | F1: =COUNTA(A:A) -> 17 | G1: =COUNTA(A:A) -> 17
A2: =IF(J2=INT(J2),"BE "&TEXT(J2,"000"),"BE "&TEXT(INT(J2),"000")&" / AE "&TEXT((J2-INT(J2))*(10 ^ (LEN(J2)-LEN(INT(J2))-1)),"000")) -> BE 000 / AE 001 | F2: =IF(I2="D","TO BE REMOVED","Remove this "&IF(I2="B","Beneficiary","Affiliated Entity")) -> Remove this Affiliated Entity | G2: =IF(I2="D",IF(J2=INT(J2),"UNDO DELETE this Beneficiary",IF(OFFSET(I2,INT(-1*(J2-INT(J2))*(10^(LEN(J2)-LEN(INT(J2))-1))),0)="D","","UNDO DELETE this Affiliated Entity")),IF(OR(OFFSET(I2,1,0)="T",OFFSET(I2,1,0)="D"),"","Add an Affiliated Entity")) -> Add an Affiliated Entity | H2: T | J2: =OFFSET(J2,-1,0)+0.01 -> 0.01
A3: ALL ABOVE IS HIDDEN | G3: UNDO DELETE this Affiliated Entity
A4: List of Beneficiaries and Affiliated Entities | E4: 1 | F4: Actions (double-click to activate) | M4: =F1 -> 17
A5: BE NR/AE | B5: BE/TP name | C5: Acronym | D5: Country | F5: =IF(E4=1,"APPLY CHANGES","All is coherent") -> APPLY CHANGES | G5: Add a Beneficiary
A6: =IF(J6=INT(J6),"BE "&TEXT(J6,"000"),"BE "&TEXT(INT(J6),"000")&" / AE "&TEXT((J6-INT(J6))*(10 ^ (LEN(J6)-LEN(INT(J6))-1)),"000")) -> BE 001 | F6: =IF(I6="D","TO BE REMOVED","Remove this "&IF(I6="B","Beneficiary","Affiliated Entity")) -> Remove this Beneficiary | G6: =IF(I6="D",IF(J6=INT(J6),"UNDO DELETE this Beneficiary",IF(OFFSET(I6,INT(-1*(J6-INT(J6))*(10^(LEN(J6)-LEN(INT(J6))-1))),0)="D","","UNDO DELETE this Affiliated Entity")),IF(OR(OFFSET(I6,1,0)="T",OFFSET(I6,1,0)="D"),"","Add an Affiliated Entity")) -> Add an Affiliated Entity | H6: B | I6: B | J6: 1 | K6: 1
A7: =IF(J7=INT(J7),"BE "&TEXT(J7,"000"),"BE "&TEXT(INT(J7),"000")&" / AE "&TEXT((J7-INT(J7))*(10 ^ (LEN(J7)-LEN(INT(J7))-1)),"000")) -> BE 002 | F7: =IF(I7="D","TO BE REMOVED","Remove this "&IF(I7="B","Beneficiary","Affiliated Entity")) -> Remove this Beneficiary | G7: =IF(I7="D",IF(J7=INT(J7),"UNDO DELETE this Beneficiary",IF(OFFSET(I7,INT(-1*(J7-INT(J7))*(10^(LEN(J7)-LEN(INT(J7))-1))),0)="D","","UNDO DELETE this Affiliated Entity")),IF(OR(OFFSET(I7,1,0)="T",OFFSET(I7,1,0)="D"),"","Add an Affiliated Entity")) -> Add an Affiliated Entity | H7: T | I7: B | J7: 2 | K7: 2
A8: =IF(J8=INT(J8),"BE "&TEXT(J8,"000"),"BE "&TEXT(INT(J8),"000")&" / AE "&TEXT((J8-INT(J8))*(10 ^ (LEN(J8)-LEN(INT(J8))-1)),"000")) -> BE 003 | F8: =IF(I8="D","TO BE REMOVED","Remove this "&IF(I8="B","Beneficiary","Affiliated Entity")) -> Remove this Beneficiary | G8: =IF(I8="D",IF(J8=INT(J8),"UNDO DELETE this Beneficiary",IF(OFFSET(I8,INT(-1*(J8-INT(J8))*(10^(LEN(J8)-LEN(INT(J8))-1))),0)="D","","UNDO DELETE this Affiliated Entity")),IF(OR(OFFSET(I8,1,0)="T",OFFSET(I8,1,0)="D"),"","Add an Affiliated Entity")) -> Add an Affiliated Entity | H8: T | I8: B | J8: 3 | K8: 3
A9: =IF(J9=INT(J9),"BE "&TEXT(J9,"000"),"BE "&TEXT(INT(J9),"000")&" / AE "&TEXT((J9-INT(J9))*(10 ^ (LEN(J9)-LEN(INT(J9))-1)),"000")) -> BE 004 | F9: =IF(I9="D","TO BE REMOVED","Remove this "&IF(I9="B","Beneficiary","Affiliated Entity")) -> Remove this Beneficiary | G9: =IF(I9="D",IF(J9=INT(J9),"UNDO DELETE this Beneficiary",IF(OFFSET(I9,INT(-1*(J9-INT(J9))*(10^(LEN(J9)-LEN(INT(J9))-1))),0)="D","","UNDO DELETE this Affiliated Entity")),IF(OR(OFFSET(I9,1,0)="T",OFFSET(I9,1,0)="D"),"","Add an Affiliated Entity")) -> Add an Affiliated Entity | H9: T | I9: B | J9: 4 | K9: 4
A10: =IF(J10=INT(J10),"BE "&TEXT(J10,"000"),"BE "&TEXT(INT(J10),"000")&" / AE "&TEXT((J10-INT(J10))*(10 ^ (LEN(J10)-LEN(INT(J10))-1)),"000")) -> BE 005 | F10: =IF(I10="D","TO BE REMOVED","Remove this "&IF(I10="B","Beneficiary","Affiliated Entity")) -> Remove this Beneficiary | G10: =IF(I10="D",IF(J10=INT(J10),"UNDO DELETE this Beneficiary",IF(OFFSET(I10,INT(-1*(J10-INT(J10))*(10^(LEN(J10)-LEN(INT(J10))-1))),0)="D","","UNDO DELETE this Affiliated Entity")),IF(OR(OFFSET(I10,1,0)="T",OFFSET(I10,1,0)="D"),"","Add an Affiliated Entity")) -> Add an Affiliated Entity | H10: T | I10: B | J10: 5 | K10: 5
A11: =IF(J11=INT(J11),"BE "&TEXT(J11,"000"),"BE "&TEXT(INT(J11),"000")&" / AE "&TEXT((J11-INT(J11))*(10 ^ (LEN(J11)-LEN(INT(J11))-1)),"000")) -> BE 006 | F11: =IF(I11="D","TO BE REMOVED","Remove this "&IF(I11="B","Beneficiary","Affiliated Entity")) -> Remove this Beneficiary | G11: =IF(I11="D",IF(J11=INT(J11),"UNDO DELETE this Beneficiary",IF(OFFSET(I11,INT(-1*(J11-INT(J11))*(10^(LEN(J11)-LEN(INT(J11))-1))),0)="D","","UNDO DELETE this Affiliated Entity")),IF(OR(OFFSET(I11,1,0)="T",OFFSET(I11,1,0)="D"),"","Add an Affiliated Entity")) -> Add an Affiliated Entity | H11: T | I11: B | J11: 6 | K11: 6
A12: =IF(J12=INT(J12),"BE "&TEXT(J12,"000"),"BE "&TEXT(INT(J12),"000")&" / AE "&TEXT((J12-INT(J12))*(10 ^ (LEN(J12)-LEN(INT(J12))-1)),"000")) -> BE 007 | F12: =IF(I12="D","TO BE REMOVED","Remove this "&IF(I12="B","Beneficiary","Affiliated Entity")) -> Remove this Beneficiary | G12: =IF(I12="D",IF(J12=INT(J12),"UNDO DELETE this Beneficiary",IF(OFFSET(I12,INT(-1*(J12-INT(J12))*(10^(LEN(J12)-LEN(INT(J12))-1))),0)="D","","UNDO DELETE this Affiliated Entity")),IF(OR(OFFSET(I12,1,0)="T",OFFSET(I12,1,0)="D"),"","Add an Affiliated Entity")) -> Add an Affiliated Entity | H12: T | I12: B | J12: 7 | K12: 7
A13: =IF(J13=INT(J13),"BE "&TEXT(J13,"000"),"BE "&TEXT(INT(J13),"000")&" / AE "&TEXT((J13-INT(J13))*(10 ^ (LEN(J13)-LEN(INT(J13))-1)),"000")) -> BE 008 | F13: =IF(I13="D","TO BE REMOVED","Remove this "&IF(I13="B","Beneficiary","Affiliated Entity")) -> Remove this Beneficiary | G13: =IF(I13="D",IF(J13=INT(J13),"UNDO DELETE this Beneficiary",IF(OFFSET(I13,INT(-1*(J13-INT(J13))*(10^(LEN(J13)-LEN(INT(J13))-1))),0)="D","","UNDO DELETE this Affiliated Entity")),IF(OR(OFFSET(I13,1,0)="T",OFFSET(I13,1,0)="D"),"","Add an Affiliated Entity")) -> Add an Affiliated Entity | H13: T | I13: B | J13: 8 | K13: 8
A14: =IF(J14=INT(J14),"BE "&TEXT(J14,"000"),"BE "&TEXT(INT(J14),"000")&" / AE "&TEXT((J14-INT(J14))*(10 ^ (LEN(J14)-LEN(INT(J14))-1)),"000")) -> BE 009 | F14: =IF(I14="D","TO BE REMOVED","Remove this "&IF(I14="B","Beneficiary","Affiliated Entity")) -> Remove this Beneficiary | G14: =IF(I14="D",IF(J14=INT(J14),"UNDO DELETE this Beneficiary",IF(OFFSET(I14,INT(-1*(J14-INT(J14))*(10^(LEN(J14)-LEN(INT(J14))-1))),0)="D","","UNDO DELETE this Affiliated Entity")),IF(OR(OFFSET(I14,1,0)="T",OFFSET(I14,1,0)="D"),"","Add an Affiliated Entity")) -> Add an Affiliated Entity | H14: T | I14: B | J14: 9 | K14: 9
A15: =IF(J15=INT(J15),"BE "&TEXT(J15,"000"),"BE "&TEXT(INT(J15),"000")&" / AE "&TEXT((J15-INT(J15))*(10 ^ (LEN(J15)-LEN(INT(J15))-1)),"000")) -> BE 010 | F15: =IF(I15="D","TO BE REMOVED","Remove this "&IF(I15="B","Beneficiary","Affiliated Entity")) -> Remove this Beneficiary | G15: =IF(I15="D",IF(J15=INT(J15),"UNDO DELETE this Beneficiary",IF(OFFSET(I15,INT(-1*(J15-INT(J15))*(10^(LEN(J15)-LEN(INT(J15))-1))),0)="D","","UNDO DELETE this Affiliated Entity")),IF(OR(OFFSET(I15,1,0)="T",OFFSET(I15,1,0)="D"),"","Add an Affiliated Entity")) -> Add an Affiliated Entity | H15: T | I15: B | J15: 10 | K15: 10
A16: =IF(J16=INT(J16),"BE "&TEXT(J16,"000"),"BE "&TEXT(INT(J16),"000")&" / AE "&TEXT((J16-INT(J16))*(10 ^ (LEN(J16)-LEN(INT(J16))-1)),"000")) -> BE 011 | F16: =IF(I16="D","TO BE REMOVED","Remove this "&IF(I16="B","Beneficiary","Affiliated Entity")) -> Remove this Beneficiary | G16: =IF(I16="D",IF(J16=INT(J16),"UNDO DELETE this Beneficiary",IF(OFFSET(I16,INT(-1*(J16-INT(J16))*(10^(LEN(J16)-LEN(INT(J16))-1))),0)="D","","UNDO DELETE this Affiliated Entity")),IF(OR(OFFSET(I16,1,0)="T",OFFSET(I16,1,0)="D"),"","Add an Affiliated Entity")) -> Add an Affiliated Entity | H16: T | I16: B | J16: 11 | K16: 11
A17: =IF(J17=INT(J17),"BE "&TEXT(J17,"000"),"BE "&TEXT(INT(J17),"000")&" / AE "&TEXT((J17-INT(J17))*(10 ^ (LEN(J17)-LEN(INT(J17))-1)),"000")) -> BE 012 | F17: =IF(I17="D","TO BE REMOVED","Remove this "&IF(I17="B","Beneficiary","Affiliated Entity")) -> Remove this Beneficiary | G17: =IF(I17="D",IF(J17=INT(J17),"UNDO DELETE this Beneficiary",IF(OFFSET(I17,INT(-1*(J17-INT(J17))*(10^(LEN(J17)-LEN(INT(J17))-1))),0)="D","","UNDO DELETE this Affiliated Entity")),IF(OR(OFFSET(I17,1,0)="T",OFFSET(I17,1,0)="D"),"","Add an Affiliated Entity")) -> Add an Affiliated Entity | H17: T | I17: B | J17: 12 | K17: 12

Sheet Work Packages List
A1: XXX | B1: XXXXXXXXXXXXXXXXXXXXXXXXXXXXXXXXXXXXXXXX | C1: . | F1: . | G1: =COUNTA(A:A) -> 13 | H1: .
A2: ="WP "&TEXT(J2,"000") -> WP 000 | D2: =IF(I2="D","TO BE REMOVED","Remove this Work Package") -> Remove this Work Package | E2: =IF(I2="D","UNDO DELETE this Work Package","") | I2: W
A3: ALL ABOVE IS HIDDEN
A4: List of Work Packages | D4: Actions (double-click to activate) | I4: 1 | M4: =G1 -> 13
A5: WP Nbr | B5: WP Label | D5: =IF(I4=1,"APPLY CHANGES","All is coherent") -> APPLY CHANGES | E5: Add a Work Package
A6: ="WP "&TEXT(J6,"000") -> WP 001 | D6: =IF(I6="D","TO BE REMOVED","Remove this Work Package") -> Remove this Work Package | E6: =IF(I6="D","UNDO DELETE this Work Package","") | I6: W | J6: 1
A7: ="WP "&TEXT(J7,"000") -> WP 002 | D7: =IF(I7="D","TO BE REMOVED","Remove this Work Package") -> Remove this Work Package | E7: =IF(I7="D","UNDO DELETE this Work Package","") | I7: W | J7: 2
A8: ="WP "&TEXT(J8,"000") -> WP 003 | D8: =IF(I8="D","TO BE REMOVED","Remove this Work Package") -> Remove this Work Package | E8: =IF(I8="D","UNDO DELETE this Work Package","") | I8: W | J8: 3
A9: ="WP "&TEXT(J9,"000") -> WP 004 | D9: =IF(I9="D","TO BE REMOVED","Remove this Work Package") -> Remove this Work Package | E9: =IF(I9="D","UNDO DELETE this Work Package","") | I9: W | J9: 4
A10: ="WP "&TEXT(J10,"000") -> WP 005 | D10: =IF(I10="D","TO BE REMOVED","Remove this Work Package") -> Remove this Work Package | E10: =IF(I10="D","UNDO DELETE this Work Package","") | I10: W | J10: 5
A11: ="WP "&TEXT(J11,"000") -> WP 006 | D11: =IF(I11="D","TO BE REMOVED","Remove this Work Package") -> Remove this Work Package | E11: =IF(I11="D","UNDO DELETE this Work Package","") | I11: W | J11: 6
A12: ="WP "&TEXT(J12,"000") -> WP 007 | D12: =IF(I12="D","TO BE REMOVED","Remove this Work Package") -> Remove this Work Package | E12: =IF(I12="D","UNDO DELETE this Work Package","") | I12: W | J12: 7
A13: ="WP "&TEXT(J13,"000") -> WP 008 | D13: =IF(I13="D","TO BE REMOVED","Remove this Work Package") -> Remove this Work Package | E13: =IF(I13="D","UNDO DELETE this Work Package","") | I13: W | J13: 8

Sheet BE 001
A1: 8 | B1: =IF(ISERROR(MATCH("STARTWP" & TEXT(A1,"000"),A:A,0)),"N",MATCH("STARTWP" & TEXT(A1,"000"),A:A,0)) -> 247 | C1: =COUNTIF(E:E,"GT") -> 8 | D1: =IF(ISERROR(MATCH("ENDWP" & TEXT(A1,"000"),A:A,0)),"N",MATCH("ENDWP" & TEXT(A1,"000"),A:A,0)) -> 279 | F1: =COUNTA(A:A) -> 272 | H1: TBE | I1: =MATCH(H1,2:2,0) -> 21 | J1: =MATCH("BE",2:2,0) -> 18 | K1: =COUNTIF(2:2,"TP") -> 0 | N1: 1 | O1: XX | P1: XX | Q1: B. Subcontracting costs (please specify details under worksheet "Comments") | R1: XX.XXX,XX | S1: XXXXXXXXX,XX | T1: XXXXXXXXXXX,XX | U1: XXXXXXXXXXXXXX,XX
A2: =INDIRECT("'"& MID(OFFSET(A2,ROW(A$3)-ROW(A2),IF(OFFSET(A2,ROW(A$2)-ROW(A2),2)="T",0,IF(OFFSET(A2,ROW(A$2)-ROW(A2),1)="T",-1,-2))),1,6) & "'!" & ADDRESS(ROW(A2),MATCH(INDIRECT(ADDRESS(2,COLUMN(A2)+IF(OFFSET(A2,ROW(A$2)-ROW(A2),2)="T",1,IF(OFFSET(A2,ROW(A$2)-ROW(A2),1)="T",0,-1))),TRUE),INDIRECT("'"& MID(OFFSET(A2,ROW(A$3)-ROW(A2),IF(OFFSET(A2,ROW(A$2)-ROW(A2),2)="T",0,IF(OFFSET(A2,ROW(A$2)-ROW(A2),1)="T",-1,-2))),1,6) & "'!2:2",TRUE),0)-IF(OFFSET(A2,ROW(A$2)-ROW(A2),2)="T",1,IF(OFFSET(A2,ROW(A$2)-ROW(A2),1)="T",0,-1))),TRUE) -> #REF! | N2: 99 | R2: =IF(OFFSET(R2,0,1)="","TT",IF(INT(OFFSET(R2,0,1))=OFFSET(R2,0,1),"BE","TP")) -> BE | S2: 1 | T2: =IF(OFFSET(T2,0,-2)="TT","E","T") -> T | U2: TBE
A3: X | Q3: =""&IF(OFFSET(Q3,-2,-3)="C","DETAILED",INDIRECT("'Beneficiaries List'!A" & MATCH(OFFSET(Q3,-2,-3),'Beneficiaries List'!$J:$J,0),TRUE)) -> BE 001 | R3: =""&INDIRECT("'Beneficiaries List'!A" & MATCH(OFFSET(R3,-1,1),'Beneficiaries List'!$K:$K,0),TRUE) -> BE 001 | U3: =IF(U2="TBE","BE " & TEXT(INDIRECT(ADDRESS(2,MATCH(INT(OFFSET(U3,-1,-2)),2:2,0)),TRUE),"000"),"PROJECT") -> BE 001
A4: X | R4: =""&INDIRECT("'Beneficiaries List'!B" & MATCH(OFFSET(R4,-2,1),'Beneficiaries List'!$K:$K,0),TRUE)
A5: X | E5: 0 | F5: 1 | G5: 2 | H5: 3 | I5: 4 | J5: 5 | K5: 6 | L5: 7 | Q5: =""&IF(OFFSET(Q5,-4,-3)="C","CONSOLIDATION",INDIRECT("'Beneficiaries List'!B" & MATCH(OFFSET(Q5,-4,-3),'Beneficiaries List'!$J:$J,0),TRUE)) | R5: =IF(OFFSET(R5,-3,0)="TT","BE+TP TOTAL COSTS","UNITS") -> UNITS | S5: =IF(OFFSET(S5,0,-1)="UNITS","COST PER UNIT","") -> COST PER UNIT | T5: =IF(OFFSET(T5,0,-2)="UNITS",IF(OFFSET(T5,-3,-2)="BE","BENEFICIARY","AFFILIATED ENTITY") & " TOTAL COSTS","") -> BENEFICIARY TOTAL COSTS | U5: BE+AE TOTAL COSTS
A6: X | R6: 0 | S6: -1 | T6: -2
A7: X | O7: Total WORK PACKAGES: | R7: =SUMIF($E:$E,"GT",R:R) -> 0 | T7: =SUMIF($E:$E,"GT",T:T) -> 0 | U7: =IF(OFFSET(U7,ROW(U$2)-ROW(U7),0)="TT",SUMIF(INDIRECT(ADDRESS(2,COLUMN($Q7)+1) & ":" & ADDRESS(2,COLUMN(U7)-1),TRUE),"TBE",INDIRECT(ADDRESS(ROW(U7), COLUMN($Q7)+1) & ":" & ADDRESS(ROW(U7),COLUMN(U7)-1),TRUE)),IF(OFFSET(U7,ROW(U$2)-ROW(U7),0)="TBE",SUMIF(INDIRECT(ADDRESS(2,MATCH(INT(OFFSET(U7,ROW(U$2)-ROW(U7),-2)),$2:$2,0)) & ":" & ADDRESS(2,COLUMN(U7)-1),TRUE),"T",INDIRECT(ADDRESS(ROW(U7), MATCH(INT(OFFSET(U7,ROW(U$2)-ROW(U7),-2)),$2:$2,0)) & ":" & ADDRESS(ROW(U7),COLUMN(U7)-1),TRUE)),IF(OFFSET(U7,0,COLUMN($M7)-COLUMN(U7))="V",OFFSET(U7,0,-2)*OFFSET(U7,0,-1),"TOTAL"))) -> 0
A8: X
A9: =IF(ISNUMBER(OFFSET(A9,0,13)),"START",IF(AND(OFFSET(A9,0,2)=0,OFFSET(A9,0,4)="GT"),"END",""))&OFFSET(A9,0,1) -> STARTWP001 | B9: =IF(ISNUMBER(OFFSET(B9,0,12)),"WP" & TEXT(OFFSET(B9,0,12),"000"),OFFSET(B9,-1,0)) -> WP001 | N9: 1 | O9: =""&VLOOKUP(OFFSET(N9,1,0),'Work Packages List'!A:B,2,FALSE)
A10: =IF(ISNUMBER(OFFSET(A10,0,12)),"START",IF(AND(OFFSET(A10,0,2)=0,OFFSET(A10,0,4)="GT"),"END",""))&OFFSET(A10,0,1) -> WP001 | B10: =IF(ISNUMBER(OFFSET(B10,0,11)),"WP" & TEXT(OFFSET(B10,0,11),"000"),OFFSET(B10,-1,0)) -> WP001 | C10: 4 | D10: WPRow.A | H10: TTA | I10: TA | M10: T | N10: ="WP " & TEXT(OFFSET(N10,-1,0),"000") -> WP 001 | O10: A. DIRECT PERSONNEL COSTS | R10: =IF(OFFSET(R10,ROW(R$2)-ROW(R10),0)="TT","TT",IF(OFFSET(R10,0,COLUMN($M10)-COLUMN(R10))="%",ROUND(OFFSET(R10,-2,0)*0.07,0),IF(OFFSET(R10,0,COLUMN($M10)-COLUMN(R10))="V","x",SUMIF(INDIRECT(ADDRESS(MATCH("START"&OFFSET(R10,0,COLUMN($B10)-COLUMN(R10)),$A:$A,0),$C10+COLUMN($E10)+1)&":"&ADDRESS(MATCH("END"&OFFSET(R10,0,COLUMN($B10)-COLUMN(R10)),$A:$A,0),$C10+COLUMN($E10)+1),TRUE),INDIRECT(ADDRESS(ROW(R10),$C10+COLUMN($E10)),TRUE),INDIRECT(ADDRESS(MATCH("START"&OFFSET(R10,0,COLUMN($B10)-COLUMN(R10)),$A:$A,0),COLUMN(R10))&":"&ADDRESS(MATCH("END"&OFFSET(R10,0,COLUMN($B10)-COLUMN(R10)),$A:$A,0),COLUMN(R10)),TRUE))))) -> 0 | T10: =IF(OFFSET(T10,ROW(T$2)-ROW(T10),0)="TT","TT",IF(OFFSET(T10,0,COLUMN($M10)-COLUMN(T10))="%",ROUND((OFFSET(T10,-2,0)-OFFSET(T10,-21,0))*0.07,2),IF(OFFSET(T10,0,COLUMN($M10)-COLUMN(T10))="V",ROUND(OFFSET(T10,0,-2)*OFFSET(T10,0,-1),2),SUMIF(INDIRECT(ADDRESS(MATCH("START"&OFFSET(T10,0,COLUMN($B10)-COLUMN(T10)),$A:$A,0),$C10+COLUMN($E10)+1)&":"&ADDRESS(MATCH("END"&OFFSET(T10,0,COLUMN($B10)-COLUMN(T10)),$A:$A,0),$C10+COLUMN($E10)+1),TRUE),INDIRECT(ADDRESS(ROW(T10),$C10+COLUMN($E10)),TRUE),INDIRECT(ADDRESS(MATCH("START"&OFFSET(T10,0,COLUMN($B10)-COLUMN(T10)),$A:$A,0),COLUMN(T10))&":"&ADDRESS(MATCH("END"&OFFSET(T10,0,COLUMN($B10)-COLUMN(T10)),$A:$A,0),COLUMN(T10)),TRUE))))) -> 0 | U10: =IF(OFFSET(U10,ROW(U$2)-ROW(U10),0)="TT",SUMIF(INDIRECT(ADDRESS(2,COLUMN($Q10)+1) & ":" & ADDRESS(2,COLUMN(U10)-1),TRUE),"TBE",INDIRECT(ADDRESS(ROW(U10), COLUMN($Q10)+1) & ":" & ADDRESS(ROW(U10),COLUMN(U10)-1),TRUE)),IF(OFFSET(U10,ROW(U$2)-ROW(U10),0)="TBE",SUMIF(INDIRECT(ADDRESS(2,MATCH(INT(OFFSET(U10,ROW(U$2)-ROW(U10),-2)),$2:$2,0)) & ":" & ADDRESS(2,COLUMN(U10)-1),TRUE),"T",INDIRECT(ADDRESS(ROW(U10), MATCH(INT(OFFSET(U10,ROW(U$2)-ROW(U10),-2)),$2:$2,0)) & ":" & ADDRESS(ROW(U10),COLUMN(U10)-1),TRUE)),IF(OFFSET(U10,0,COLUMN($M10)-COLUMN(U10))="V",OFFSET(U10,0,-2)*OFFSET(U10,0,-1),"TOTAL"))) -> 0
A11: =IF(ISNUMBER(OFFSET(A11,0,12)),"START",IF(AND(OFFSET(A11,0,2)=0,OFFSET(A11,0,4)="GT"),"END",""))&OFFSET(A11,0,1) -> WP001 | B11: =IF(ISNUMBER(OFFSET(B11,0,11)),"WP" & TEXT(OFFSET(B11,0,11),"000"),OFFSET(B11,-1,0)) -> WP001 | C11: 6 | D11: WPRow.B | J11: TA | K11: T1 | M11: T | P11: A1. Employees (or equivalent) person months | R11: =IF(OFFSET(R11,ROW(R$2)-ROW(R11),0)="TT","TT",IF(OFFSET(R11,0,COLUMN($M11)-COLUMN(R11))="%",ROUND(OFFSET(R11,-2,0)*0.07,0),IF(OFFSET(R11,0,COLUMN($M11)-COLUMN(R11))="V","x",SUMIF(INDIRECT(ADDRESS(MATCH("START"&OFFSET(R11,0,COLUMN($B11)-COLUMN(R11)),$A:$A,0),$C11+COLUMN($E11)+1)&":"&ADDRESS(MATCH("END"&OFFSET(R11,0,COLUMN($B11)-COLUMN(R11)),$A:$A,0),$C11+COLUMN($E11)+1),TRUE),INDIRECT(ADDRESS(ROW(R11),$C11+COLUMN($E11)),TRUE),INDIRECT(ADDRESS(MATCH("START"&OFFSET(R11,0,COLUMN($B11)-COLUMN(R11)),$A:$A,0),COLUMN(R11))&":"&ADDRESS(MATCH("END"&OFFSET(R11,0,COLUMN($B11)-COLUMN(R11)),$A:$A,0),COLUMN(R11)),TRUE))))) -> 0 | T11: =IF(OFFSET(T11,ROW(T$2)-ROW(T11),0)="TT","TT",IF(OFFSET(T11,0,COLUMN($M11)-COLUMN(T11))="%",ROUND((OFFSET(T11,-2,0)-OFFSET(T11,-21,0))*0.07,2),IF(OFFSET(T11,0,COLUMN($M11)-COLUMN(T11))="V",ROUND(OFFSET(T11,0,-2)*OFFSET(T11,0,-1),2),SUMIF(INDIRECT(ADDRESS(MATCH("START"&OFFSET(T11,0,COLUMN($B11)-COLUMN(T11)),$A:$A,0),$C11+COLUMN($E11)+1)&":"&ADDRESS(MATCH("END"&OFFSET(T11,0,COLUMN($B11)-COLUMN(T11)),$A:$A,0),$C11+COLUMN($E11)+1),TRUE),INDIRECT(ADDRESS(ROW(T11),$C11+COLUMN($E11)),TRUE),INDIRECT(ADDRESS(MATCH("START"&OFFSET(T11,0,COLUMN($B11)-COLUMN(T11)),$A:$A,0),COLUMN(T11))&":"&ADDRESS(MATCH("END"&OFFSET(T11,0,COLUMN($B11)-COLUMN(T11)),$A:$A,0),COLUMN(T11)),TRUE))))) -> 0 | U11: =IF(OFFSET(U11,ROW(U$2)-ROW(U11),0)="TT",SUMIF(INDIRECT(ADDRESS(2,COLUMN($Q11)+1) & ":" & ADDRESS(2,COLUMN(U11)-1),TRUE),"TBE",INDIRECT(ADDRESS(ROW(U11), COLUMN($Q11)+1) & ":" & ADDRESS(ROW(U11),COLUMN(U11)-1),TRUE)),IF(OFFSET(U11,ROW(U$2)-ROW(U11),0)="TBE",SUMIF(INDIRECT(ADDRESS(2,MATCH(INT(OFFSET(U11,ROW(U$2)-ROW(U11),-2)),$2:$2,0)) & ":" & ADDRESS(2,COLUMN(U11)-1),TRUE),"T",INDIRECT(ADDRESS(ROW(U11), MATCH(INT(OFFSET(U11,ROW(U$2)-ROW(U11),-2)),$2:$2,0)) & ":" & ADDRESS(ROW(U11),COLUMN(U11)-1),TRUE)),IF(OFFSET(U11,0,COLUMN($M11)-COLUMN(U11))="V",OFFSET(U11,0,-2)*OFFSET(U11,0,-1),"TOTAL"))) -> 0
A12: =IF(ISNUMBER(OFFSET(A12,0,12)),"START",IF(AND(OFFSET(A12,0,2)=0,OFFSET(A12,0,4)="GT"),"END",""))&OFFSET(A12,0,1) -> WP001 | B12: =IF(ISNUMBER(OFFSET(B12,0,11)),"WP" & TEXT(OFFSET(B12,0,11),"000"),OFFSET(B12,-1,0)) -> WP001 | C12: 7 | D12: WPRow.C | L12: T1 | M12: V | Q12: =EMP_TYPE1 -> Type 1 | T12: =IF(OFFSET(T12,ROW(T$2)-ROW(T12),0)="TT","TT",IF(OFFSET(T12,0,COLUMN($M12)-COLUMN(T12))="%",ROUND((OFFSET(T12,-2,0)-OFFSET(T12,-21,0))*0.07,2),IF(OFFSET(T12,0,COLUMN($M12)-COLUMN(T12))="V",ROUND(OFFSET(T12,0,-2)*OFFSET(T12,0,-1),2),SUMIF(INDIRECT(ADDRESS(MATCH("START"&OFFSET(T12,0,COLUMN($B12)-COLUMN(T12)),$A:$A,0),$C12+COLUMN($E12)+1)&":"&ADDRESS(MATCH("END"&OFFSET(T12,0,COLUMN($B12)-COLUMN(T12)),$A:$A,0),$C12+COLUMN($E12)+1),TRUE),INDIRECT(ADDRESS(ROW(T12),$C12+COLUMN($E12)),TRUE),INDIRECT(ADDRESS(MATCH("START"&OFFSET(T12,0,COLUMN($B12)-COLUMN(T12)),$A:$A,0),COLUMN(T12))&":"&ADDRESS(MATCH("END"&OFFSET(T12,0,COLUMN($B12)-COLUMN(T12)),$A:$A,0),COLUMN(T12)),TRUE))))) -> 0 | U12: =IF(OFFSET(U12,ROW(U$2)-ROW(U12),0)="TT",SUMIF(INDIRECT(ADDRESS(2,COLUMN($Q12)+1) & ":" & ADDRESS(2,COLUMN(U12)-1),TRUE),"TBE",INDIRECT(ADDRESS(ROW(U12), COLUMN($Q12)+1) & ":" & ADDRESS(ROW(U12),COLUMN(U12)-1),TRUE)),IF(OFFSET(U12,ROW(U$2)-ROW(U12),0)="TBE",SUMIF(INDIRECT(ADDRESS(2,MATCH(INT(OFFSET(U12,ROW(U$2)-ROW(U12),-2)),$2:$2,0)) & ":" & ADDRESS(2,COLUMN(U12)-1),TRUE),"T",INDIRECT(ADDRESS(ROW(U12), MATCH(INT(OFFSET(U12,ROW(U$2)-ROW(U12),-2)),$2:$2,0)) & ":" & ADDRESS(ROW(U12),COLUMN(U12)-1),TRUE)),IF(OFFSET(U12,0,COLUMN($M12)-COLUMN(U12))="V",OFFSET(U12,0,-2)*OFFSET(U12,0,-1),"TOTAL"))) -> 0
A13: =IF(ISNUMBER(OFFSET(A13,0,12)),"START",IF(AND(OFFSET(A13,0,2)=0,OFFSET(A13,0,4)="GT"),"END",""))&OFFSET(A13,0,1) -> WP001 | B13: =IF(ISNUMBER(OFFSET(B13,0,11)),"WP" & TEXT(OFFSET(B13,0,11),"000"),OFFSET(B13,-1,0)) -> WP001 | C13: 7 | D13: WPRow.D | L13: T1 | M13: V | Q13: =EMP_TYPE2 -> Type 2 | T13: =IF(OFFSET(T13,ROW(T$2)-ROW(T13),0)="TT","TT",IF(OFFSET(T13,0,COLUMN($M13)-COLUMN(T13))="%",ROUND((OFFSET(T13,-2,0)-OFFSET(T13,-21,0))*0.07,2),IF(OFFSET(T13,0,COLUMN($M13)-COLUMN(T13))="V",ROUND(OFFSET(T13,0,-2)*OFFSET(T13,0,-1),2),SUMIF(INDIRECT(ADDRESS(MATCH("START"&OFFSET(T13,0,COLUMN($B13)-COLUMN(T13)),$A:$A,0),$C13+COLUMN($E13)+1)&":"&ADDRESS(MATCH("END"&OFFSET(T13,0,COLUMN($B13)-COLUMN(T13)),$A:$A,0),$C13+COLUMN($E13)+1),TRUE),INDIRECT(ADDRESS(ROW(T13),$C13+COLUMN($E13)),TRUE),INDIRECT(ADDRESS(MATCH("START"&OFFSET(T13,0,COLUMN($B13)-COLUMN(T13)),$A:$A,0),COLUMN(T13))&":"&ADDRESS(MATCH("END"&OFFSET(T13,0,COLUMN($B13)-COLUMN(T13)),$A:$A,0),COLUMN(T13)),TRUE))))) -> 0 | U13: =IF(OFFSET(U13,ROW(U$2)-ROW(U13),0)="TT",SUMIF(INDIRECT(ADDRESS(2,COLUMN($Q13)+1) & ":" & ADDRESS(2,COLUMN(U13)-1),TRUE),"TBE",INDIRECT(ADDRESS(ROW(U13), COLUMN($Q13)+1) & ":" & ADDRESS(ROW(U13),COLUMN(U13)-1),TRUE)),IF(OFFSET(U13,ROW(U$2)-ROW(U13),0)="TBE",SUMIF(INDIRECT(ADDRESS(2,MATCH(INT(OFFSET(U13,ROW(U$2)-ROW(U13),-2)),$2:$2,0)) & ":" & ADDRESS(2,COLUMN(U13)-1),TRUE),"T",INDIRECT(ADDRESS(ROW(U13), MATCH(INT(OFFSET(U13,ROW(U$2)-ROW(U13),-2)),$2:$2,0)) & ":" & ADDRESS(ROW(U13),COLUMN(U13)-1),TRUE)),IF(OFFSET(U13,0,COLUMN($M13)-COLUMN(U13))="V",OFFSET(U13,0,-2)*OFFSET(U13,0,-1),"TOTAL"))) -> 0
A14: =IF(ISNUMBER(OFFSET(A14,0,12)),"START",IF(AND(OFFSET(A14,0,2)=0,OFFSET(A14,0,4)="GT"),"END",""))&OFFSET(A14,0,1) -> WP001 | B14: =IF(ISNUMBER(OFFSET(B14,0,11)),"WP" & TEXT(OFFSET(B14,0,11),"000"),OFFSET(B14,-1,0)) -> WP001 | C14: 7 | D14: WPRow.E | L14: T1 | M14: V | Q14: =EMP_TYPE3 -> Type 3 | T14: =IF(OFFSET(T14,ROW(T$2)-ROW(T14),0)="TT","TT",IF(OFFSET(T14,0,COLUMN($M14)-COLUMN(T14))="%",ROUND((OFFSET(T14,-2,0)-OFFSET(T14,-21,0))*0.07,2),IF(OFFSET(T14,0,COLUMN($M14)-COLUMN(T14))="V",ROUND(OFFSET(T14,0,-2)*OFFSET(T14,0,-1),2),SUMIF(INDIRECT(ADDRESS(MATCH("START"&OFFSET(T14,0,COLUMN($B14)-COLUMN(T14)),$A:$A,0),$C14+COLUMN($E14)+1)&":"&ADDRESS(MATCH("END"&OFFSET(T14,0,COLUMN($B14)-COLUMN(T14)),$A:$A,0),$C14+COLUMN($E14)+1),TRUE),INDIRECT(ADDRESS(ROW(T14),$C14+COLUMN($E14)),TRUE),INDIRECT(ADDRESS(MATCH("START"&OFFSET(T14,0,COLUMN($B14)-COLUMN(T14)),$A:$A,0),COLUMN(T14))&":"&ADDRESS(MATCH("END"&OFFSET(T14,0,COLUMN($B14)-COLUMN(T14)),$A:$A,0),COLUMN(T14)),TRUE))))) -> 0 | U14: =IF(OFFSET(U14,ROW(U$2)-ROW(U14),0)="TT",SUMIF(INDIRECT(ADDRESS(2,COLUMN($Q14)+1) & ":" & ADDRESS(2,COLUMN(U14)-1),TRUE),"TBE",INDIRECT(ADDRESS(ROW(U14), COLUMN($Q14)+1) & ":" & ADDRESS(ROW(U14),COLUMN(U14)-1),TRUE)),IF(OFFSET(U14,ROW(U$2)-ROW(U14),0)="TBE",SUMIF(INDIRECT(ADDRESS(2,MATCH(INT(OFFSET(U14,ROW(U$2)-ROW(U14),-2)),$2:$2,0)) & ":" & ADDRESS(2,COLUMN(U14)-1),TRUE),"T",INDIRECT(ADDRESS(ROW(U14), MATCH(INT(OFFSET(U14,ROW(U$2)-ROW(U14),-2)),$2:$2,0)) & ":" & ADDRESS(ROW(U14),COLUMN(U14)-1),TRUE)),IF(OFFSET(U14,0,COLUMN($M14)-COLUMN(U14))="V",OFFSET(U14,0,-2)*OFFSET(U14,0,-1),"TOTAL"))) -> 0
A15: =IF(ISNUMBER(OFFSET(A15,0,12)),"START",IF(AND(OFFSET(A15,0,2)=0,OFFSET(A15,0,4)="GT"),"END",""))&OFFSET(A15,0,1) -> WP001 | B15: =IF(ISNUMBER(OFFSET(B15,0,11)),"WP" & TEXT(OFFSET(B15,0,11),"000"),OFFSET(B15,-1,0)) -> WP001 | C15: 7 | D15: WPRow.F | L15: T1 | M15: V | Q15: =EMP_TYPE4 -> Type 4 | T15: =IF(OFFSET(T15,ROW(T$2)-ROW(T15),0)="TT","TT",IF(OFFSET(T15,0,COLUMN($M15)-COLUMN(T15))="%",ROUND((OFFSET(T15,-2,0)-OFFSET(T15,-21,0))*0.07,2),IF(OFFSET(T15,0,COLUMN($M15)-COLUMN(T15))="V",ROUND(OFFSET(T15,0,-2)*OFFSET(T15,0,-1),2),SUMIF(INDIRECT(ADDRESS(MATCH("START"&OFFSET(T15,0,COLUMN($B15)-COLUMN(T15)),$A:$A,0),$C15+COLUMN($E15)+1)&":"&ADDRESS(MATCH("END"&OFFSET(T15,0,COLUMN($B15)-COLUMN(T15)),$A:$A,0),$C15+COLUMN($E15)+1),TRUE),INDIRECT(ADDRESS(ROW(T15),$C15+COLUMN($E15)),TRUE),INDIRECT(ADDRESS(MATCH("START"&OFFSET(T15,0,COLUMN($B15)-COLUMN(T15)),$A:$A,0),COLUMN(T15))&":"&ADDRESS(MATCH("END"&OFFSET(T15,0,COLUMN($B15)-COLUMN(T15)),$A:$A,0),COLUMN(T15)),TRUE))))) -> 0 | U15: =IF(OFFSET(U15,ROW(U$2)-ROW(U15),0)="TT",SUMIF(INDIRECT(ADDRESS(2,COLUMN($Q15)+1) & ":" & ADDRESS(2,COLUMN(U15)-1),TRUE),"TBE",INDIRECT(ADDRESS(ROW(U15), COLUMN($Q15)+1) & ":" & ADDRESS(ROW(U15),COLUMN(U15)-1),TRUE)),IF(OFFSET(U15,ROW(U$2)-ROW(U15),0)="TBE",SUMIF(INDIRECT(ADDRESS(2,MATCH(INT(OFFSET(U15,ROW(U$2)-ROW(U15),-2)),$2:$2,0)) & ":" & ADDRESS(2,COLUMN(U15)-1),TRUE),"T",INDIRECT(ADDRESS(ROW(U15), MATCH(INT(OFFSET(U15,ROW(U$2)-ROW(U15),-2)),$2:$2,0)) & ":" & ADDRESS(ROW(U15),COLUMN(U15)-1),TRUE)),IF(OFFSET(U15,0,COLUMN($M15)-COLUMN(U15))="V",OFFSET(U15,0,-2)*OFFSET(U15,0,-1),"TOTAL"))) -> 0
A16: =IF(ISNUMBER(OFFSET(A16,0,12)),"START",IF(AND(OFFSET(A16,0,2)=0,OFFSET(A16,0,4)="GT"),"END",""))&OFFSET(A16,0,1) -> WP001 | B16: =IF(ISNUMBER(OFFSET(B16,0,11)),"WP" & TEXT(OFFSET(B16,0,11),"000"),OFFSET(B16,-1,0)) -> WP001 | C16: 7 | D16: WPRow.G | L16: T1 | M16: V | Q16: =EMP_OTHER -> Type 5 | T16: =IF(OFFSET(T16,ROW(T$2)-ROW(T16),0)="TT","TT",IF(OFFSET(T16,0,COLUMN($M16)-COLUMN(T16))="%",ROUND((OFFSET(T16,-2,0)-OFFSET(T16,-21,0))*0.07,2),IF(OFFSET(T16,0,COLUMN($M16)-COLUMN(T16))="V",ROUND(OFFSET(T16,0,-2)*OFFSET(T16,0,-1),2),SUMIF(INDIRECT(ADDRESS(MATCH("START"&OFFSET(T16,0,COLUMN($B16)-COLUMN(T16)),$A:$A,0),$C16+COLUMN($E16)+1)&":"&ADDRESS(MATCH("END"&OFFSET(T16,0,COLUMN($B16)-COLUMN(T16)),$A:$A,0),$C16+COLUMN($E16)+1),TRUE),INDIRECT(ADDRESS(ROW(T16),$C16+COLUMN($E16)),TRUE),INDIRECT(ADDRESS(MATCH("START"&OFFSET(T16,0,COLUMN($B16)-COLUMN(T16)),$A:$A,0),COLUMN(T16))&":"&ADDRESS(MATCH("END"&OFFSET(T16,0,COLUMN($B16)-COLUMN(T16)),$A:$A,0),COLUMN(T16)),TRUE))))) -> 0 | U16: =IF(OFFSET(U16,ROW(U$2)-ROW(U16),0)="TT",SUMIF(INDIRECT(ADDRESS(2,COLUMN($Q16)+1) & ":" & ADDRESS(2,COLUMN(U16)-1),TRUE),"TBE",INDIRECT(ADDRESS(ROW(U16), COLUMN($Q16)+1) & ":" & ADDRESS(ROW(U16),COLUMN(U16)-1),TRUE)),IF(OFFSET(U16,ROW(U$2)-ROW(U16),0)="TBE",SUMIF(INDIRECT(ADDRESS(2,MATCH(INT(OFFSET(U16,ROW(U$2)-ROW(U16),-2)),$2:$2,0)) & ":" & ADDRESS(2,COLUMN(U16)-1),TRUE),"T",INDIRECT(ADDRESS(ROW(U16), MATCH(INT(OFFSET(U16,ROW(U$2)-ROW(U16),-2)),$2:$2,0)) & ":" & ADDRESS(ROW(U16),COLUMN(U16)-1),TRUE)),IF(OFFSET(U16,0,COLUMN($M16)-COLUMN(U16))="V",OFFSET(U16,0,-2)*OFFSET(U16,0,-1),"TOTAL"))) -> 0
A17: =IF(ISNUMBER(OFFSET(A17,0,12)),"START",IF(AND(OFFSET(A17,0,2)=0,OFFSET(A17,0,4)="GT"),"END",""))&OFFSET(A17,0,1) -> WP001 | B17: =IF(ISNUMBER(OFFSET(B17,0,11)),"WP" & TEXT(OFFSET(B17,0,11),"000"),OFFSET(B17,-1,0)) -> WP001 | C17: 6 | D17: WPRow.H | J17: TA | M17: V | P17: A.2 Natural persons under direct contract | T17: =IF(OFFSET(T17,ROW(T$2)-ROW(T17),0)="TT","TT",IF(OFFSET(T17,0,COLUMN($M17)-COLUMN(T17))="%",ROUND((OFFSET(T17,-2,0)-OFFSET(T17,-21,0))*0.07,2),IF(OFFSET(T17,0,COLUMN($M17)-COLUMN(T17))="V",ROUND(OFFSET(T17,0,-2)*OFFSET(T17,0,-1),2),SUMIF(INDIRECT(ADDRESS(MATCH("START"&OFFSET(T17,0,COLUMN($B17)-COLUMN(T17)),$A:$A,0),$C17+COLUMN($E17)+1)&":"&ADDRESS(MATCH("END"&OFFSET(T17,0,COLUMN($B17)-COLUMN(T17)),$A:$A,0),$C17+COLUMN($E17)+1),TRUE),INDIRECT(ADDRESS(ROW(T17),$C17+COLUMN($E17)),TRUE),INDIRECT(ADDRESS(MATCH("START"&OFFSET(T17,0,COLUMN($B17)-COLUMN(T17)),$A:$A,0),COLUMN(T17))&":"&ADDRESS(MATCH("END"&OFFSET(T17,0,COLUMN($B17)-COLUMN(T17)),$A:$A,0),COLUMN(T17)),TRUE))))) -> 0 | U17: =IF(OFFSET(U17,ROW(U$2)-ROW(U17),0)="TT",SUMIF(INDIRECT(ADDRESS(2,COLUMN($Q17)+1) & ":" & ADDRESS(2,COLUMN(U17)-1),TRUE),"TBE",INDIRECT(ADDRESS(ROW(U17), COLUMN($Q17)+1) & ":" & ADDRESS(ROW(U17),COLUMN(U17)-1),TRUE)),IF(OFFSET(U17,ROW(U$2)-ROW(U17),0)="TBE",SUMIF(INDIRECT(ADDRESS(2,MATCH(INT(OFFSET(U17,ROW(U$2)-ROW(U17),-2)),$2:$2,0)) & ":" & ADDRESS(2,COLUMN(U17)-1),TRUE),"T",INDIRECT(ADDRESS(ROW(U17), MATCH(INT(OFFSET(U17,ROW(U$2)-ROW(U17),-2)),$2:$2,0)) & ":" & ADDRESS(ROW(U17),COLUMN(U17)-1),TRUE)),IF(OFFSET(U17,0,COLUMN($M17)-COLUMN(U17))="V",OFFSET(U17,0,-2)*OFFSET(U17,0,-1),"TOTAL"))) -> 0
A18: =IF(ISNUMBER(OFFSET(A18,0,12)),"START",IF(AND(OFFSET(A18,0,2)=0,OFFSET(A18,0,4)="GT"),"END",""))&OFFSET(A18,0,1) -> WP001 | B18: =IF(ISNUMBER(OFFSET(B18,0,11)),"WP" & TEXT(OFFSET(B18,0,11),"000"),OFFSET(B18,-1,0)) -> WP001 | C18: 6 | D18: WPRow.I | J18: TA | M18: V | P18: A.3 Seconded persons | T18: =IF(OFFSET(T18,ROW(T$2)-ROW(T18),0)="TT","TT",IF(OFFSET(T18,0,COLUMN($M18)-COLUMN(T18))="%",ROUND((OFFSET(T18,-2,0)-OFFSET(T18,-21,0))*0.07,2),IF(OFFSET(T18,0,COLUMN($M18)-COLUMN(T18))="V",ROUND(OFFSET(T18,0,-2)*OFFSET(T18,0,-1),2),SUMIF(INDIRECT(ADDRESS(MATCH("START"&OFFSET(T18,0,COLUMN($B18)-COLUMN(T18)),$A:$A,0),$C18+COLUMN($E18)+1)&":"&ADDRESS(MATCH("END"&OFFSET(T18,0,COLUMN($B18)-COLUMN(T18)),$A:$A,0),$C18+COLUMN($E18)+1),TRUE),INDIRECT(ADDRESS(ROW(T18),$C18+COLUMN($E18)),TRUE),INDIRECT(ADDRESS(MATCH("START"&OFFSET(T18,0,COLUMN($B18)-COLUMN(T18)),$A:$A,0),COLUMN(T18))&":"&ADDRESS(MATCH("END"&OFFSET(T18,0,COLUMN($B18)-COLUMN(T18)),$A:$A,0),COLUMN(T18)),TRUE))))) -> 0 | U18: =IF(OFFSET(U18,ROW(U$2)-ROW(U18),0)="TT",SUMIF(INDIRECT(ADDRESS(2,COLUMN($Q18)+1) & ":" & ADDRESS(2,COLUMN(U18)-1),TRUE),"TBE",INDIRECT(ADDRESS(ROW(U18), COLUMN($Q18)+1) & ":" & ADDRESS(ROW(U18),COLUMN(U18)-1),TRUE)),IF(OFFSET(U18,ROW(U$2)-ROW(U18),0)="TBE",SUMIF(INDIRECT(ADDRESS(2,MATCH(INT(OFFSET(U18,ROW(U$2)-ROW(U18),-2)),$2:$2,0)) & ":" & ADDRESS(2,COLUMN(U18)-1),TRUE),"T",INDIRECT(ADDRESS(ROW(U18), MATCH(INT(OFFSET(U18,ROW(U$2)-ROW(U18),-2)),$2:$2,0)) & ":" & ADDRESS(ROW(U18),COLUMN(U18)-1),TRUE)),IF(OFFSET(U18,0,COLUMN($M18)-COLUMN(U18))="V",OFFSET(U18,0,-2)*OFFSET(U18,0,-1),"TOTAL"))) -> 0
A19: =IF(ISNUMBER(OFFSET(A19,0,12)),"START",IF(AND(OFFSET(A19,0,2)=0,OFFSET(A19,0,4)="GT"),"END",""))&OFFSET(A19,0,1) -> WP001 | B19: =IF(ISNUMBER(OFFSET(B19,0,11)),"WP" & TEXT(OFFSET(B19,0,11),"000"),OFFSET(B19,-1,0)) -> WP001 | C19: 6 | D19: WPRow.J | J19: TA | M19: V | P19: A.4 SME Owners without salary | T19: =IF(OFFSET(T19,ROW(T$2)-ROW(T19),0)="TT","TT",IF(OFFSET(T19,0,COLUMN($M19)-COLUMN(T19))="%",ROUND((OFFSET(T19,-2,0)-OFFSET(T19,-21,0))*0.07,2),IF(OFFSET(T19,0,COLUMN($M19)-COLUMN(T19))="V",ROUND(OFFSET(T19,0,-2)*OFFSET(T19,0,-1),2),SUMIF(INDIRECT(ADDRESS(MATCH("START"&OFFSET(T19,0,COLUMN($B19)-COLUMN(T19)),$A:$A,0),$C19+COLUMN($E19)+1)&":"&ADDRESS(MATCH("END"&OFFSET(T19,0,COLUMN($B19)-COLUMN(T19)),$A:$A,0),$C19+COLUMN($E19)+1),TRUE),INDIRECT(ADDRESS(ROW(T19),$C19+COLUMN($E19)),TRUE),INDIRECT(ADDRESS(MATCH("START"&OFFSET(T19,0,COLUMN($B19)-COLUMN(T19)),$A:$A,0),COLUMN(T19))&":"&ADDRESS(MATCH("END"&OFFSET(T19,0,COLUMN($B19)-COLUMN(T19)),$A:$A,0),COLUMN(T19)),TRUE))))) -> 0 | U19: =IF(OFFSET(U19,ROW(U$2)-ROW(U19),0)="TT",SUMIF(INDIRECT(ADDRESS(2,COLUMN($Q19)+1) & ":" & ADDRESS(2,COLUMN(U19)-1),TRUE),"TBE",INDIRECT(ADDRESS(ROW(U19), COLUMN($Q19)+1) & ":" & ADDRESS(ROW(U19),COLUMN(U19)-1),TRUE)),IF(OFFSET(U19,ROW(U$2)-ROW(U19),0)="TBE",SUMIF(INDIRECT(ADDRESS(2,MATCH(INT(OFFSET(U19,ROW(U$2)-ROW(U19),-2)),$2:$2,0)) & ":" & ADDRESS(2,COLUMN(U19)-1),TRUE),"T",INDIRECT(ADDRESS(ROW(U19), MATCH(INT(OFFSET(U19,ROW(U$2)-ROW(U19),-2)),$2:$2,0)) & ":" & ADDRESS(ROW(U19),COLUMN(U19)-1),TRUE)),IF(OFFSET(U19,0,COLUMN($M19)-COLUMN(U19))="V",OFFSET(U19,0,-2)*OFFSET(U19,0,-1),"TOTAL"))) -> 0
A20: =IF(ISNUMBER(OFFSET(A20,0,12)),"START",IF(AND(OFFSET(A20,0,2)=0,OFFSET(A20,0,4)="GT"),"END",""))&OFFSET(A20,0,1) -> WP001 | B20: =IF(ISNUMBER(OFFSET(B20,0,11)),"WP" & TEXT(OFFSET(B20,0,11),"000"),OFFSET(B20,-1,0)) -> WP001 | C20: 6 | D20: WPRow.K | J20: TA | M20: V | P20: A.5 Volunteers | T20: =IF(OFFSET(T20,ROW(T$2)-ROW(T20),0)="TT","TT",IF(OFFSET(T20,0,COLUMN($M20)-COLUMN(T20))="%",ROUND((OFFSET(T20,-2,0)-OFFSET(T20,-21,0))*0.07,2),IF(OFFSET(T20,0,COLUMN($M20)-COLUMN(T20))="V",ROUND(OFFSET(T20,0,-2)*OFFSET(T20,0,-1),2),SUMIF(INDIRECT(ADDRESS(MATCH("START"&OFFSET(T20,0,COLUMN($B20)-COLUMN(T20)),$A:$A,0),$C20+COLUMN($E20)+1)&":"&ADDRESS(MATCH("END"&OFFSET(T20,0,COLUMN($B20)-COLUMN(T20)),$A:$A,0),$C20+COLUMN($E20)+1),TRUE),INDIRECT(ADDRESS(ROW(T20),$C20+COLUMN($E20)),TRUE),INDIRECT(ADDRESS(MATCH("START"&OFFSET(T20,0,COLUMN($B20)-COLUMN(T20)),$A:$A,0),COLUMN(T20))&":"&ADDRESS(MATCH("END"&OFFSET(T20,0,COLUMN($B20)-COLUMN(T20)),$A:$A,0),COLUMN(T20)),TRUE))))) -> 0 | U20: =IF(OFFSET(U20,ROW(U$2)-ROW(U20),0)="TT",SUMIF(INDIRECT(ADDRESS(2,COLUMN($Q20)+1) & ":" & ADDRESS(2,COLUMN(U20)-1),TRUE),"TBE",INDIRECT(ADDRESS(ROW(U20), COLUMN($Q20)+1) & ":" & ADDRESS(ROW(U20),COLUMN(U20)-1),TRUE)),IF(OFFSET(U20,ROW(U$2)-ROW(U20),0)="TBE",SUMIF(INDIRECT(ADDRESS(2,MATCH(INT(OFFSET(U20,ROW(U$2)-ROW(U20),-2)),$2:$2,0)) & ":" & ADDRESS(2,COLUMN(U20)-1),TRUE),"T",INDIRECT(ADDRESS(ROW(U20), MATCH(INT(OFFSET(U20,ROW(U$2)-ROW(U20),-2)),$2:$2,0)) & ":" & ADDRESS(ROW(U20),COLUMN(U20)-1),TRUE)),IF(OFFSET(U20,0,COLUMN($M20)-COLUMN(U20))="V",OFFSET(U20,0,-2)*OFFSET(U20,0,-1),"TOTAL"))) -> 0
A21: =IF(ISNUMBER(OFFSET(A21,0,12)),"START",IF(AND(OFFSET(A21,0,2)=0,OFFSET(A21,0,4)="GT"),"END",""))&OFFSET(A21,0,1) -> WP001 | B21: =IF(ISNUMBER(OFFSET(B21,0,11)),"WP" & TEXT(OFFSET(B21,0,11),"000"),OFFSET(B21,-1,0)) -> WP001 | C21: 4 | D21: WPRow.L | H21: TTA | I21: TB | M21: V | O21: B. Subcontracting costs (please specify details under worksheet "Comments") | T21: =IF(OFFSET(T21,ROW(T$2)-ROW(T21),0)="TT","TT",IF(OFFSET(T21,0,COLUMN($M21)-COLUMN(T21))="%",ROUND((OFFSET(T21,-2,0)-OFFSET(T21,-21,0))*0.07,2),IF(OFFSET(T21,0,COLUMN($M21)-COLUMN(T21))="V",ROUND(OFFSET(T21,0,-2)*OFFSET(T21,0,-1),2),SUMIF(INDIRECT(ADDRESS(MATCH("START"&OFFSET(T21,0,COLUMN($B21)-COLUMN(T21)),$A:$A,0),$C21+COLUMN($E21)+1)&":"&ADDRESS(MATCH("END"&OFFSET(T21,0,COLUMN($B21)-COLUMN(T21)),$A:$A,0),$C21+COLUMN($E21)+1),TRUE),INDIRECT(ADDRESS(ROW(T21),$C21+COLUMN($E21)),TRUE),INDIRECT(ADDRESS(MATCH("START"&OFFSET(T21,0,COLUMN($B21)-COLUMN(T21)),$A:$A,0),COLUMN(T21))&":"&ADDRESS(MATCH("END"&OFFSET(T21,0,COLUMN($B21)-COLUMN(T21)),$A:$A,0),COLUMN(T21)),TRUE))))) -> 0 | U21: =IF(OFFSET(U21,ROW(U$2)-ROW(U21),0)="TT",SUMIF(INDIRECT(ADDRESS(2,COLUMN($Q21)+1) & ":" & ADDRESS(2,COLUMN(U21)-1),TRUE),"TBE",INDIRECT(ADDRESS(ROW(U21), COLUMN($Q21)+1) & ":" & ADDRESS(ROW(U21),COLUMN(U21)-1),TRUE)),IF(OFFSET(U21,ROW(U$2)-ROW(U21),0)="TBE",SUMIF(INDIRECT(ADDRESS(2,MATCH(INT(OFFSET(U21,ROW(U$2)-ROW(U21),-2)),$2:$2,0)) & ":" & ADDRESS(2,COLUMN(U21)-1),TRUE),"T",INDIRECT(ADDRESS(ROW(U21), MATCH(INT(OFFSET(U21,ROW(U$2)-ROW(U21),-2)),$2:$2,0)) & ":" & ADDRESS(ROW(U21),COLUMN(U21)-1),TRUE)),IF(OFFSET(U21,0,COLUMN($M21)-COLUMN(U21))="V",OFFSET(U21,0,-2)*OFFSET(U21,0,-1),"TOTAL"))) -> 0
A22: =IF(ISNUMBER(OFFSET(A22,0,12)),"START",IF(AND(OFFSET(A22,0,2)=0,OFFSET(A22,0,4)="GT"),"END",""))&OFFSET(A22,0,1) -> WP001 | B22: =IF(ISNUMBER(OFFSET(B22,0,11)),"WP" & TEXT(OFFSET(B22,0,11),"000"),OFFSET(B22,-1,0)) -> WP001 | C22: 4 | D22: WPRow.M | H22: TTA | I22: TC | M22: T | O22: C. Purchase costs | T22: =IF(OFFSET(T22,ROW(T$2)-ROW(T22),0)="TT","TT",IF(OFFSET(T22,0,COLUMN($M22)-COLUMN(T22))="%",ROUND((OFFSET(T22,-2,0)-OFFSET(T22,-21,0))*0.07,2),IF(OFFSET(T22,0,COLUMN($M22)-COLUMN(T22))="V",ROUND(OFFSET(T22,0,-2)*OFFSET(T22,0,-1),2),SUMIF(INDIRECT(ADDRESS(MATCH("START"&OFFSET(T22,0,COLUMN($B22)-COLUMN(T22)),$A:$A,0),$C22+COLUMN($E22)+1)&":"&ADDRESS(MATCH("END"&OFFSET(T22,0,COLUMN($B22)-COLUMN(T22)),$A:$A,0),$C22+COLUMN($E22)+1),TRUE),INDIRECT(ADDRESS(ROW(T22),$C22+COLUMN($E22)),TRUE),INDIRECT(ADDRESS(MATCH("START"&OFFSET(T22,0,COLUMN($B22)-COLUMN(T22)),$A:$A,0),COLUMN(T22))&":"&ADDRESS(MATCH("END"&OFFSET(T22,0,COLUMN($B22)-COLUMN(T22)),$A:$A,0),COLUMN(T22)),TRUE))))) -> 0 | U22: =IF(OFFSET(U22,ROW(U$2)-ROW(U22),0)="TT",SUMIF(INDIRECT(ADDRESS(2,COLUMN($Q22)+1) & ":" & ADDRESS(2,COLUMN(U22)-1),TRUE),"TBE",INDIRECT(ADDRESS(ROW(U22), COLUMN($Q22)+1) & ":" & ADDRESS(ROW(U22),COLUMN(U22)-1),TRUE)),IF(OFFSET(U22,ROW(U$2)-ROW(U22),0)="TBE",SUMIF(INDIRECT(ADDRESS(2,MATCH(INT(OFFSET(U22,ROW(U$2)-ROW(U22),-2)),$2:$2,0)) & ":" & ADDRESS(2,COLUMN(U22)-1),TRUE),"T",INDIRECT(ADDRESS(ROW(U22), MATCH(INT(OFFSET(U22,ROW(U$2)-ROW(U22),-2)),$2:$2,0)) & ":" & ADDRESS(ROW(U22),COLUMN(U22)-1),TRUE)),IF(OFFSET(U22,0,COLUMN($M22)-COLUMN(U22))="V",OFFSET(U22,0,-2)*OFFSET(U22,0,-1),"TOTAL"))) -> 0
A23: =IF(ISNUMBER(OFFSET(A23,0,12)),"START",IF(AND(OFFSET(A23,0,2)=0,OFFSET(A23,0,4)="GT"),"END",""))&OFFSET(A23,0,1) -> WP001 | B23: =IF(ISNUMBER(OFFSET(B23,0,11)),"WP" & TEXT(OFFSET(B23,0,11),"000"),OFFSET(B23,-1,0)) -> WP001 | C23: 6 | D23: WPRow.N | J23: TC | K23: T3 | M23: T | P23: C.1 Travel and subsistence per travel or day | T23: =IF(OFFSET(T23,ROW(T$2)-ROW(T23),0)="TT","TT",IF(OFFSET(T23,0,COLUMN($M23)-COLUMN(T23))="%",ROUND((OFFSET(T23,-2,0)-OFFSET(T23,-21,0))*0.07,2),IF(OFFSET(T23,0,COLUMN($M23)-COLUMN(T23))="V",ROUND(OFFSET(T23,0,-2)*OFFSET(T23,0,-1),2),SUMIF(INDIRECT(ADDRESS(MATCH("START"&OFFSET(T23,0,COLUMN($B23)-COLUMN(T23)),$A:$A,0),$C23+COLUMN($E23)+1)&":"&ADDRESS(MATCH("END"&OFFSET(T23,0,COLUMN($B23)-COLUMN(T23)),$A:$A,0),$C23+COLUMN($E23)+1),TRUE),INDIRECT(ADDRESS(ROW(T23),$C23+COLUMN($E23)),TRUE),INDIRECT(ADDRESS(MATCH("START"&OFFSET(T23,0,COLUMN($B23)-COLUMN(T23)),$A:$A,0),COLUMN(T23))&":"&ADDRESS(MATCH("END"&OFFSET(T23,0,COLUMN($B23)-COLUMN(T23)),$A:$A,0),COLUMN(T23)),TRUE))))) -> 0 | U23: =IF(OFFSET(U23,ROW(U$2)-ROW(U23),0)="TT",SUMIF(INDIRECT(ADDRESS(2,COLUMN($Q23)+1) & ":" & ADDRESS(2,COLUMN(U23)-1),TRUE),"TBE",INDIRECT(ADDRESS(ROW(U23), COLUMN($Q23)+1) & ":" & ADDRESS(ROW(U23),COLUMN(U23)-1),TRUE)),IF(OFFSET(U23,ROW(U$2)-ROW(U23),0)="TBE",SUMIF(INDIRECT(ADDRESS(2,MATCH(INT(OFFSET(U23,ROW(U$2)-ROW(U23),-2)),$2:$2,0)) & ":" & ADDRESS(2,COLUMN(U23)-1),TRUE),"T",INDIRECT(ADDRESS(ROW(U23), MATCH(INT(OFFSET(U23,ROW(U$2)-ROW(U23),-2)),$2:$2,0)) & ":" & ADDRESS(ROW(U23),COLUMN(U23)-1),TRUE)),IF(OFFSET(U23,0,COLUMN($M23)-COLUMN(U23))="V",OFFSET(U23,0,-2)*OFFSET(U23,0,-1),"TOTAL"))) -> 0
A24: =IF(ISNUMBER(OFFSET(A24,0,12)),"START",IF(AND(OFFSET(A24,0,2)=0,OFFSET(A24,0,4)="GT"),"END",""))&OFFSET(A24,0,1) -> WP001 | B24: =IF(ISNUMBER(OFFSET(B24,0,11)),"WP" & TEXT(OFFSET(B24,0,11),"000"),OFFSET(B24,-1,0)) -> WP001 | C24: 7 | D24: WPRow.O | L24: T3 | M24: V | Q24: Travel | T24: =IF(OFFSET(T24,ROW(T$2)-ROW(T24),0)="TT","TT",IF(OFFSET(T24,0,COLUMN($M24)-COLUMN(T24))="%",ROUND((OFFSET(T24,-2,0)-OFFSET(T24,-21,0))*0.07,2),IF(OFFSET(T24,0,COLUMN($M24)-COLUMN(T24))="V",ROUND(OFFSET(T24,0,-2)*OFFSET(T24,0,-1),2),SUMIF(INDIRECT(ADDRESS(MATCH("START"&OFFSET(T24,0,COLUMN($B24)-COLUMN(T24)),$A:$A,0),$C24+COLUMN($E24)+1)&":"&ADDRESS(MATCH("END"&OFFSET(T24,0,COLUMN($B24)-COLUMN(T24)),$A:$A,0),$C24+COLUMN($E24)+1),TRUE),INDIRECT(ADDRESS(ROW(T24),$C24+COLUMN($E24)),TRUE),INDIRECT(ADDRESS(MATCH("START"&OFFSET(T24,0,COLUMN($B24)-COLUMN(T24)),$A:$A,0),COLUMN(T24))&":"&ADDRESS(MATCH("END"&OFFSET(T24,0,COLUMN($B24)-COLUMN(T24)),$A:$A,0),COLUMN(T24)),TRUE))))) -> 0 | U24: =IF(OFFSET(U24,ROW(U$2)-ROW(U24),0)="TT",SUMIF(INDIRECT(ADDRESS(2,COLUMN($Q24)+1) & ":" & ADDRESS(2,COLUMN(U24)-1),TRUE),"TBE",INDIRECT(ADDRESS(ROW(U24), COLUMN($Q24)+1) & ":" & ADDRESS(ROW(U24),COLUMN(U24)-1),TRUE)),IF(OFFSET(U24,ROW(U$2)-ROW(U24),0)="TBE",SUMIF(INDIRECT(ADDRESS(2,MATCH(INT(OFFSET(U24,ROW(U$2)-ROW(U24),-2)),$2:$2,0)) & ":" & ADDRESS(2,COLUMN(U24)-1),TRUE),"T",INDIRECT(ADDRESS(ROW(U24), MATCH(INT(OFFSET(U24,ROW(U$2)-ROW(U24),-2)),$2:$2,0)) & ":" & ADDRESS(ROW(U24),COLUMN(U24)-1),TRUE)),IF(OFFSET(U24,0,COLUMN($M24)-COLUMN(U24))="V",OFFSET(U24,0,-2)*OFFSET(U24,0,-1),"TOTAL"))) -> 0
A25: =IF(ISNUMBER(OFFSET(A25,0,12)),"START",IF(AND(OFFSET(A25,0,2)=0,OFFSET(A25,0,4)="GT"),"END",""))&OFFSET(A25,0,1) -> WP001 | B25: =IF(ISNUMBER(OFFSET(B25,0,11)),"WP" & TEXT(OFFSET(B25,0,11),"000"),OFFSET(B25,-1,0)) -> WP001 | C25: 7 | D25: WPRow.P | L25: T3 | M25: V | Q25: Accommodation | T25: =IF(OFFSET(T25,ROW(T$2)-ROW(T25),0)="TT","TT",IF(OFFSET(T25,0,COLUMN($M25)-COLUMN(T25))="%",ROUND((OFFSET(T25,-2,0)-OFFSET(T25,-21,0))*0.07,2),IF(OFFSET(T25,0,COLUMN($M25)-COLUMN(T25))="V",ROUND(OFFSET(T25,0,-2)*OFFSET(T25,0,-1),2),SUMIF(INDIRECT(ADDRESS(MATCH("START"&OFFSET(T25,0,COLUMN($B25)-COLUMN(T25)),$A:$A,0),$C25+COLUMN($E25)+1)&":"&ADDRESS(MATCH("END"&OFFSET(T25,0,COLUMN($B25)-COLUMN(T25)),$A:$A,0),$C25+COLUMN($E25)+1),TRUE),INDIRECT(ADDRESS(ROW(T25),$C25+COLUMN($E25)),TRUE),INDIRECT(ADDRESS(MATCH("START"&OFFSET(T25,0,COLUMN($B25)-COLUMN(T25)),$A:$A,0),COLUMN(T25))&":"&ADDRESS(MATCH("END"&OFFSET(T25,0,COLUMN($B25)-COLUMN(T25)),$A:$A,0),COLUMN(T25)),TRUE))))) -> 0 | U25: =IF(OFFSET(U25,ROW(U$2)-ROW(U25),0)="TT",SUMIF(INDIRECT(ADDRESS(2,COLUMN($Q25)+1) & ":" & ADDRESS(2,COLUMN(U25)-1),TRUE),"TBE",INDIRECT(ADDRESS(ROW(U25), COLUMN($Q25)+1) & ":" & ADDRESS(ROW(U25),COLUMN(U25)-1),TRUE)),IF(OFFSET(U25,ROW(U$2)-ROW(U25),0)="TBE",SUMIF(INDIRECT(ADDRESS(2,MATCH(INT(OFFSET(U25,ROW(U$2)-ROW(U25),-2)),$2:$2,0)) & ":" & ADDRESS(2,COLUMN(U25)-1),TRUE),"T",INDIRECT(ADDRESS(ROW(U25), MATCH(INT(OFFSET(U25,ROW(U$2)-ROW(U25),-2)),$2:$2,0)) & ":" & ADDRESS(ROW(U25),COLUMN(U25)-1),TRUE)),IF(OFFSET(U25,0,COLUMN($M25)-COLUMN(U25))="V",OFFSET(U25,0,-2)*OFFSET(U25,0,-1),"TOTAL"))) -> 0
A26: =IF(ISNUMBER(OFFSET(A26,0,12)),"START",IF(AND(OFFSET(A26,0,2)=0,OFFSET(A26,0,4)="GT"),"END",""))&OFFSET(A26,0,1) -> WP001 | B26: =IF(ISNUMBER(OFFSET(B26,0,11)),"WP" & TEXT(OFFSET(B26,0,11),"000"),OFFSET(B26,-1,0)) -> WP001 | C26: 7 | D26: WPRow.Q | L26: T3 | M26: V | Q26: Subsistence | T26: =IF(OFFSET(T26,ROW(T$2)-ROW(T26),0)="TT","TT",IF(OFFSET(T26,0,COLUMN($M26)-COLUMN(T26))="%",ROUND((OFFSET(T26,-2,0)-OFFSET(T26,-21,0))*0.07,2),IF(OFFSET(T26,0,COLUMN($M26)-COLUMN(T26))="V",ROUND(OFFSET(T26,0,-2)*OFFSET(T26,0,-1),2),SUMIF(INDIRECT(ADDRESS(MATCH("START"&OFFSET(T26,0,COLUMN($B26)-COLUMN(T26)),$A:$A,0),$C26+COLUMN($E26)+1)&":"&ADDRESS(MATCH("END"&OFFSET(T26,0,COLUMN($B26)-COLUMN(T26)),$A:$A,0),$C26+COLUMN($E26)+1),TRUE),INDIRECT(ADDRESS(ROW(T26),$C26+COLUMN($E26)),TRUE),INDIRECT(ADDRESS(MATCH("START"&OFFSET(T26,0,COLUMN($B26)-COLUMN(T26)),$A:$A,0),COLUMN(T26))&":"&ADDRESS(MATCH("END"&OFFSET(T26,0,COLUMN($B26)-COLUMN(T26)),$A:$A,0),COLUMN(T26)),TRUE))))) -> 0 | U26: =IF(OFFSET(U26,ROW(U$2)-ROW(U26),0)="TT",SUMIF(INDIRECT(ADDRESS(2,COLUMN($Q26)+1) & ":" & ADDRESS(2,COLUMN(U26)-1),TRUE),"TBE",INDIRECT(ADDRESS(ROW(U26), COLUMN($Q26)+1) & ":" & ADDRESS(ROW(U26),COLUMN(U26)-1),TRUE)),IF(OFFSET(U26,ROW(U$2)-ROW(U26),0)="TBE",SUMIF(INDIRECT(ADDRESS(2,MATCH(INT(OFFSET(U26,ROW(U$2)-ROW(U26),-2)),$2:$2,0)) & ":" & ADDRESS(2,COLUMN(U26)-1),TRUE),"T",INDIRECT(ADDRESS(ROW(U26), MATCH(INT(OFFSET(U26,ROW(U$2)-ROW(U26),-2)),$2:$2,0)) & ":" & ADDRESS(ROW(U26),COLUMN(U26)-1),TRUE)),IF(OFFSET(U26,0,COLUMN($M26)-COLUMN(U26))="V",OFFSET(U26,0,-2)*OFFSET(U26,0,-1),"TOTAL"))) -> 0
A27: =IF(ISNUMBER(OFFSET(A27,0,12)),"START",IF(AND(OFFSET(A27,0,2)=0,OFFSET(A27,0,4)="GT"),"END",""))&OFFSET(A27,0,1) -> WP001 | B27: =IF(ISNUMBER(OFFSET(B27,0,11)),"WP" & TEXT(OFFSET(B27,0,11),"000"),OFFSET(B27,-1,0)) -> WP001 | C27: 5 | D27: WPRow.R | J27: TC | M27: V | P27: C.2 Equipment (please refer to the Depreciation Cost sheet) | T27: =IF(OFFSET(T27,ROW(T$2)-ROW(T27),0)="TT","TT",IF(OFFSET(T27,0,COLUMN($M27)-COLUMN(T27))="%",ROUND((OFFSET(T27,-2,0)-OFFSET(T27,-21,0))*0.07,2),IF(OFFSET(T27,0,COLUMN($M27)-COLUMN(T27))="V",ROUND(OFFSET(T27,0,-2)*OFFSET(T27,0,-1),2),SUMIF(INDIRECT(ADDRESS(MATCH("START"&OFFSET(T27,0,COLUMN($B27)-COLUMN(T27)),$A:$A,0),$C27+COLUMN($E27)+1)&":"&ADDRESS(MATCH("END"&OFFSET(T27,0,COLUMN($B27)-COLUMN(T27)),$A:$A,0),$C27+COLUMN($E27)+1),TRUE),INDIRECT(ADDRESS(ROW(T27),$C27+COLUMN($E27)),TRUE),INDIRECT(ADDRESS(MATCH("START"&OFFSET(T27,0,COLUMN($B27)-COLUMN(T27)),$A:$A,0),COLUMN(T27))&":"&ADDRESS(MATCH("END"&OFFSET(T27,0,COLUMN($B27)-COLUMN(T27)),$A:$A,0),COLUMN(T27)),TRUE))))) -> 0 | U27: =IF(OFFSET(U27,ROW(U$2)-ROW(U27),0)="TT",SUMIF(INDIRECT(ADDRESS(2,COLUMN($Q27)+1) & ":" & ADDRESS(2,COLUMN(U27)-1),TRUE),"TBE",INDIRECT(ADDRESS(ROW(U27), COLUMN($Q27)+1) & ":" & ADDRESS(ROW(U27),COLUMN(U27)-1),TRUE)),IF(OFFSET(U27,ROW(U$2)-ROW(U27),0)="TBE",SUMIF(INDIRECT(ADDRESS(2,MATCH(INT(OFFSET(U27,ROW(U$2)-ROW(U27),-2)),$2:$2,0)) & ":" & ADDRESS(2,COLUMN(U27)-1),TRUE),"T",INDIRECT(ADDRESS(ROW(U27), MATCH(INT(OFFSET(U27,ROW(U$2)-ROW(U27),-2)),$2:$2,0)) & ":" & ADDRESS(ROW(U27),COLUMN(U27)-1),TRUE)),IF(OFFSET(U27,0,COLUMN($M27)-COLUMN(U27))="V",OFFSET(U27,0,-2)*OFFSET(U27,0,-1),"TOTAL"))) -> 0
A28: =IF(ISNUMBER(OFFSET(A28,0,12)),"START",IF(AND(OFFSET(A28,0,2)=0,OFFSET(A28,0,4)="GT"),"END",""))&OFFSET(A28,0,1) -> WP001 | B28: =IF(ISNUMBER(OFFSET(B28,0,11)),"WP" & TEXT(OFFSET(B28,0,11),"000"),OFFSET(B28,-1,0)) -> WP001 | C28: 6 | D28: WPRow.S | J28: TC | K28: T4 | M28: T | P28: C.3 Other goods, works and services | T28: =IF(OFFSET(T28,ROW(T$2)-ROW(T28),0)="TT","TT",IF(OFFSET(T28,0,COLUMN($M28)-COLUMN(T28))="%",ROUND((OFFSET(T28,-2,0)-OFFSET(T28,-21,0))*0.07,2),IF(OFFSET(T28,0,COLUMN($M28)-COLUMN(T28))="V",ROUND(OFFSET(T28,0,-2)*OFFSET(T28,0,-1),2),SUMIF(INDIRECT(ADDRESS(MATCH("START"&OFFSET(T28,0,COLUMN($B28)-COLUMN(T28)),$A:$A,0),$C28+COLUMN($E28)+1)&":"&ADDRESS(MATCH("END"&OFFSET(T28,0,COLUMN($B28)-COLUMN(T28)),$A:$A,0),$C28+COLUMN($E28)+1),TRUE),INDIRECT(ADDRESS(ROW(T28),$C28+COLUMN($E28)),TRUE),INDIRECT(ADDRESS(MATCH("START"&OFFSET(T28,0,COLUMN($B28)-COLUMN(T28)),$A:$A,0),COLUMN(T28))&":"&ADDRESS(MATCH("END"&OFFSET(T28,0,COLUMN($B28)-COLUMN(T28)),$A:$A,0),COLUMN(T28)),TRUE))))) -> 0 | U28: =IF(OFFSET(U28,ROW(U$2)-ROW(U28),0)="TT",SUMIF(INDIRECT(ADDRESS(2,COLUMN($Q28)+1) & ":" & ADDRESS(2,COLUMN(U28)-1),TRUE),"TBE",INDIRECT(ADDRESS(ROW(U28), COLUMN($Q28)+1) & ":" & ADDRESS(ROW(U28),COLUMN(U28)-1),TRUE)),IF(OFFSET(U28,ROW(U$2)-ROW(U28),0)="TBE",SUMIF(INDIRECT(ADDRESS(2,MATCH(INT(OFFSET(U28,ROW(U$2)-ROW(U28),-2)),$2:$2,0)) & ":" & ADDRESS(2,COLUMN(U28)-1),TRUE),"T",INDIRECT(ADDRESS(ROW(U28), MATCH(INT(OFFSET(U28,ROW(U$2)-ROW(U28),-2)),$2:$2,0)) & ":" & ADDRESS(ROW(U28),COLUMN(U28)-1),TRUE)),IF(OFFSET(U28,0,COLUMN($M28)-COLUMN(U28))="V",OFFSET(U28,0,-2)*OFFSET(U28,0,-1),"TOTAL"))) -> 0
A29: =IF(ISNUMBER(OFFSET(A29,0,12)),"START",IF(AND(OFFSET(A29,0,2)=0,OFFSET(A29,0,4)="GT"),"END",""))&OFFSET(A29,0,1) -> WP001 | B29: =IF(ISNUMBER(OFFSET(B29,0,11)),"WP" & TEXT(OFFSET(B29,0,11),"000"),OFFSET(B29,-1,0)) -> WP001 | C29: 7 | D29: WPRow.T | L29: T4 | M29: V | Q29: Consumables | T29: =IF(OFFSET(T29,ROW(T$2)-ROW(T29),0)="TT","TT",IF(OFFSET(T29,0,COLUMN($M29)-COLUMN(T29))="%",ROUND((OFFSET(T29,-2,0)-OFFSET(T29,-21,0))*0.07,2),IF(OFFSET(T29,0,COLUMN($M29)-COLUMN(T29))="V",ROUND(OFFSET(T29,0,-2)*OFFSET(T29,0,-1),2),SUMIF(INDIRECT(ADDRESS(MATCH("START"&OFFSET(T29,0,COLUMN($B29)-COLUMN(T29)),$A:$A,0),$C29+COLUMN($E29)+1)&":"&ADDRESS(MATCH("END"&OFFSET(T29,0,COLUMN($B29)-COLUMN(T29)),$A:$A,0),$C29+COLUMN($E29)+1),TRUE),INDIRECT(ADDRESS(ROW(T29),$C29+COLUMN($E29)),TRUE),INDIRECT(ADDRESS(MATCH("START"&OFFSET(T29,0,COLUMN($B29)-COLUMN(T29)),$A:$A,0),COLUMN(T29))&":"&ADDRESS(MATCH("END"&OFFSET(T29,0,COLUMN($B29)-COLUMN(T29)),$A:$A,0),COLUMN(T29)),TRUE))))) -> 0 | U29: =IF(OFFSET(U29,ROW(U$2)-ROW(U29),0)="TT",SUMIF(INDIRECT(ADDRESS(2,COLUMN($Q29)+1) & ":" & ADDRESS(2,COLUMN(U29)-1),TRUE),"TBE",INDIRECT(ADDRESS(ROW(U29), COLUMN($Q29)+1) & ":" & ADDRESS(ROW(U29),COLUMN(U29)-1),TRUE)),IF(OFFSET(U29,ROW(U$2)-ROW(U29),0)="TBE",SUMIF(INDIRECT(ADDRESS(2,MATCH(INT(OFFSET(U29,ROW(U$2)-ROW(U29),-2)),$2:$2,0)) & ":" & ADDRESS(2,COLUMN(U29)-1),TRUE),"T",INDIRECT(ADDRESS(ROW(U29), MATCH(INT(OFFSET(U29,ROW(U$2)-ROW(U29),-2)),$2:$2,0)) & ":" & ADDRESS(ROW(U29),COLUMN(U29)-1),TRUE)),IF(OFFSET(U29,0,COLUMN($M29)-COLUMN(U29))="V",OFFSET(U29,0,-2)*OFFSET(U29,0,-1),"TOTAL"))) -> 0
A30: =IF(ISNUMBER(OFFSET(A30,0,12)),"START",IF(AND(OFFSET(A30,0,2)=0,OFFSET(A30,0,4)="GT"),"END",""))&OFFSET(A30,0,1) -> WP001 | B30: =IF(ISNUMBER(OFFSET(B30,0,11)),"WP" & TEXT(OFFSET(B30,0,11),"000"),OFFSET(B30,-1,0)) -> WP001 | C30: 7 | D30: WPRow.U | L30: T4 | M30: V | Q30: Services for Meetings, Seminars | T30: =IF(OFFSET(T30,ROW(T$2)-ROW(T30),0)="TT","TT",IF(OFFSET(T30,0,COLUMN($M30)-COLUMN(T30))="%",ROUND((OFFSET(T30,-2,0)-OFFSET(T30,-21,0))*0.07,2),IF(OFFSET(T30,0,COLUMN($M30)-COLUMN(T30))="V",ROUND(OFFSET(T30,0,-2)*OFFSET(T30,0,-1),2),SUMIF(INDIRECT(ADDRESS(MATCH("START"&OFFSET(T30,0,COLUMN($B30)-COLUMN(T30)),$A:$A,0),$C30+COLUMN($E30)+1)&":"&ADDRESS(MATCH("END"&OFFSET(T30,0,COLUMN($B30)-COLUMN(T30)),$A:$A,0),$C30+COLUMN($E30)+1),TRUE),INDIRECT(ADDRESS(ROW(T30),$C30+COLUMN($E30)),TRUE),INDIRECT(ADDRESS(MATCH("START"&OFFSET(T30,0,COLUMN($B30)-COLUMN(T30)),$A:$A,0),COLUMN(T30))&":"&ADDRESS(MATCH("END"&OFFSET(T30,0,COLUMN($B30)-COLUMN(T30)),$A:$A,0),COLUMN(T30)),TRUE))))) -> 0 | U30: =IF(OFFSET(U30,ROW(U$2)-ROW(U30),0)="TT",SUMIF(INDIRECT(ADDRESS(2,COLUMN($Q30)+1) & ":" & ADDRESS(2,COLUMN(U30)-1),TRUE),"TBE",INDIRECT(ADDRESS(ROW(U30), COLUMN($Q30)+1) & ":" & ADDRESS(ROW(U30),COLUMN(U30)-1),TRUE)),IF(OFFSET(U30,ROW(U$2)-ROW(U30),0)="TBE",SUMIF(INDIRECT(ADDRESS(2,MATCH(INT(OFFSET(U30,ROW(U$2)-ROW(U30),-2)),$2:$2,0)) & ":" & ADDRESS(2,COLUMN(U30)-1),TRUE),"T",INDIRECT(ADDRESS(ROW(U30), MATCH(INT(OFFSET(U30,ROW(U$2)-ROW(U30),-2)),$2:$2,0)) & ":" & ADDRESS(ROW(U30),COLUMN(U30)-1),TRUE)),IF(OFFSET(U30,0,COLUMN($M30)-COLUMN(U30))="V",OFFSET(U30,0,-2)*OFFSET(U30,0,-1),"TOTAL"))) -> 0
A31: =IF(ISNUMBER(OFFSET(A31,0,12)),"START",IF(AND(OFFSET(A31,0,2)=0,OFFSET(A31,0,4)="GT"),"END",""))&OFFSET(A31,0,1) -> WP001 | B31: =IF(ISNUMBER(OFFSET(B31,0,11)),"WP" & TEXT(OFFSET(B31,0,11),"000"),OFFSET(B31,-1,0)) -> WP001 | C31: 7 | D31: WPRow.V | L31: T4 | M31: V | Q31: Services for communication/promotion/dissemination | T31: =IF(OFFSET(T31,ROW(T$2)-ROW(T31),0)="TT","TT",IF(OFFSET(T31,0,COLUMN($M31)-COLUMN(T31))="%",ROUND((OFFSET(T31,-2,0)-OFFSET(T31,-21,0))*0.07,2),IF(OFFSET(T31,0,COLUMN($M31)-COLUMN(T31))="V",ROUND(OFFSET(T31,0,-2)*OFFSET(T31,0,-1),2),SUMIF(INDIRECT(ADDRESS(MATCH("START"&OFFSET(T31,0,COLUMN($B31)-COLUMN(T31)),$A:$A,0),$C31+COLUMN($E31)+1)&":"&ADDRESS(MATCH("END"&OFFSET(T31,0,COLUMN($B31)-COLUMN(T31)),$A:$A,0),$C31+COLUMN($E31)+1),TRUE),INDIRECT(ADDRESS(ROW(T31),$C31+COLUMN($E31)),TRUE),INDIRECT(ADDRESS(MATCH("START"&OFFSET(T31,0,COLUMN($B31)-COLUMN(T31)),$A:$A,0),COLUMN(T31))&":"&ADDRESS(MATCH("END"&OFFSET(T31,0,COLUMN($B31)-COLUMN(T31)),$A:$A,0),COLUMN(T31)),TRUE))))) -> 0 | U31: =IF(OFFSET(U31,ROW(U$2)-ROW(U31),0)="TT",SUMIF(INDIRECT(ADDRESS(2,COLUMN($Q31)+1) & ":" & ADDRESS(2,COLUMN(U31)-1),TRUE),"TBE",INDIRECT(ADDRESS(ROW(U31), COLUMN($Q31)+1) & ":" & ADDRESS(ROW(U31),COLUMN(U31)-1),TRUE)),IF(OFFSET(U31,ROW(U$2)-ROW(U31),0)="TBE",SUMIF(INDIRECT(ADDRESS(2,MATCH(INT(OFFSET(U31,ROW(U$2)-ROW(U31),-2)),$2:$2,0)) & ":" & ADDRESS(2,COLUMN(U31)-1),TRUE),"T",INDIRECT(ADDRESS(ROW(U31), MATCH(INT(OFFSET(U31,ROW(U$2)-ROW(U31),-2)),$2:$2,0)) & ":" & ADDRESS(ROW(U31),COLUMN(U31)-1),TRUE)),IF(OFFSET(U31,0,COLUMN($M31)-COLUMN(U31))="V",OFFSET(U31,0,-2)*OFFSET(U31,0,-1),"TOTAL"))) -> 0
A32: =IF(ISNUMBER(OFFSET(A32,0,12)),"START",IF(AND(OFFSET(A32,0,2)=0,OFFSET(A32,0,4)="GT"),"END",""))&OFFSET(A32,0,1) -> WP001 | B32: =IF(ISNUMBER(OFFSET(B32,0,11)),"WP" & TEXT(OFFSET(B32,0,11),"000"),OFFSET(B32,-1,0)) -> WP001 | C32: 7 | D32: WPRow.W | L32: T4 | M32: V | Q32: Website | T32: =IF(OFFSET(T32,ROW(T$2)-ROW(T32),0)="TT","TT",IF(OFFSET(T32,0,COLUMN($M32)-COLUMN(T32))="%",ROUND((OFFSET(T32,-2,0)-OFFSET(T32,-21,0))*0.07,2),IF(OFFSET(T32,0,COLUMN($M32)-COLUMN(T32))="V",ROUND(OFFSET(T32,0,-2)*OFFSET(T32,0,-1),2),SUMIF(INDIRECT(ADDRESS(MATCH("START"&OFFSET(T32,0,COLUMN($B32)-COLUMN(T32)),$A:$A,0),$C32+COLUMN($E32)+1)&":"&ADDRESS(MATCH("END"&OFFSET(T32,0,COLUMN($B32)-COLUMN(T32)),$A:$A,0),$C32+COLUMN($E32)+1),TRUE),INDIRECT(ADDRESS(ROW(T32),$C32+COLUMN($E32)),TRUE),INDIRECT(ADDRESS(MATCH("START"&OFFSET(T32,0,COLUMN($B32)-COLUMN(T32)),$A:$A,0),COLUMN(T32))&":"&ADDRESS(MATCH("END"&OFFSET(T32,0,COLUMN($B32)-COLUMN(T32)),$A:$A,0),COLUMN(T32)),TRUE))))) -> 0 | U32: =IF(OFFSET(U32,ROW(U$2)-ROW(U32),0)="TT",SUMIF(INDIRECT(ADDRESS(2,COLUMN($Q32)+1) & ":" & ADDRESS(2,COLUMN(U32)-1),TRUE),"TBE",INDIRECT(ADDRESS(ROW(U32), COLUMN($Q32)+1) & ":" & ADDRESS(ROW(U32),COLUMN(U32)-1),TRUE)),IF(OFFSET(U32,ROW(U$2)-ROW(U32),0)="TBE",SUMIF(INDIRECT(ADDRESS(2,MATCH(INT(OFFSET(U32,ROW(U$2)-ROW(U32),-2)),$2:$2,0)) & ":" & ADDRESS(2,COLUMN(U32)-1),TRUE),"T",INDIRECT(ADDRESS(ROW(U32), MATCH(INT(OFFSET(U32,ROW(U$2)-ROW(U32),-2)),$2:$2,0)) & ":" & ADDRESS(ROW(U32),COLUMN(U32)-1),TRUE)),IF(OFFSET(U32,0,COLUMN($M32)-COLUMN(U32))="V",OFFSET(U32,0,-2)*OFFSET(U32,0,-1),"TOTAL"))) -> 0
A33: =IF(ISNUMBER(OFFSET(A33,0,12)),"START",IF(AND(OFFSET(A33,0,2)=0,OFFSET(A33,0,4)="GT"),"END",""))&OFFSET(A33,0,1) -> WP001 | B33: =IF(ISNUMBER(OFFSET(B33,0,11)),"WP" & TEXT(OFFSET(B33,0,11),"000"),OFFSET(B33,-1,0)) -> WP001 | C33: 7 | D33: WPRow.X | L33: T4 | M33: V | Q33: Artistic Fees | T33: =IF(OFFSET(T33,ROW(T$2)-ROW(T33),0)="TT","TT",IF(OFFSET(T33,0,COLUMN($M33)-COLUMN(T33))="%",ROUND((OFFSET(T33,-2,0)-OFFSET(T33,-21,0))*0.07,2),IF(OFFSET(T33,0,COLUMN($M33)-COLUMN(T33))="V",ROUND(OFFSET(T33,0,-2)*OFFSET(T33,0,-1),2),SUMIF(INDIRECT(ADDRESS(MATCH("START"&OFFSET(T33,0,COLUMN($B33)-COLUMN(T33)),$A:$A,0),$C33+COLUMN($E33)+1)&":"&ADDRESS(MATCH("END"&OFFSET(T33,0,COLUMN($B33)-COLUMN(T33)),$A:$A,0),$C33+COLUMN($E33)+1),TRUE),INDIRECT(ADDRESS(ROW(T33),$C33+COLUMN($E33)),TRUE),INDIRECT(ADDRESS(MATCH("START"&OFFSET(T33,0,COLUMN($B33)-COLUMN(T33)),$A:$A,0),COLUMN(T33))&":"&ADDRESS(MATCH("END"&OFFSET(T33,0,COLUMN($B33)-COLUMN(T33)),$A:$A,0),COLUMN(T33)),TRUE))))) -> 0 | U33: =IF(OFFSET(U33,ROW(U$2)-ROW(U33),0)="TT",SUMIF(INDIRECT(ADDRESS(2,COLUMN($Q33)+1) & ":" & ADDRESS(2,COLUMN(U33)-1),TRUE),"TBE",INDIRECT(ADDRESS(ROW(U33), COLUMN($Q33)+1) & ":" & ADDRESS(ROW(U33),COLUMN(U33)-1),TRUE)),IF(OFFSET(U33,ROW(U$2)-ROW(U33),0)="TBE",SUMIF(INDIRECT(ADDRESS(2,MATCH(INT(OFFSET(U33,ROW(U$2)-ROW(U33),-2)),$2:$2,0)) & ":" & ADDRESS(2,COLUMN(U33)-1),TRUE),"T",INDIRECT(ADDRESS(ROW(U33), MATCH(INT(OFFSET(U33,ROW(U$2)-ROW(U33),-2)),$2:$2,0)) & ":" & ADDRESS(ROW(U33),COLUMN(U33)-1),TRUE)),IF(OFFSET(U33,0,COLUMN($M33)-COLUMN(U33))="V",OFFSET(U33,0,-2)*OFFSET(U33,0,-1),"TOTAL"))) -> 0
A34: =IF(ISNUMBER(OFFSET(A34,0,12)),"START",IF(AND(OFFSET(A34,0,2)=0,OFFSET(A34,0,4)="GT"),"END",""))&OFFSET(A34,0,1) -> WP001 | B34: =IF(ISNUMBER(OFFSET(B34,0,11)),"WP" & TEXT(OFFSET(B34,0,11),"000"),OFFSET(B34,-1,0)) -> WP001 | C34: 7 | D34: WPRow.Y | L34: T4 | M34: V | Q34: Other (please specify details under worksheet "Comments") | T34: =IF(OFFSET(T34,ROW(T$2)-ROW(T34),0)="TT","TT",IF(OFFSET(T34,0,COLUMN($M34)-COLUMN(T34))="%",ROUND((OFFSET(T34,-2,0)-OFFSET(T34,-21,0))*0.07,2),IF(OFFSET(T34,0,COLUMN($M34)-COLUMN(T34))="V",ROUND(OFFSET(T34,0,-2)*OFFSET(T34,0,-1),2),SUMIF(INDIRECT(ADDRESS(MATCH("START"&OFFSET(T34,0,COLUMN($B34)-COLUMN(T34)),$A:$A,0),$C34+COLUMN($E34)+1)&":"&ADDRESS(MATCH("END"&OFFSET(T34,0,COLUMN($B34)-COLUMN(T34)),$A:$A,0),$C34+COLUMN($E34)+1),TRUE),INDIRECT(ADDRESS(ROW(T34),$C34+COLUMN($E34)),TRUE),INDIRECT(ADDRESS(MATCH("START"&OFFSET(T34,0,COLUMN($B34)-COLUMN(T34)),$A:$A,0),COLUMN(T34))&":"&ADDRESS(MATCH("END"&OFFSET(T34,0,COLUMN($B34)-COLUMN(T34)),$A:$A,0),COLUMN(T34)),TRUE))))) -> 0 | U34: =IF(OFFSET(U34,ROW(U$2)-ROW(U34),0)="TT",SUMIF(INDIRECT(ADDRESS(2,COLUMN($Q34)+1) & ":" & ADDRESS(2,COLUMN(U34)-1),TRUE),"TBE",INDIRECT(ADDRESS(ROW(U34), COLUMN($Q34)+1) & ":" & ADDRESS(ROW(U34),COLUMN(U34)-1),TRUE)),IF(OFFSET(U34,ROW(U$2)-ROW(U34),0)="TBE",SUMIF(INDIRECT(ADDRESS(2,MATCH(INT(OFFSET(U34,ROW(U$2)-ROW(U34),-2)),$2:$2,0)) & ":" & ADDRESS(2,COLUMN(U34)-1),TRUE),"T",INDIRECT(ADDRESS(ROW(U34), MATCH(INT(OFFSET(U34,ROW(U$2)-ROW(U34),-2)),$2:$2,0)) & ":" & ADDRESS(ROW(U34),COLUMN(U34)-1),TRUE)),IF(OFFSET(U34,0,COLUMN($M34)-COLUMN(U34))="V",OFFSET(U34,0,-2)*OFFSET(U34,0,-1),"TOTAL"))) -> 0
A35: =IF(ISNUMBER(OFFSET(A35,0,12)),"START",IF(AND(OFFSET(A35,0,2)=0,OFFSET(A35,0,4)="GT"),"END",""))&OFFSET(A35,0,1) -> WP001 | B35: =IF(ISNUMBER(OFFSET(B35,0,11)),"WP" & TEXT(OFFSET(B35,0,11),"000"),OFFSET(B35,-1,0)) -> WP001 | C35: 4 | D35: WPRow.Z | H35: TTA | I35: TD | M35: T | O35: D. Other cost categories | T35: =IF(OFFSET(T35,ROW(T$2)-ROW(T35),0)="TT","TT",IF(OFFSET(T35,0,COLUMN($M35)-COLUMN(T35))="%",ROUND((OFFSET(T35,-2,0)-OFFSET(T35,-21,0))*0.07,2),IF(OFFSET(T35,0,COLUMN($M35)-COLUMN(T35))="V",ROUND(OFFSET(T35,0,-2)*OFFSET(T35,0,-1),2),SUMIF(INDIRECT(ADDRESS(MATCH("START"&OFFSET(T35,0,COLUMN($B35)-COLUMN(T35)),$A:$A,0),$C35+COLUMN($E35)+1)&":"&ADDRESS(MATCH("END"&OFFSET(T35,0,COLUMN($B35)-COLUMN(T35)),$A:$A,0),$C35+COLUMN($E35)+1),TRUE),INDIRECT(ADDRESS(ROW(T35),$C35+COLUMN($E35)),TRUE),INDIRECT(ADDRESS(MATCH("START"&OFFSET(T35,0,COLUMN($B35)-COLUMN(T35)),$A:$A,0),COLUMN(T35))&":"&ADDRESS(MATCH("END"&OFFSET(T35,0,COLUMN($B35)-COLUMN(T35)),$A:$A,0),COLUMN(T35)),TRUE))))) -> 0 | U35: =IF(OFFSET(U35,ROW(U$2)-ROW(U35),0)="TT",SUMIF(INDIRECT(ADDRESS(2,COLUMN($Q35)+1) & ":" & ADDRESS(2,COLUMN(U35)-1),TRUE),"TBE",INDIRECT(ADDRESS(ROW(U35), COLUMN($Q35)+1) & ":" & ADDRESS(ROW(U35),COLUMN(U35)-1),TRUE)),IF(OFFSET(U35,ROW(U$2)-ROW(U35),0)="TBE",SUMIF(INDIRECT(ADDRESS(2,MATCH(INT(OFFSET(U35,ROW(U$2)-ROW(U35),-2)),$2:$2,0)) & ":" & ADDRESS(2,COLUMN(U35)-1),TRUE),"T",INDIRECT(ADDRESS(ROW(U35), MATCH(INT(OFFSET(U35,ROW(U$2)-ROW(U35),-2)),$2:$2,0)) & ":" & ADDRESS(ROW(U35),COLUMN(U35)-1),TRUE)),IF(OFFSET(U35,0,COLUMN($M35)-COLUMN(U35))="V",OFFSET(U35,0,-2)*OFFSET(U35,0,-1),"TOTAL"))) -> 0
A36: =IF(ISNUMBER(OFFSET(A36,0,12)),"START",IF(AND(OFFSET(A36,0,2)=0,OFFSET(A36,0,4)="GT"),"END",""))&OFFSET(A36,0,1) -> WP001 | B36: =IF(ISNUMBER(OFFSET(B36,0,11)),"WP" & TEXT(OFFSET(B36,0,11),"000"),OFFSET(B36,-1,0)) -> WP001 | C36: 5 | D36: WPRow.0 | J36: TD | M36: V | P36: D.1 Financial support to third parties | T36: =IF(OFFSET(T36,ROW(T$2)-ROW(T36),0)="TT","TT",IF(OFFSET(T36,0,COLUMN($M36)-COLUMN(T36))="%",ROUND((OFFSET(T36,-2,0)-OFFSET(T36,-21,0))*0.07,2),IF(OFFSET(T36,0,COLUMN($M36)-COLUMN(T36))="V",ROUND(OFFSET(T36,0,-2)*OFFSET(T36,0,-1),2),SUMIF(INDIRECT(ADDRESS(MATCH("START"&OFFSET(T36,0,COLUMN($B36)-COLUMN(T36)),$A:$A,0),$C36+COLUMN($E36)+1)&":"&ADDRESS(MATCH("END"&OFFSET(T36,0,COLUMN($B36)-COLUMN(T36)),$A:$A,0),$C36+COLUMN($E36)+1),TRUE),INDIRECT(ADDRESS(ROW(T36),$C36+COLUMN($E36)),TRUE),INDIRECT(ADDRESS(MATCH("START"&OFFSET(T36,0,COLUMN($B36)-COLUMN(T36)),$A:$A,0),COLUMN(T36))&":"&ADDRESS(MATCH("END"&OFFSET(T36,0,COLUMN($B36)-COLUMN(T36)),$A:$A,0),COLUMN(T36)),TRUE))))) -> 0 | U36: =IF(OFFSET(U36,ROW(U$2)-ROW(U36),0)="TT",SUMIF(INDIRECT(ADDRESS(2,COLUMN($Q36)+1) & ":" & ADDRESS(2,COLUMN(U36)-1),TRUE),"TBE",INDIRECT(ADDRESS(ROW(U36), COLUMN($Q36)+1) & ":" & ADDRESS(ROW(U36),COLUMN(U36)-1),TRUE)),IF(OFFSET(U36,ROW(U$2)-ROW(U36),0)="TBE",SUMIF(INDIRECT(ADDRESS(2,MATCH(INT(OFFSET(U36,ROW(U$2)-ROW(U36),-2)),$2:$2,0)) & ":" & ADDRESS(2,COLUMN(U36)-1),TRUE),"T",INDIRECT(ADDRESS(ROW(U36), MATCH(INT(OFFSET(U36,ROW(U$2)-ROW(U36),-2)),$2:$2,0)) & ":" & ADDRESS(ROW(U36),COLUMN(U36)-1),TRUE)),IF(OFFSET(U36,0,COLUMN($M36)-COLUMN(U36))="V",OFFSET(U36,0,-2)*OFFSET(U36,0,-1),"TOTAL"))) -> 0
A37: =IF(ISNUMBER(OFFSET(A37,0,12)),"START",IF(AND(OFFSET(A37,0,2)=0,OFFSET(A37,0,4)="GT"),"END",""))&OFFSET(A37,0,1) -> WP001 | B37: =IF(ISNUMBER(OFFSET(B37,0,11)),"WP" & TEXT(OFFSET(B37,0,11),"000"),OFFSET(B37,-1,0)) -> WP001 | C37: 2 | D37: WPRow.1 | F37: GT | G37: TTA | M37: T | O37: TOTAL DIRECT COSTS INCLUDING SUBCONTRACTING (A+B+C+D) | T37: =IF(OFFSET(T37,ROW(T$2)-ROW(T37),0)="TT","TT",IF(OFFSET(T37,0,COLUMN($M37)-COLUMN(T37))="%",ROUND((OFFSET(T37,-2,0)-OFFSET(T37,-21,0))*0.07,2),IF(OFFSET(T37,0,COLUMN($M37)-COLUMN(T37))="V",ROUND(OFFSET(T37,0,-2)*OFFSET(T37,0,-1),2),SUMIF(INDIRECT(ADDRESS(MATCH("START"&OFFSET(T37,0,COLUMN($B37)-COLUMN(T37)),$A:$A,0),$C37+COLUMN($E37)+1)&":"&ADDRESS(MATCH("END"&OFFSET(T37,0,COLUMN($B37)-COLUMN(T37)),$A:$A,0),$C37+COLUMN($E37)+1),TRUE),INDIRECT(ADDRESS(ROW(T37),$C37+COLUMN($E37)),TRUE),INDIRECT(ADDRESS(MATCH("START"&OFFSET(T37,0,COLUMN($B37)-COLUMN(T37)),$A:$A,0),COLUMN(T37))&":"&ADDRESS(MATCH("END"&OFFSET(T37,0,COLUMN($B37)-COLUMN(T37)),$A:$A,0),COLUMN(T37)),TRUE))))) -> 0 | U37: =IF(OFFSET(U37,ROW(U$2)-ROW(U37),0)="TT",SUMIF(INDIRECT(ADDRESS(2,COLUMN($Q37)+1) & ":" & ADDRESS(2,COLUMN(U37)-1),TRUE),"TBE",INDIRECT(ADDRESS(ROW(U37), COLUMN($Q37)+1) & ":" & ADDRESS(ROW(U37),COLUMN(U37)-1),TRUE)),IF(OFFSET(U37,ROW(U$2)-ROW(U37),0)="TBE",SUMIF(INDIRECT(ADDRESS(2,MATCH(INT(OFFSET(U37,ROW(U$2)-ROW(U37),-2)),$2:$2,0)) & ":" & ADDRESS(2,COLUMN(U37)-1),TRUE),"T",INDIRECT(ADDRESS(ROW(U37), MATCH(INT(OFFSET(U37,ROW(U$2)-ROW(U37),-2)),$2:$2,0)) & ":" & ADDRESS(ROW(U37),COLUMN(U37)-1),TRUE)),IF(OFFSET(U37,0,COLUMN($M37)-COLUMN(U37))="V",OFFSET(U37,0,-2)*OFFSET(U37,0,-1),"TOTAL"))) -> 0
A38: =IF(ISNUMBER(OFFSET(A38,0,12)),"START",IF(AND(OFFSET(A38,0,2)=0,OFFSET(A38,0,4)="GT"),"END",""))&OFFSET(A38,0,1) -> WP001 | B38: =IF(ISNUMBER(OFFSET(B38,0,11)),"WP" & TEXT(OFFSET(B38,0,11),"000"),OFFSET(B38,-1,0)) -> WP001 | C38: 1
A39: =IF(ISNUMBER(OFFSET(A39,0,12)),"START",IF(AND(OFFSET(A39,0,2)=0,OFFSET(A39,0,4)="GT"),"END",""))&OFFSET(A39,0,1) -> WP001 | B39: =IF(ISNUMBER(OFFSET(B39,0,11)),"WP" & TEXT(OFFSET(B39,0,11),"000"),OFFSET(B39,-1,0)) -> WP001 | C39: 2 | D39: WPRow.2 | F39: GT | M39: % | O39: E. Indirect costs 7% | T39: =IF(OFFSET(T39,ROW(T$2)-ROW(T39),0)="TT","TT",IF(OFFSET(T39,0,COLUMN($M39)-COLUMN(T39))="%",ROUND((OFFSET(T39,-2,0)-OFFSET(T39,-19,0))*0.07,2),IF(OFFSET(T39,0,COLUMN($M39)-COLUMN(T39))="V",ROUND(OFFSET(T39,0,-2)*OFFSET(T39,0,-1),2),SUMIF(INDIRECT(ADDRESS(MATCH("START"&OFFSET(T39,0,COLUMN($B39)-COLUMN(T39)),$A:$A,0),$C39+COLUMN($E39)+1)&":"&ADDRESS(MATCH("END"&OFFSET(T39,0,COLUMN($B39)-COLUMN(T39)),$A:$A,0),$C39+COLUMN($E39)+1),TRUE),INDIRECT(ADDRESS(ROW(T39),$C39+COLUMN($E39)),TRUE),INDIRECT(ADDRESS(MATCH("START"&OFFSET(T39,0,COLUMN($B39)-COLUMN(T39)),$A:$A,0),COLUMN(T39))&":"&ADDRESS(MATCH("END"&OFFSET(T39,0,COLUMN($B39)-COLUMN(T39)),$A:$A,0),COLUMN(T39)),TRUE))))) -> 0 | U39: =IF(OFFSET(U39,ROW(U$2)-ROW(U39),0)="TT",SUMIF(INDIRECT(ADDRESS(2,COLUMN($Q39)+1) & ":" & ADDRESS(2,COLUMN(U39)-1),TRUE),"TBE",INDIRECT(ADDRESS(ROW(U39), COLUMN($Q39)+1) & ":" & ADDRESS(ROW(U39),COLUMN(U39)-1),TRUE)),IF(OFFSET(U39,ROW(U$2)-ROW(U39),0)="TBE",SUMIF(INDIRECT(ADDRESS(2,MATCH(INT(OFFSET(U39,ROW(U$2)-ROW(U39),-2)),$2:$2,0)) & ":" & ADDRESS(2,COLUMN(U39)-1),TRUE),"T",INDIRECT(ADDRESS(ROW(U39), MATCH(INT(OFFSET(U39,ROW(U$2)-ROW(U39),-2)),$2:$2,0)) & ":" & ADDRESS(ROW(U39),COLUMN(U39)-1),TRUE)),IF(OFFSET(U39,0,COLUMN($M39)-COLUMN(U39))="V",OFFSET(U39,0,-2)*OFFSET(U39,0,-1),"TOTAL"))) -> 0
A40: =IF(ISNUMBER(OFFSET(A40,0,12)),"START",IF(AND(OFFSET(A40,0,2)=0,OFFSET(A40,0,4)="GT"),"END",""))&OFFSET(A40,0,1) -> WP001 | B40: =IF(ISNUMBER(OFFSET(B40,0,11)),"WP" & TEXT(OFFSET(B40,0,11),"000"),OFFSET(B40,-1,0)) -> WP001 | C40: 1
A41: =IF(ISNUMBER(OFFSET(A41,0,12)),"START",IF(AND(OFFSET(A41,0,2)=0,OFFSET(A41,0,4)="GT"),"END",""))&OFFSET(A41,0,1) -> ENDWP001 | B41: =IF(ISNUMBER(OFFSET(B41,0,11)),"WP" & TEXT(OFFSET(B41,0,11),"000"),OFFSET(B41,-1,0)) -> WP001 | C41: 0 | D41: WPRow.3 | E41: GT | M41: T | O41: ="TOTAL COSTS (A+B+C+D+E) - " & OFFSET(O41,-26,0) -> TOTAL COSTS (A+B+C+D+E) - | T41: =IF(OFFSET(T41,ROW(T$2)-ROW(T41),0)="TT","TT",IF(OFFSET(T41,0,COLUMN($M41)-COLUMN(T41))="%",ROUND((OFFSET(T41,-2,0)-OFFSET(T41,-21,0))*0.07,2),IF(OFFSET(T41,0,COLUMN($M41)-COLUMN(T41))="V",ROUND(OFFSET(T41,0,-2)*OFFSET(T41,0,-1),2),SUMIF(INDIRECT(ADDRESS(MATCH("START"&OFFSET(T41,0,COLUMN($B41)-COLUMN(T41)),$A:$A,0),$C41+COLUMN($E41)+1)&":"&ADDRESS(MATCH("END"&OFFSET(T41,0,COLUMN($B41)-COLUMN(T41)),$A:$A,0),$C41+COLUMN($E41)+1),TRUE),INDIRECT(ADDRESS(ROW(T41),$C41+COLUMN($E41)),TRUE),INDIRECT(ADDRESS(MATCH("START"&OFFSET(T41,0,COLUMN($B41)-COLUMN(T41)),$A:$A,0),COLUMN(T41))&":"&ADDRESS(MATCH("END"&OFFSET(T41,0,COLUMN($B41)-COLUMN(T41)),$A:$A,0),COLUMN(T41)),TRUE))))) -> 0 | U41: =IF(OFFSET(U41,ROW(U$2)-ROW(U41),0)="TT",SUMIF(INDIRECT(ADDRESS(2,COLUMN($Q41)+1) & ":" & ADDRESS(2,COLUMN(U41)-1),TRUE),"TBE",INDIRECT(ADDRESS(ROW(U41), COLUMN($Q41)+1) & ":" & ADDRESS(ROW(U41),COLUMN(U41)-1),TRUE)),IF(OFFSET(U41,ROW(U$2)-ROW(U41),0)="TBE",SUMIF(INDIRECT(ADDRESS(2,MATCH(INT(OFFSET(U41,ROW(U$2)-ROW(U41),-2)),$2:$2,0)) & ":" & ADDRESS(2,COLUMN(U41)-1),TRUE),"T",INDIRECT(ADDRESS(ROW(U41), MATCH(INT(OFFSET(U41,ROW(U$2)-ROW(U41),-2)),$2:$2,0)) & ":" & ADDRESS(ROW(U41),COLUMN(U41)-1),TRUE)),IF(OFFSET(U41,0,COLUMN($M41)-COLUMN(U41))="V",OFFSET(U41,0,-2)*OFFSET(U41,0,-1),"TOTAL"))) -> 0
A43: =IF(ISNUMBER(OFFSET(A43,0,13)),"START",IF(AND(OFFSET(A43,0,2)=0,OFFSET(A43,0,4)="GT"),"END",""))&OFFSET(A43,0,1) -> STARTWP002 | B43: =IF(ISNUMBER(OFFSET(B43,0,12)),"WP" & TEXT(OFFSET(B43,0,12),"000"),OFFSET(B43,-1,0)) -> WP002 | N43: 2 | O43: =""&VLOOKUP(OFFSET(N43,1,0),'Work Packages List'!A:B,2,FALSE)
A44: =IF(ISNUMBER(OFFSET(A44,0,12)),"START",IF(AND(OFFSET(A44,0,2)=0,OFFSET(A44,0,4)="GT"),"END",""))&OFFSET(A44,0,1) -> WP002 | B44: =IF(ISNUMBER(OFFSET(B44,0,11)),"WP" & TEXT(OFFSET(B44,0,11),"000"),OFFSET(B44,-1,0)) -> WP002 | C44: 4 | D44: WPRow.A | H44: TTA | I44: TA | M44: T | N44: ="WP " & TEXT(OFFSET(N44,-1,0),"000") -> WP 002 | O44: A. DIRECT PERSONNEL COSTS | R44: =IF(OFFSET(R44,ROW(R$2)-ROW(R44),0)="TT","TT",IF(OFFSET(R44,0,COLUMN($M44)-COLUMN(R44))="%",ROUND(OFFSET(R44,-2,0)*0.07,0),IF(OFFSET(R44,0,COLUMN($M44)-COLUMN(R44))="V","x",SUMIF(INDIRECT(ADDRESS(MATCH("START"&OFFSET(R44,0,COLUMN($B44)-COLUMN(R44)),$A:$A,0),$C44+COLUMN($E44)+1)&":"&ADDRESS(MATCH("END"&OFFSET(R44,0,COLUMN($B44)-COLUMN(R44)),$A:$A,0),$C44+COLUMN($E44)+1),TRUE),INDIRECT(ADDRESS(ROW(R44),$C44+COLUMN($E44)),TRUE),INDIRECT(ADDRESS(MATCH("START"&OFFSET(R44,0,COLUMN($B44)-COLUMN(R44)),$A:$A,0),COLUMN(R44))&":"&ADDRESS(MATCH("END"&OFFSET(R44,0,COLUMN($B44)-COLUMN(R44)),$A:$A,0),COLUMN(R44)),TRUE))))) -> 0 | T44: =IF(OFFSET(T44,ROW(T$2)-ROW(T44),0)="TT","TT",IF(OFFSET(T44,0,COLUMN($M44)-COLUMN(T44))="%",ROUND((OFFSET(T44,-2,0)-OFFSET(T44,-21,0))*0.07,2),IF(OFFSET(T44,0,COLUMN($M44)-COLUMN(T44))="V",ROUND(OFFSET(T44,0,-2)*OFFSET(T44,0,-1),2),SUMIF(INDIRECT(ADDRESS(MATCH("START"&OFFSET(T44,0,COLUMN($B44)-COLUMN(T44)),$A:$A,0),$C44+COLUMN($E44)+1)&":"&ADDRESS(MATCH("END"&OFFSET(T44,0,COLUMN($B44)-COLUMN(T44)),$A:$A,0),$C44+COLUMN($E44)+1),TRUE),INDIRECT(ADDRESS(ROW(T44),$C44+COLUMN($E44)),TRUE),INDIRECT(ADDRESS(MATCH("START"&OFFSET(T44,0,COLUMN($B44)-COLUMN(T44)),$A:$A,0),COLUMN(T44))&":"&ADDRESS(MATCH("END"&OFFSET(T44,0,COLUMN($B44)-COLUMN(T44)),$A:$A,0),COLUMN(T44)),TRUE))))) -> 0 | U44: =IF(OFFSET(U44,ROW(U$2)-ROW(U44),0)="TT",SUMIF(INDIRECT(ADDRESS(2,COLUMN($Q44)+1) & ":" & ADDRESS(2,COLUMN(U44)-1),TRUE),"TBE",INDIRECT(ADDRESS(ROW(U44), COLUMN($Q44)+1) & ":" & ADDRESS(ROW(U44),COLUMN(U44)-1),TRUE)),IF(OFFSET(U44,ROW(U$2)-ROW(U44),0)="TBE",SUMIF(INDIRECT(ADDRESS(2,MATCH(INT(OFFSET(U44,ROW(U$2)-ROW(U44),-2)),$2:$2,0)) & ":" & ADDRESS(2,COLUMN(U44)-1),TRUE),"T",INDIRECT(ADDRESS(ROW(U44), MATCH(INT(OFFSET(U44,ROW(U$2)-ROW(U44),-2)),$2:$2,0)) & ":" & ADDRESS(ROW(U44),COLUMN(U44)-1),TRUE)),IF(OFFSET(U44,0,COLUMN($M44)-COLUMN(U44))="V",OFFSET(U44,0,-2)*OFFSET(U44,0,-1),"TOTAL"))) -> 0
A45: =IF(ISNUMBER(OFFSET(A45,0,12)),"START",IF(AND(OFFSET(A45,0,2)=0,OFFSET(A45,0,4)="GT"),"END",""))&OFFSET(A45,0,1) -> WP002 | B45: =IF(ISNUMBER(OFFSET(B45,0,11)),"WP" & TEXT(OFFSET(B45,0,11),"000"),OFFSET(B45,-1,0)) -> WP002 | C45: 6 | D45: WPRow.B | J45: TA | K45: T1 | M45: T | P45: A1. Employees (or equivalent) person months | R45: =IF(OFFSET(R45,ROW(R$2)-ROW(R45),0)="TT","TT",IF(OFFSET(R45,0,COLUMN($M45)-COLUMN(R45))="%",ROUND(OFFSET(R45,-2,0)*0.07,0),IF(OFFSET(R45,0,COLUMN($M45)-COLUMN(R45))="V","x",SUMIF(INDIRECT(ADDRESS(MATCH("START"&OFFSET(R45,0,COLUMN($B45)-COLUMN(R45)),$A:$A,0),$C45+COLUMN($E45)+1)&":"&ADDRESS(MATCH("END"&OFFSET(R45,0,COLUMN($B45)-COLUMN(R45)),$A:$A,0),$C45+COLUMN($E45)+1),TRUE),INDIRECT(ADDRESS(ROW(R45),$C45+COLUMN($E45)),TRUE),INDIRECT(ADDRESS(MATCH("START"&OFFSET(R45,0,COLUMN($B45)-COLUMN(R45)),$A:$A,0),COLUMN(R45))&":"&ADDRESS(MATCH("END"&OFFSET(R45,0,COLUMN($B45)-COLUMN(R45)),$A:$A,0),COLUMN(R45)),TRUE))))) -> 0 | T45: =IF(OFFSET(T45,ROW(T$2)-ROW(T45),0)="TT","TT",IF(OFFSET(T45,0,COLUMN($M45)-COLUMN(T45))="%",ROUND((OFFSET(T45,-2,0)-OFFSET(T45,-21,0))*0.07,2),IF(OFFSET(T45,0,COLUMN($M45)-COLUMN(T45))="V",ROUND(OFFSET(T45,0,-2)*OFFSET(T45,0,-1),2),SUMIF(INDIRECT(ADDRESS(MATCH("START"&OFFSET(T45,0,COLUMN($B45)-COLUMN(T45)),$A:$A,0),$C45+COLUMN($E45)+1)&":"&ADDRESS(MATCH("END"&OFFSET(T45,0,COLUMN($B45)-COLUMN(T45)),$A:$A,0),$C45+COLUMN($E45)+1),TRUE),INDIRECT(ADDRESS(ROW(T45),$C45+COLUMN($E45)),TRUE),INDIRECT(ADDRESS(MATCH("START"&OFFSET(T45,0,COLUMN($B45)-COLUMN(T45)),$A:$A,0),COLUMN(T45))&":"&ADDRESS(MATCH("END"&OFFSET(T45,0,COLUMN($B45)-COLUMN(T45)),$A:$A,0),COLUMN(T45)),TRUE))))) -> 0 | U45: =IF(OFFSET(U45,ROW(U$2)-ROW(U45),0)="TT",SUMIF(INDIRECT(ADDRESS(2,COLUMN($Q45)+1) & ":" & ADDRESS(2,COLUMN(U45)-1),TRUE),"TBE",INDIRECT(ADDRESS(ROW(U45), COLUMN($Q45)+1) & ":" & ADDRESS(ROW(U45),COLUMN(U45)-1),TRUE)),IF(OFFSET(U45,ROW(U$2)-ROW(U45),0)="TBE",SUMIF(INDIRECT(ADDRESS(2,MATCH(INT(OFFSET(U45,ROW(U$2)-ROW(U45),-2)),$2:$2,0)) & ":" & ADDRESS(2,COLUMN(U45)-1),TRUE),"T",INDIRECT(ADDRESS(ROW(U45), MATCH(INT(OFFSET(U45,ROW(U$2)-ROW(U45),-2)),$2:$2,0)) & ":" & ADDRESS(ROW(U45),COLUMN(U45)-1),TRUE)),IF(OFFSET(U45,0,COLUMN($M45)-COLUMN(U45))="V",OFFSET(U45,0,-2)*OFFSET(U45,0,-1),"TOTAL"))) -> 0
A46: =IF(ISNUMBER(OFFSET(A46,0,12)),"START",IF(AND(OFFSET(A46,0,2)=0,OFFSET(A46,0,4)="GT"),"END",""))&OFFSET(A46,0,1) -> WP002 | B46: =IF(ISNUMBER(OFFSET(B46,0,11)),"WP" & TEXT(OFFSET(B46,0,11),"000"),OFFSET(B46,-1,0)) -> WP002 | C46: 7 | D46: WPRow.C | L46: T1 | M46: V | Q46: =EMP_TYPE1 -> Type 1 | T46: =IF(OFFSET(T46,ROW(T$2)-ROW(T46),0)="TT","TT",IF(OFFSET(T46,0,COLUMN($M46)-COLUMN(T46))="%",ROUND((OFFSET(T46,-2,0)-OFFSET(T46,-21,0))*0.07,2),IF(OFFSET(T46,0,COLUMN($M46)-COLUMN(T46))="V",ROUND(OFFSET(T46,0,-2)*OFFSET(T46,0,-1),2),SUMIF(INDIRECT(ADDRESS(MATCH("START"&OFFSET(T46,0,COLUMN($B46)-COLUMN(T46)),$A:$A,0),$C46+COLUMN($E46)+1)&":"&ADDRESS(MATCH("END"&OFFSET(T46,0,COLUMN($B46)-COLUMN(T46)),$A:$A,0),$C46+COLUMN($E46)+1),TRUE),INDIRECT(ADDRESS(ROW(T46),$C46+COLUMN($E46)),TRUE),INDIRECT(ADDRESS(MATCH("START"&OFFSET(T46,0,COLUMN($B46)-COLUMN(T46)),$A:$A,0),COLUMN(T46))&":"&ADDRESS(MATCH("END"&OFFSET(T46,0,COLUMN($B46)-COLUMN(T46)),$A:$A,0),COLUMN(T46)),TRUE))))) -> 0 | U46: =IF(OFFSET(U46,ROW(U$2)-ROW(U46),0)="TT",SUMIF(INDIRECT(ADDRESS(2,COLUMN($Q46)+1) & ":" & ADDRESS(2,COLUMN(U46)-1),TRUE),"TBE",INDIRECT(ADDRESS(ROW(U46), COLUMN($Q46)+1) & ":" & ADDRESS(ROW(U46),COLUMN(U46)-1),TRUE)),IF(OFFSET(U46,ROW(U$2)-ROW(U46),0)="TBE",SUMIF(INDIRECT(ADDRESS(2,MATCH(INT(OFFSET(U46,ROW(U$2)-ROW(U46),-2)),$2:$2,0)) & ":" & ADDRESS(2,COLUMN(U46)-1),TRUE),"T",INDIRECT(ADDRESS(ROW(U46), MATCH(INT(OFFSET(U46,ROW(U$2)-ROW(U46),-2)),$2:$2,0)) & ":" & ADDRESS(ROW(U46),COLUMN(U46)-1),TRUE)),IF(OFFSET(U46,0,COLUMN($M46)-COLUMN(U46))="V",OFFSET(U46,0,-2)*OFFSET(U46,0,-1),"TOTAL"))) -> 0
A47: =IF(ISNUMBER(OFFSET(A47,0,12)),"START",IF(AND(OFFSET(A47,0,2)=0,OFFSET(A47,0,4)="GT"),"END",""))&OFFSET(A47,0,1) -> WP002 | B47: =IF(ISNUMBER(OFFSET(B47,0,11)),"WP" & TEXT(OFFSET(B47,0,11),"000"),OFFSET(B47,-1,0)) -> WP002 | C47: 7 | D47: WPRow.D | L47: T1 | M47: V | Q47: =EMP_TYPE2 -> Type 2 | T47: =IF(OFFSET(T47,ROW(T$2)-ROW(T47),0)="TT","TT",IF(OFFSET(T47,0,COLUMN($M47)-COLUMN(T47))="%",ROUND((OFFSET(T47,-2,0)-OFFSET(T47,-21,0))*0.07,2),IF(OFFSET(T47,0,COLUMN($M47)-COLUMN(T47))="V",ROUND(OFFSET(T47,0,-2)*OFFSET(T47,0,-1),2),SUMIF(INDIRECT(ADDRESS(MATCH("START"&OFFSET(T47,0,COLUMN($B47)-COLUMN(T47)),$A:$A,0),$C47+COLUMN($E47)+1)&":"&ADDRESS(MATCH("END"&OFFSET(T47,0,COLUMN($B47)-COLUMN(T47)),$A:$A,0),$C47+COLUMN($E47)+1),TRUE),INDIRECT(ADDRESS(ROW(T47),$C47+COLUMN($E47)),TRUE),INDIRECT(ADDRESS(MATCH("START"&OFFSET(T47,0,COLUMN($B47)-COLUMN(T47)),$A:$A,0),COLUMN(T47))&":"&ADDRESS(MATCH("END"&OFFSET(T47,0,COLUMN($B47)-COLUMN(T47)),$A:$A,0),COLUMN(T47)),TRUE))))) -> 0 | U47: =IF(OFFSET(U47,ROW(U$2)-ROW(U47),0)="TT",SUMIF(INDIRECT(ADDRESS(2,COLUMN($Q47)+1) & ":" & ADDRESS(2,COLUMN(U47)-1),TRUE),"TBE",INDIRECT(ADDRESS(ROW(U47), COLUMN($Q47)+1) & ":" & ADDRESS(ROW(U47),COLUMN(U47)-1),TRUE)),IF(OFFSET(U47,ROW(U$2)-ROW(U47),0)="TBE",SUMIF(INDIRECT(ADDRESS(2,MATCH(INT(OFFSET(U47,ROW(U$2)-ROW(U47),-2)),$2:$2,0)) & ":" & ADDRESS(2,COLUMN(U47)-1),TRUE),"T",INDIRECT(ADDRESS(ROW(U47), MATCH(INT(OFFSET(U47,ROW(U$2)-ROW(U47),-2)),$2:$2,0)) & ":" & ADDRESS(ROW(U47),COLUMN(U47)-1),TRUE)),IF(OFFSET(U47,0,COLUMN($M47)-COLUMN(U47))="V",OFFSET(U47,0,-2)*OFFSET(U47,0,-1),"TOTAL"))) -> 0
A48: =IF(ISNUMBER(OFFSET(A48,0,12)),"START",IF(AND(OFFSET(A48,0,2)=0,OFFSET(A48,0,4)="GT"),"END",""))&OFFSET(A48,0,1) -> WP002 | B48: =IF(ISNUMBER(OFFSET(B48,0,11)),"WP" & TEXT(OFFSET(B48,0,11),"000"),OFFSET(B48,-1,0)) -> WP002 | C48: 7 | D48: WPRow.E | L48: T1 | M48: V | Q48: =EMP_TYPE3 -> Type 3 | T48: =IF(OFFSET(T48,ROW(T$2)-ROW(T48),0)="TT","TT",IF(OFFSET(T48,0,COLUMN($M48)-COLUMN(T48))="%",ROUND((OFFSET(T48,-2,0)-OFFSET(T48,-21,0))*0.07,2),IF(OFFSET(T48,0,COLUMN($M48)-COLUMN(T48))="V",ROUND(OFFSET(T48,0,-2)*OFFSET(T48,0,-1),2),SUMIF(INDIRECT(ADDRESS(MATCH("START"&OFFSET(T48,0,COLUMN($B48)-COLUMN(T48)),$A:$A,0),$C48+COLUMN($E48)+1)&":"&ADDRESS(MATCH("END"&OFFSET(T48,0,COLUMN($B48)-COLUMN(T48)),$A:$A,0),$C48+COLUMN($E48)+1),TRUE),INDIRECT(ADDRESS(ROW(T48),$C48+COLUMN($E48)),TRUE),INDIRECT(ADDRESS(MATCH("START"&OFFSET(T48,0,COLUMN($B48)-COLUMN(T48)),$A:$A,0),COLUMN(T48))&":"&ADDRESS(MATCH("END"&OFFSET(T48,0,COLUMN($B48)-COLUMN(T48)),$A:$A,0),COLUMN(T48)),TRUE))))) -> 0 | U48: =IF(OFFSET(U48,ROW(U$2)-ROW(U48),0)="TT",SUMIF(INDIRECT(ADDRESS(2,COLUMN($Q48)+1) & ":" & ADDRESS(2,COLUMN(U48)-1),TRUE),"TBE",INDIRECT(ADDRESS(ROW(U48), COLUMN($Q48)+1) & ":" & ADDRESS(ROW(U48),COLUMN(U48)-1),TRUE)),IF(OFFSET(U48,ROW(U$2)-ROW(U48),0)="TBE",SUMIF(INDIRECT(ADDRESS(2,MATCH(INT(OFFSET(U48,ROW(U$2)-ROW(U48),-2)),$2:$2,0)) & ":" & ADDRESS(2,COLUMN(U48)-1),TRUE),"T",INDIRECT(ADDRESS(ROW(U48), MATCH(INT(OFFSET(U48,ROW(U$2)-ROW(U48),-2)),$2:$2,0)) & ":" & ADDRESS(ROW(U48),COLUMN(U48)-1),TRUE)),IF(OFFSET(U48,0,COLUMN($M48)-COLUMN(U48))="V",OFFSET(U48,0,-2)*OFFSET(U48,0,-1),"TOTAL"))) -> 0
A49: =IF(ISNUMBER(OFFSET(A49,0,12)),"START",IF(AND(OFFSET(A49,0,2)=0,OFFSET(A49,0,4)="GT"),"END",""))&OFFSET(A49,0,1) -> WP002 | B49: =IF(ISNUMBER(OFFSET(B49,0,11)),"WP" & TEXT(OFFSET(B49,0,11),"000"),OFFSET(B49,-1,0)) -> WP002 | C49: 7 | D49: WPRow.F | L49: T1 | M49: V | Q49: =EMP_TYPE4 -> Type 4 | T49: =IF(OFFSET(T49,ROW(T$2)-ROW(T49),0)="TT","TT",IF(OFFSET(T49,0,COLUMN($M49)-COLUMN(T49))="%",ROUND((OFFSET(T49,-2,0)-OFFSET(T49,-21,0))*0.07,2),IF(OFFSET(T49,0,COLUMN($M49)-COLUMN(T49))="V",ROUND(OFFSET(T49,0,-2)*OFFSET(T49,0,-1),2),SUMIF(INDIRECT(ADDRESS(MATCH("START"&OFFSET(T49,0,COLUMN($B49)-COLUMN(T49)),$A:$A,0),$C49+COLUMN($E49)+1)&":"&ADDRESS(MATCH("END"&OFFSET(T49,0,COLUMN($B49)-COLUMN(T49)),$A:$A,0),$C49+COLUMN($E49)+1),TRUE),INDIRECT(ADDRESS(ROW(T49),$C49+COLUMN($E49)),TRUE),INDIRECT(ADDRESS(MATCH("START"&OFFSET(T49,0,COLUMN($B49)-COLUMN(T49)),$A:$A,0),COLUMN(T49))&":"&ADDRESS(MATCH("END"&OFFSET(T49,0,COLUMN($B49)-COLUMN(T49)),$A:$A,0),COLUMN(T49)),TRUE))))) -> 0 | U49: =IF(OFFSET(U49,ROW(U$2)-ROW(U49),0)="TT",SUMIF(INDIRECT(ADDRESS(2,COLUMN($Q49)+1) & ":" & ADDRESS(2,COLUMN(U49)-1),TRUE),"TBE",INDIRECT(ADDRESS(ROW(U49), COLUMN($Q49)+1) & ":" & ADDRESS(ROW(U49),COLUMN(U49)-1),TRUE)),IF(OFFSET(U49,ROW(U$2)-ROW(U49),0)="TBE",SUMIF(INDIRECT(ADDRESS(2,MATCH(INT(OFFSET(U49,ROW(U$2)-ROW(U49),-2)),$2:$2,0)) & ":" & ADDRESS(2,COLUMN(U49)-1),TRUE),"T",INDIRECT(ADDRESS(ROW(U49), MATCH(INT(OFFSET(U49,ROW(U$2)-ROW(U49),-2)),$2:$2,0)) & ":" & ADDRESS(ROW(U49),COLUMN(U49)-1),TRUE)),IF(OFFSET(U49,0,COLUMN($M49)-COLUMN(U49))="V",OFFSET(U49,0,-2)*OFFSET(U49,0,-1),"TOTAL"))) -> 0
A50: =IF(ISNUMBER(OFFSET(A50,0,12)),"START",IF(AND(OFFSET(A50,0,2)=0,OFFSET(A50,0,4)="GT"),"END",""))&OFFSET(A50,0,1) -> WP002 | B50: =IF(ISNUMBER(OFFSET(B50,0,11)),"WP" & TEXT(OFFSET(B50,0,11),"000"),OFFSET(B50,-1,0)) -> WP002 | C50: 7 | D50: WPRow.G | L50: T1 | M50: V | Q50: =EMP_OTHER -> Type 5 | T50: =IF(OFFSET(T50,ROW(T$2)-ROW(T50),0)="TT","TT",IF(OFFSET(T50,0,COLUMN($M50)-COLUMN(T50))="%",ROUND((OFFSET(T50,-2,0)-OFFSET(T50,-21,0))*0.07,2),IF(OFFSET(T50,0,COLUMN($M50)-COLUMN(T50))="V",ROUND(OFFSET(T50,0,-2)*OFFSET(T50,0,-1),2),SUMIF(INDIRECT(ADDRESS(MATCH("START"&OFFSET(T50,0,COLUMN($B50)-COLUMN(T50)),$A:$A,0),$C50+COLUMN($E50)+1)&":"&ADDRESS(MATCH("END"&OFFSET(T50,0,COLUMN($B50)-COLUMN(T50)),$A:$A,0),$C50+COLUMN($E50)+1),TRUE),INDIRECT(ADDRESS(ROW(T50),$C50+COLUMN($E50)),TRUE),INDIRECT(ADDRESS(MATCH("START"&OFFSET(T50,0,COLUMN($B50)-COLUMN(T50)),$A:$A,0),COLUMN(T50))&":"&ADDRESS(MATCH("END"&OFFSET(T50,0,COLUMN($B50)-COLUMN(T50)),$A:$A,0),COLUMN(T50)),TRUE))))) -> 0 | U50: =IF(OFFSET(U50,ROW(U$2)-ROW(U50),0)="TT",SUMIF(INDIRECT(ADDRESS(2,COLUMN($Q50)+1) & ":" & ADDRESS(2,COLUMN(U50)-1),TRUE),"TBE",INDIRECT(ADDRESS(ROW(U50), COLUMN($Q50)+1) & ":" & ADDRESS(ROW(U50),COLUMN(U50)-1),TRUE)),IF(OFFSET(U50,ROW(U$2)-ROW(U50),0)="TBE",SUMIF(INDIRECT(ADDRESS(2,MATCH(INT(OFFSET(U50,ROW(U$2)-ROW(U50),-2)),$2:$2,0)) & ":" & ADDRESS(2,COLUMN(U50)-1),TRUE),"T",INDIRECT(ADDRESS(ROW(U50), MATCH(INT(OFFSET(U50,ROW(U$2)-ROW(U50),-2)),$2:$2,0)) & ":" & ADDRESS(ROW(U50),COLUMN(U50)-1),TRUE)),IF(OFFSET(U50,0,COLUMN($M50)-COLUMN(U50))="V",OFFSET(U50,0,-2)*OFFSET(U50,0,-1),"TOTAL"))) -> 0
A51: =IF(ISNUMBER(OFFSET(A51,0,12)),"START",IF(AND(OFFSET(A51,0,2)=0,OFFSET(A51,0,4)="GT"),"END",""))&OFFSET(A51,0,1) -> WP002 | B51: =IF(ISNUMBER(OFFSET(B51,0,11)),"WP" & TEXT(OFFSET(B51,0,11),"000"),OFFSET(B51,-1,0)) -> WP002 | C51: 6 | D51: WPRow.H | J51: TA | M51: V | P51: A.2 Natural persons under direct contract | T51: =IF(OFFSET(T51,ROW(T$2)-ROW(T51),0)="TT","TT",IF(OFFSET(T51,0,COLUMN($M51)-COLUMN(T51))="%",ROUND((OFFSET(T51,-2,0)-OFFSET(T51,-21,0))*0.07,2),IF(OFFSET(T51,0,COLUMN($M51)-COLUMN(T51))="V",ROUND(OFFSET(T51,0,-2)*OFFSET(T51,0,-1),2),SUMIF(INDIRECT(ADDRESS(MATCH("START"&OFFSET(T51,0,COLUMN($B51)-COLUMN(T51)),$A:$A,0),$C51+COLUMN($E51)+1)&":"&ADDRESS(MATCH("END"&OFFSET(T51,0,COLUMN($B51)-COLUMN(T51)),$A:$A,0),$C51+COLUMN($E51)+1),TRUE),INDIRECT(ADDRESS(ROW(T51),$C51+COLUMN($E51)),TRUE),INDIRECT(ADDRESS(MATCH("START"&OFFSET(T51,0,COLUMN($B51)-COLUMN(T51)),$A:$A,0),COLUMN(T51))&":"&ADDRESS(MATCH("END"&OFFSET(T51,0,COLUMN($B51)-COLUMN(T51)),$A:$A,0),COLUMN(T51)),TRUE))))) -> 0 | U51: =IF(OFFSET(U51,ROW(U$2)-ROW(U51),0)="TT",SUMIF(INDIRECT(ADDRESS(2,COLUMN($Q51)+1) & ":" & ADDRESS(2,COLUMN(U51)-1),TRUE),"TBE",INDIRECT(ADDRESS(ROW(U51), COLUMN($Q51)+1) & ":" & ADDRESS(ROW(U51),COLUMN(U51)-1),TRUE)),IF(OFFSET(U51,ROW(U$2)-ROW(U51),0)="TBE",SUMIF(INDIRECT(ADDRESS(2,MATCH(INT(OFFSET(U51,ROW(U$2)-ROW(U51),-2)),$2:$2,0)) & ":" & ADDRESS(2,COLUMN(U51)-1),TRUE),"T",INDIRECT(ADDRESS(ROW(U51), MATCH(INT(OFFSET(U51,ROW(U$2)-ROW(U51),-2)),$2:$2,0)) & ":" & ADDRESS(ROW(U51),COLUMN(U51)-1),TRUE)),IF(OFFSET(U51,0,COLUMN($M51)-COLUMN(U51))="V",OFFSET(U51,0,-2)*OFFSET(U51,0,-1),"TOTAL"))) -> 0
A52: =IF(ISNUMBER(OFFSET(A52,0,12)),"START",IF(AND(OFFSET(A52,0,2)=0,OFFSET(A52,0,4)="GT"),"END",""))&OFFSET(A52,0,1) -> WP002 | B52: =IF(ISNUMBER(OFFSET(B52,0,11)),"WP" & TEXT(OFFSET(B52,0,11),"000"),OFFSET(B52,-1,0)) -> WP002 | C52: 6 | D52: WPRow.I | J52: TA | M52: V | P52: A.3 Seconded persons | T52: =IF(OFFSET(T52,ROW(T$2)-ROW(T52),0)="TT","TT",IF(OFFSET(T52,0,COLUMN($M52)-COLUMN(T52))="%",ROUND((OFFSET(T52,-2,0)-OFFSET(T52,-21,0))*0.07,2),IF(OFFSET(T52,0,COLUMN($M52)-COLUMN(T52))="V",ROUND(OFFSET(T52,0,-2)*OFFSET(T52,0,-1),2),SUMIF(INDIRECT(ADDRESS(MATCH("START"&OFFSET(T52,0,COLUMN($B52)-COLUMN(T52)),$A:$A,0),$C52+COLUMN($E52)+1)&":"&ADDRESS(MATCH("END"&OFFSET(T52,0,COLUMN($B52)-COLUMN(T52)),$A:$A,0),$C52+COLUMN($E52)+1),TRUE),INDIRECT(ADDRESS(ROW(T52),$C52+COLUMN($E52)),TRUE),INDIRECT(ADDRESS(MATCH("START"&OFFSET(T52,0,COLUMN($B52)-COLUMN(T52)),$A:$A,0),COLUMN(T52))&":"&ADDRESS(MATCH("END"&OFFSET(T52,0,COLUMN($B52)-COLUMN(T52)),$A:$A,0),COLUMN(T52)),TRUE))))) -> 0 | U52: =IF(OFFSET(U52,ROW(U$2)-ROW(U52),0)="TT",SUMIF(INDIRECT(ADDRESS(2,COLUMN($Q52)+1) & ":" & ADDRESS(2,COLUMN(U52)-1),TRUE),"TBE",INDIRECT(ADDRESS(ROW(U52), COLUMN($Q52)+1) & ":" & ADDRESS(ROW(U52),COLUMN(U52)-1),TRUE)),IF(OFFSET(U52,ROW(U$2)-ROW(U52),0)="TBE",SUMIF(INDIRECT(ADDRESS(2,MATCH(INT(OFFSET(U52,ROW(U$2)-ROW(U52),-2)),$2:$2,0)) & ":" & ADDRESS(2,COLUMN(U52)-1),TRUE),"T",INDIRECT(ADDRESS(ROW(U52), MATCH(INT(OFFSET(U52,ROW(U$2)-ROW(U52),-2)),$2:$2,0)) & ":" & ADDRESS(ROW(U52),COLUMN(U52)-1),TRUE)),IF(OFFSET(U52,0,COLUMN($M52)-COLUMN(U52))="V",OFFSET(U52,0,-2)*OFFSET(U52,0,-1),"TOTAL"))) -> 0
A53: =IF(ISNUMBER(OFFSET(A53,0,12)),"START",IF(AND(OFFSET(A53,0,2)=0,OFFSET(A53,0,4)="GT"),"END",""))&OFFSET(A53,0,1) -> WP002 | B53: =IF(ISNUMBER(OFFSET(B53,0,11)),"WP" & TEXT(OFFSET(B53,0,11),"000"),OFFSET(B53,-1,0)) -> WP002 | C53: 6 | D53: WPRow.J | J53: TA | M53: V | P53: A.4 SME Owners without salary | T53: =IF(OFFSET(T53,ROW(T$2)-ROW(T53),0)="TT","TT",IF(OFFSET(T53,0,COLUMN($M53)-COLUMN(T53))="%",ROUND((OFFSET(T53,-2,0)-OFFSET(T53,-21,0))*0.07,2),IF(OFFSET(T53,0,COLUMN($M53)-COLUMN(T53))="V",ROUND(OFFSET(T53,0,-2)*OFFSET(T53,0,-1),2),SUMIF(INDIRECT(ADDRESS(MATCH("START"&OFFSET(T53,0,COLUMN($B53)-COLUMN(T53)),$A:$A,0),$C53+COLUMN($E53)+1)&":"&ADDRESS(MATCH("END"&OFFSET(T53,0,COLUMN($B53)-COLUMN(T53)),$A:$A,0),$C53+COLUMN($E53)+1),TRUE),INDIRECT(ADDRESS(ROW(T53),$C53+COLUMN($E53)),TRUE),INDIRECT(ADDRESS(MATCH("START"&OFFSET(T53,0,COLUMN($B53)-COLUMN(T53)),$A:$A,0),COLUMN(T53))&":"&ADDRESS(MATCH("END"&OFFSET(T53,0,COLUMN($B53)-COLUMN(T53)),$A:$A,0),COLUMN(T53)),TRUE))))) -> 0 | U53: =IF(OFFSET(U53,ROW(U$2)-ROW(U53),0)="TT",SUMIF(INDIRECT(ADDRESS(2,COLUMN($Q53)+1) & ":" & ADDRESS(2,COLUMN(U53)-1),TRUE),"TBE",INDIRECT(ADDRESS(ROW(U53), COLUMN($Q53)+1) & ":" & ADDRESS(ROW(U53),COLUMN(U53)-1),TRUE)),IF(OFFSET(U53,ROW(U$2)-ROW(U53),0)="TBE",SUMIF(INDIRECT(ADDRESS(2,MATCH(INT(OFFSET(U53,ROW(U$2)-ROW(U53),-2)),$2:$2,0)) & ":" & ADDRESS(2,COLUMN(U53)-1),TRUE),"T",INDIRECT(ADDRESS(ROW(U53), MATCH(INT(OFFSET(U53,ROW(U$2)-ROW(U53),-2)),$2:$2,0)) & ":" & ADDRESS(ROW(U53),COLUMN(U53)-1),TRUE)),IF(OFFSET(U53,0,COLUMN($M53)-COLUMN(U53))="V",OFFSET(U53,0,-2)*OFFSET(U53,0,-1),"TOTAL"))) -> 0
A54: =IF(ISNUMBER(OFFSET(A54,0,12)),"START",IF(AND(OFFSET(A54,0,2)=0,OFFSET(A54,0,4)="GT"),"END",""))&OFFSET(A54,0,1) -> WP002 | B54: =IF(ISNUMBER(OFFSET(B54,0,11)),"WP" & TEXT(OFFSET(B54,0,11),"000"),OFFSET(B54,-1,0)) -> WP002 | C54: 6 | D54: WPRow.K | J54: TA | M54: V | P54: A.5 Volunteers | T54: =IF(OFFSET(T54,ROW(T$2)-ROW(T54),0)="TT","TT",IF(OFFSET(T54,0,COLUMN($M54)-COLUMN(T54))="%",ROUND((OFFSET(T54,-2,0)-OFFSET(T54,-21,0))*0.07,2),IF(OFFSET(T54,0,COLUMN($M54)-COLUMN(T54))="V",ROUND(OFFSET(T54,0,-2)*OFFSET(T54,0,-1),2),SUMIF(INDIRECT(ADDRESS(MATCH("START"&OFFSET(T54,0,COLUMN($B54)-COLUMN(T54)),$A:$A,0),$C54+COLUMN($E54)+1)&":"&ADDRESS(MATCH("END"&OFFSET(T54,0,COLUMN($B54)-COLUMN(T54)),$A:$A,0),$C54+COLUMN($E54)+1),TRUE),INDIRECT(ADDRESS(ROW(T54),$C54+COLUMN($E54)),TRUE),INDIRECT(ADDRESS(MATCH("START"&OFFSET(T54,0,COLUMN($B54)-COLUMN(T54)),$A:$A,0),COLUMN(T54))&":"&ADDRESS(MATCH("END"&OFFSET(T54,0,COLUMN($B54)-COLUMN(T54)),$A:$A,0),COLUMN(T54)),TRUE))))) -> 0 | U54: =IF(OFFSET(U54,ROW(U$2)-ROW(U54),0)="TT",SUMIF(INDIRECT(ADDRESS(2,COLUMN($Q54)+1) & ":" & ADDRESS(2,COLUMN(U54)-1),TRUE),"TBE",INDIRECT(ADDRESS(ROW(U54), COLUMN($Q54)+1) & ":" & ADDRESS(ROW(U54),COLUMN(U54)-1),TRUE)),IF(OFFSET(U54,ROW(U$2)-ROW(U54),0)="TBE",SUMIF(INDIRECT(ADDRESS(2,MATCH(INT(OFFSET(U54,ROW(U$2)-ROW(U54),-2)),$2:$2,0)) & ":" & ADDRESS(2,COLUMN(U54)-1),TRUE),"T",INDIRECT(ADDRESS(ROW(U54), MATCH(INT(OFFSET(U54,ROW(U$2)-ROW(U54),-2)),$2:$2,0)) & ":" & ADDRESS(ROW(U54),COLUMN(U54)-1),TRUE)),IF(OFFSET(U54,0,COLUMN($M54)-COLUMN(U54))="V",OFFSET(U54,0,-2)*OFFSET(U54,0,-1),"TOTAL"))) -> 0
A55: =IF(ISNUMBER(OFFSET(A55,0,12)),"START",IF(AND(OFFSET(A55,0,2)=0,OFFSET(A55,0,4)="GT"),"END",""))&OFFSET(A55,0,1) -> WP002 | B55: =IF(ISNUMBER(OFFSET(B55,0,11)),"WP" & TEXT(OFFSET(B55,0,11),"000"),OFFSET(B55,-1,0)) -> WP002 | C55: 4 | D55: WPRow.L | H55: TTA | I55: TB | M55: V | O55: B. Subcontracting costs (please specify details under worksheet "Comments") | T55: =IF(OFFSET(T55,ROW(T$2)-ROW(T55),0)="TT","TT",IF(OFFSET(T55,0,COLUMN($M55)-COLUMN(T55))="%",ROUND((OFFSET(T55,-2,0)-OFFSET(T55,-21,0))*0.07,2),IF(OFFSET(T55,0,COLUMN($M55)-COLUMN(T55))="V",ROUND(OFFSET(T55,0,-2)*OFFSET(T55,0,-1),2),SUMIF(INDIRECT(ADDRESS(MATCH("START"&OFFSET(T55,0,COLUMN($B55)-COLUMN(T55)),$A:$A,0),$C55+COLUMN($E55)+1)&":"&ADDRESS(MATCH("END"&OFFSET(T55,0,COLUMN($B55)-COLUMN(T55)),$A:$A,0),$C55+COLUMN($E55)+1),TRUE),INDIRECT(ADDRESS(ROW(T55),$C55+COLUMN($E55)),TRUE),INDIRECT(ADDRESS(MATCH("START"&OFFSET(T55,0,COLUMN($B55)-COLUMN(T55)),$A:$A,0),COLUMN(T55))&":"&ADDRESS(MATCH("END"&OFFSET(T55,0,COLUMN($B55)-COLUMN(T55)),$A:$A,0),COLUMN(T55)),TRUE))))) -> 0 | U55: =IF(OFFSET(U55,ROW(U$2)-ROW(U55),0)="TT",SUMIF(INDIRECT(ADDRESS(2,COLUMN($Q55)+1) & ":" & ADDRESS(2,COLUMN(U55)-1),TRUE),"TBE",INDIRECT(ADDRESS(ROW(U55), COLUMN($Q55)+1) & ":" & ADDRESS(ROW(U55),COLUMN(U55)-1),TRUE)),IF(OFFSET(U55,ROW(U$2)-ROW(U55),0)="TBE",SUMIF(INDIRECT(ADDRESS(2,MATCH(INT(OFFSET(U55,ROW(U$2)-ROW(U55),-2)),$2:$2,0)) & ":" & ADDRESS(2,COLUMN(U55)-1),TRUE),"T",INDIRECT(ADDRESS(ROW(U55), MATCH(INT(OFFSET(U55,ROW(U$2)-ROW(U55),-2)),$2:$2,0)) & ":" & ADDRESS(ROW(U55),COLUMN(U55)-1),TRUE)),IF(OFFSET(U55,0,COLUMN($M55)-COLUMN(U55))="V",OFFSET(U55,0,-2)*OFFSET(U55,0,-1),"TOTAL"))) -> 0
A56: =IF(ISNUMBER(OFFSET(A56,0,12)),"START",IF(AND(OFFSET(A56,0,2)=0,OFFSET(A56,0,4)="GT"),"END",""))&OFFSET(A56,0,1) -> WP002 | B56: =IF(ISNUMBER(OFFSET(B56,0,11)),"WP" & TEXT(OFFSET(B56,0,11),"000"),OFFSET(B56,-1,0)) -> WP002 | C56: 4 | D56: WPRow.M | H56: TTA | I56: TC | M56: T | O56: C. Purchase costs | T56: =IF(OFFSET(T56,ROW(T$2)-ROW(T56),0)="TT","TT",IF(OFFSET(T56,0,COLUMN($M56)-COLUMN(T56))="%",ROUND((OFFSET(T56,-2,0)-OFFSET(T56,-21,0))*0.07,2),IF(OFFSET(T56,0,COLUMN($M56)-COLUMN(T56))="V",ROUND(OFFSET(T56,0,-2)*OFFSET(T56,0,-1),2),SUMIF(INDIRECT(ADDRESS(MATCH("START"&OFFSET(T56,0,COLUMN($B56)-COLUMN(T56)),$A:$A,0),$C56+COLUMN($E56)+1)&":"&ADDRESS(MATCH("END"&OFFSET(T56,0,COLUMN($B56)-COLUMN(T56)),$A:$A,0),$C56+COLUMN($E56)+1),TRUE),INDIRECT(ADDRESS(ROW(T56),$C56+COLUMN($E56)),TRUE),INDIRECT(ADDRESS(MATCH("START"&OFFSET(T56,0,COLUMN($B56)-COLUMN(T56)),$A:$A,0),COLUMN(T56))&":"&ADDRESS(MATCH("END"&OFFSET(T56,0,COLUMN($B56)-COLUMN(T56)),$A:$A,0),COLUMN(T56)),TRUE))))) -> 0 | U56: =IF(OFFSET(U56,ROW(U$2)-ROW(U56),0)="TT",SUMIF(INDIRECT(ADDRESS(2,COLUMN($Q56)+1) & ":" & ADDRESS(2,COLUMN(U56)-1),TRUE),"TBE",INDIRECT(ADDRESS(ROW(U56), COLUMN($Q56)+1) & ":" & ADDRESS(ROW(U56),COLUMN(U56)-1),TRUE)),IF(OFFSET(U56,ROW(U$2)-ROW(U56),0)="TBE",SUMIF(INDIRECT(ADDRESS(2,MATCH(INT(OFFSET(U56,ROW(U$2)-ROW(U56),-2)),$2:$2,0)) & ":" & ADDRESS(2,COLUMN(U56)-1),TRUE),"T",INDIRECT(ADDRESS(ROW(U56), MATCH(INT(OFFSET(U56,ROW(U$2)-ROW(U56),-2)),$2:$2,0)) & ":" & ADDRESS(ROW(U56),COLUMN(U56)-1),TRUE)),IF(OFFSET(U56,0,COLUMN($M56)-COLUMN(U56))="V",OFFSET(U56,0,-2)*OFFSET(U56,0,-1),"TOTAL"))) -> 0
A57: =IF(ISNUMBER(OFFSET(A57,0,12)),"START",IF(AND(OFFSET(A57,0,2)=0,OFFSET(A57,0,4)="GT"),"END",""))&OFFSET(A57,0,1) -> WP002 | B57: =IF(ISNUMBER(OFFSET(B57,0,11)),"WP" & TEXT(OFFSET(B57,0,11),"000"),OFFSET(B57,-1,0)) -> WP002 | C57: 6 | D57: WPRow.N | J57: TC | K57: T3 | M57: T | P57: C.1 Travel and subsistence per travel or day | T57: =IF(OFFSET(T57,ROW(T$2)-ROW(T57),0)="TT","TT",IF(OFFSET(T57,0,COLUMN($M57)-COLUMN(T57))="%",ROUND((OFFSET(T57,-2,0)-OFFSET(T57,-21,0))*0.07,2),IF(OFFSET(T57,0,COLUMN($M57)-COLUMN(T57))="V",ROUND(OFFSET(T57,0,-2)*OFFSET(T57,0,-1),2),SUMIF(INDIRECT(ADDRESS(MATCH("START"&OFFSET(T57,0,COLUMN($B57)-COLUMN(T57)),$A:$A,0),$C57+COLUMN($E57)+1)&":"&ADDRESS(MATCH("END"&OFFSET(T57,0,COLUMN($B57)-COLUMN(T57)),$A:$A,0),$C57+COLUMN($E57)+1),TRUE),INDIRECT(ADDRESS(ROW(T57),$C57+COLUMN($E57)),TRUE),INDIRECT(ADDRESS(MATCH("START"&OFFSET(T57,0,COLUMN($B57)-COLUMN(T57)),$A:$A,0),COLUMN(T57))&":"&ADDRESS(MATCH("END"&OFFSET(T57,0,COLUMN($B57)-COLUMN(T57)),$A:$A,0),COLUMN(T57)),TRUE))))) -> 0 | U57: =IF(OFFSET(U57,ROW(U$2)-ROW(U57),0)="TT",SUMIF(INDIRECT(ADDRESS(2,COLUMN($Q57)+1) & ":" & ADDRESS(2,COLUMN(U57)-1),TRUE),"TBE",INDIRECT(ADDRESS(ROW(U57), COLUMN($Q57)+1) & ":" & ADDRESS(ROW(U57),COLUMN(U57)-1),TRUE)),IF(OFFSET(U57,ROW(U$2)-ROW(U57),0)="TBE",SUMIF(INDIRECT(ADDRESS(2,MATCH(INT(OFFSET(U57,ROW(U$2)-ROW(U57),-2)),$2:$2,0)) & ":" & ADDRESS(2,COLUMN(U57)-1),TRUE),"T",INDIRECT(ADDRESS(ROW(U57), MATCH(INT(OFFSET(U57,ROW(U$2)-ROW(U57),-2)),$2:$2,0)) & ":" & ADDRESS(ROW(U57),COLUMN(U57)-1),TRUE)),IF(OFFSET(U57,0,COLUMN($M57)-COLUMN(U57))="V",OFFSET(U57,0,-2)*OFFSET(U57,0,-1),"TOTAL"))) -> 0
A58: =IF(ISNUMBER(OFFSET(A58,0,12)),"START",IF(AND(OFFSET(A58,0,2)=0,OFFSET(A58,0,4)="GT"),"END",""))&OFFSET(A58,0,1) -> WP002 | B58: =IF(ISNUMBER(OFFSET(B58,0,11)),"WP" & TEXT(OFFSET(B58,0,11),"000"),OFFSET(B58,-1,0)) -> WP002 | C58: 7 | D58: WPRow.O | L58: T3 | M58: V | Q58: Travel | T58: =IF(OFFSET(T58,ROW(T$2)-ROW(T58),0)="TT","TT",IF(OFFSET(T58,0,COLUMN($M58)-COLUMN(T58))="%",ROUND((OFFSET(T58,-2,0)-OFFSET(T58,-21,0))*0.07,2),IF(OFFSET(T58,0,COLUMN($M58)-COLUMN(T58))="V",ROUND(OFFSET(T58,0,-2)*OFFSET(T58,0,-1),2),SUMIF(INDIRECT(ADDRESS(MATCH("START"&OFFSET(T58,0,COLUMN($B58)-COLUMN(T58)),$A:$A,0),$C58+COLUMN($E58)+1)&":"&ADDRESS(MATCH("END"&OFFSET(T58,0,COLUMN($B58)-COLUMN(T58)),$A:$A,0),$C58+COLUMN($E58)+1),TRUE),INDIRECT(ADDRESS(ROW(T58),$C58+COLUMN($E58)),TRUE),INDIRECT(ADDRESS(MATCH("START"&OFFSET(T58,0,COLUMN($B58)-COLUMN(T58)),$A:$A,0),COLUMN(T58))&":"&ADDRESS(MATCH("END"&OFFSET(T58,0,COLUMN($B58)-COLUMN(T58)),$A:$A,0),COLUMN(T58)),TRUE))))) -> 0 | U58: =IF(OFFSET(U58,ROW(U$2)-ROW(U58),0)="TT",SUMIF(INDIRECT(ADDRESS(2,COLUMN($Q58)+1) & ":" & ADDRESS(2,COLUMN(U58)-1),TRUE),"TBE",INDIRECT(ADDRESS(ROW(U58), COLUMN($Q58)+1) & ":" & ADDRESS(ROW(U58),COLUMN(U58)-1),TRUE)),IF(OFFSET(U58,ROW(U$2)-ROW(U58),0)="TBE",SUMIF(INDIRECT(ADDRESS(2,MATCH(INT(OFFSET(U58,ROW(U$2)-ROW(U58),-2)),$2:$2,0)) & ":" & ADDRESS(2,COLUMN(U58)-1),TRUE),"T",INDIRECT(ADDRESS(ROW(U58), MATCH(INT(OFFSET(U58,ROW(U$2)-ROW(U58),-2)),$2:$2,0)) & ":" & ADDRESS(ROW(U58),COLUMN(U58)-1),TRUE)),IF(OFFSET(U58,0,COLUMN($M58)-COLUMN(U58))="V",OFFSET(U58,0,-2)*OFFSET(U58,0,-1),"TOTAL"))) -> 0
A59: =IF(ISNUMBER(OFFSET(A59,0,12)),"START",IF(AND(OFFSET(A59,0,2)=0,OFFSET(A59,0,4)="GT"),"END",""))&OFFSET(A59,0,1) -> WP002 | B59: =IF(ISNUMBER(OFFSET(B59,0,11)),"WP" & TEXT(OFFSET(B59,0,11),"000"),OFFSET(B59,-1,0)) -> WP002 | C59: 7 | D59: WPRow.P | L59: T3 | M59: V | Q59: Accommodation | T59: =IF(OFFSET(T59,ROW(T$2)-ROW(T59),0)="TT","TT",IF(OFFSET(T59,0,COLUMN($M59)-COLUMN(T59))="%",ROUND((OFFSET(T59,-2,0)-OFFSET(T59,-21,0))*0.07,2),IF(OFFSET(T59,0,COLUMN($M59)-COLUMN(T59))="V",ROUND(OFFSET(T59,0,-2)*OFFSET(T59,0,-1),2),SUMIF(INDIRECT(ADDRESS(MATCH("START"&OFFSET(T59,0,COLUMN($B59)-COLUMN(T59)),$A:$A,0),$C59+COLUMN($E59)+1)&":"&ADDRESS(MATCH("END"&OFFSET(T59,0,COLUMN($B59)-COLUMN(T59)),$A:$A,0),$C59+COLUMN($E59)+1),TRUE),INDIRECT(ADDRESS(ROW(T59),$C59+COLUMN($E59)),TRUE),INDIRECT(ADDRESS(MATCH("START"&OFFSET(T59,0,COLUMN($B59)-COLUMN(T59)),$A:$A,0),COLUMN(T59))&":"&ADDRESS(MATCH("END"&OFFSET(T59,0,COLUMN($B59)-COLUMN(T59)),$A:$A,0),COLUMN(T59)),TRUE))))) -> 0 | U59: =IF(OFFSET(U59,ROW(U$2)-ROW(U59),0)="TT",SUMIF(INDIRECT(ADDRESS(2,COLUMN($Q59)+1) & ":" & ADDRESS(2,COLUMN(U59)-1),TRUE),"TBE",INDIRECT(ADDRESS(ROW(U59), COLUMN($Q59)+1) & ":" & ADDRESS(ROW(U59),COLUMN(U59)-1),TRUE)),IF(OFFSET(U59,ROW(U$2)-ROW(U59),0)="TBE",SUMIF(INDIRECT(ADDRESS(2,MATCH(INT(OFFSET(U59,ROW(U$2)-ROW(U59),-2)),$2:$2,0)) & ":" & ADDRESS(2,COLUMN(U59)-1),TRUE),"T",INDIRECT(ADDRESS(ROW(U59), MATCH(INT(OFFSET(U59,ROW(U$2)-ROW(U59),-2)),$2:$2,0)) & ":" & ADDRESS(ROW(U59),COLUMN(U59)-1),TRUE)),IF(OFFSET(U59,0,COLUMN($M59)-COLUMN(U59))="V",OFFSET(U59,0,-2)*OFFSET(U59,0,-1),"TOTAL"))) -> 0
A60: =IF(ISNUMBER(OFFSET(A60,0,12)),"START",IF(AND(OFFSET(A60,0,2)=0,OFFSET(A60,0,4)="GT"),"END",""))&OFFSET(A60,0,1) -> WP002 | B60: =IF(ISNUMBER(OFFSET(B60,0,11)),"WP" & TEXT(OFFSET(B60,0,11),"000"),OFFSET(B60,-1,0)) -> WP002 | C60: 7 | D60: WPRow.Q | L60: T3 | M60: V | Q60: Subsistence | T60: =IF(OFFSET(T60,ROW(T$2)-ROW(T60),0)="TT","TT",IF(OFFSET(T60,0,COLUMN($M60)-COLUMN(T60))="%",ROUND((OFFSET(T60,-2,0)-OFFSET(T60,-21,0))*0.07,2),IF(OFFSET(T60,0,COLUMN($M60)-COLUMN(T60))="V",ROUND(OFFSET(T60,0,-2)*OFFSET(T60,0,-1),2),SUMIF(INDIRECT(ADDRESS(MATCH("START"&OFFSET(T60,0,COLUMN($B60)-COLUMN(T60)),$A:$A,0),$C60+COLUMN($E60)+1)&":"&ADDRESS(MATCH("END"&OFFSET(T60,0,COLUMN($B60)-COLUMN(T60)),$A:$A,0),$C60+COLUMN($E60)+1),TRUE),INDIRECT(ADDRESS(ROW(T60),$C60+COLUMN($E60)),TRUE),INDIRECT(ADDRESS(MATCH("START"&OFFSET(T60,0,COLUMN($B60)-COLUMN(T60)),$A:$A,0),COLUMN(T60))&":"&ADDRESS(MATCH("END"&OFFSET(T60,0,COLUMN($B60)-COLUMN(T60)),$A:$A,0),COLUMN(T60)),TRUE))))) -> 0 | U60: =IF(OFFSET(U60,ROW(U$2)-ROW(U60),0)="TT",SUMIF(INDIRECT(ADDRESS(2,COLUMN($Q60)+1) & ":" & ADDRESS(2,COLUMN(U60)-1),TRUE),"TBE",INDIRECT(ADDRESS(ROW(U60), COLUMN($Q60)+1) & ":" & ADDRESS(ROW(U60),COLUMN(U60)-1),TRUE)),IF(OFFSET(U60,ROW(U$2)-ROW(U60),0)="TBE",SUMIF(INDIRECT(ADDRESS(2,MATCH(INT(OFFSET(U60,ROW(U$2)-ROW(U60),-2)),$2:$2,0)) & ":" & ADDRESS(2,COLUMN(U60)-1),TRUE),"T",INDIRECT(ADDRESS(ROW(U60), MATCH(INT(OFFSET(U60,ROW(U$2)-ROW(U60),-2)),$2:$2,0)) & ":" & ADDRESS(ROW(U60),COLUMN(U60)-1),TRUE)),IF(OFFSET(U60,0,COLUMN($M60)-COLUMN(U60))="V",OFFSET(U60,0,-2)*OFFSET(U60,0,-1),"TOTAL"))) -> 0
A61: =IF(ISNUMBER(OFFSET(A61,0,12)),"START",IF(AND(OFFSET(A61,0,2)=0,OFFSET(A61,0,4)="GT"),"END",""))&OFFSET(A61,0,1) -> WP002 | B61: =IF(ISNUMBER(OFFSET(B61,0,11)),"WP" & TEXT(OFFSET(B61,0,11),"000"),OFFSET(B61,-1,0)) -> WP002 | C61: 5 | D61: WPRow.R | J61: TC | M61: V | P61: C.2 Equipment (please refer to the Depreciation Cost sheet) | T61: =IF(OFFSET(T61,ROW(T$2)-ROW(T61),0)="TT","TT",IF(OFFSET(T61,0,COLUMN($M61)-COLUMN(T61))="%",ROUND((OFFSET(T61,-2,0)-OFFSET(T61,-21,0))*0.07,2),IF(OFFSET(T61,0,COLUMN($M61)-COLUMN(T61))="V",ROUND(OFFSET(T61,0,-2)*OFFSET(T61,0,-1),2),SUMIF(INDIRECT(ADDRESS(MATCH("START"&OFFSET(T61,0,COLUMN($B61)-COLUMN(T61)),$A:$A,0),$C61+COLUMN($E61)+1)&":"&ADDRESS(MATCH("END"&OFFSET(T61,0,COLUMN($B61)-COLUMN(T61)),$A:$A,0),$C61+COLUMN($E61)+1),TRUE),INDIRECT(ADDRESS(ROW(T61),$C61+COLUMN($E61)),TRUE),INDIRECT(ADDRESS(MATCH("START"&OFFSET(T61,0,COLUMN($B61)-COLUMN(T61)),$A:$A,0),COLUMN(T61))&":"&ADDRESS(MATCH("END"&OFFSET(T61,0,COLUMN($B61)-COLUMN(T61)),$A:$A,0),COLUMN(T61)),TRUE))))) -> 0 | U61: =IF(OFFSET(U61,ROW(U$2)-ROW(U61),0)="TT",SUMIF(INDIRECT(ADDRESS(2,COLUMN($Q61)+1) & ":" & ADDRESS(2,COLUMN(U61)-1),TRUE),"TBE",INDIRECT(ADDRESS(ROW(U61), COLUMN($Q61)+1) & ":" & ADDRESS(ROW(U61),COLUMN(U61)-1),TRUE)),IF(OFFSET(U61,ROW(U$2)-ROW(U61),0)="TBE",SUMIF(INDIRECT(ADDRESS(2,MATCH(INT(OFFSET(U61,ROW(U$2)-ROW(U61),-2)),$2:$2,0)) & ":" & ADDRESS(2,COLUMN(U61)-1),TRUE),"T",INDIRECT(ADDRESS(ROW(U61), MATCH(INT(OFFSET(U61,ROW(U$2)-ROW(U61),-2)),$2:$2,0)) & ":" & ADDRESS(ROW(U61),COLUMN(U61)-1),TRUE)),IF(OFFSET(U61,0,COLUMN($M61)-COLUMN(U61))="V",OFFSET(U61,0,-2)*OFFSET(U61,0,-1),"TOTAL"))) -> 0
A62: =IF(ISNUMBER(OFFSET(A62,0,12)),"START",IF(AND(OFFSET(A62,0,2)=0,OFFSET(A62,0,4)="GT"),"END",""))&OFFSET(A62,0,1) -> WP002 | B62: =IF(ISNUMBER(OFFSET(B62,0,11)),"WP" & TEXT(OFFSET(B62,0,11),"000"),OFFSET(B62,-1,0)) -> WP002 | C62: 6 | D62: WPRow.S | J62: TC | K62: T4 | M62: T | P62: C.3 Other goods, works and services | T62: =IF(OFFSET(T62,ROW(T$2)-ROW(T62),0)="TT","TT",IF(OFFSET(T62,0,COLUMN($M62)-COLUMN(T62))="%",ROUND((OFFSET(T62,-2,0)-OFFSET(T62,-21,0))*0.07,2),IF(OFFSET(T62,0,COLUMN($M62)-COLUMN(T62))="V",ROUND(OFFSET(T62,0,-2)*OFFSET(T62,0,-1),2),SUMIF(INDIRECT(ADDRESS(MATCH("START"&OFFSET(T62,0,COLUMN($B62)-COLUMN(T62)),$A:$A,0),$C62+COLUMN($E62)+1)&":"&ADDRESS(MATCH("END"&OFFSET(T62,0,COLUMN($B62)-COLUMN(T62)),$A:$A,0),$C62+COLUMN($E62)+1),TRUE),INDIRECT(ADDRESS(ROW(T62),$C62+COLUMN($E62)),TRUE),INDIRECT(ADDRESS(MATCH("START"&OFFSET(T62,0,COLUMN($B62)-COLUMN(T62)),$A:$A,0),COLUMN(T62))&":"&ADDRESS(MATCH("END"&OFFSET(T62,0,COLUMN($B62)-COLUMN(T62)),$A:$A,0),COLUMN(T62)),TRUE))))) -> 0 | U62: =IF(OFFSET(U62,ROW(U$2)-ROW(U62),0)="TT",SUMIF(INDIRECT(ADDRESS(2,COLUMN($Q62)+1) & ":" & ADDRESS(2,COLUMN(U62)-1),TRUE),"TBE",INDIRECT(ADDRESS(ROW(U62), COLUMN($Q62)+1) & ":" & ADDRESS(ROW(U62),COLUMN(U62)-1),TRUE)),IF(OFFSET(U62,ROW(U$2)-ROW(U62),0)="TBE",SUMIF(INDIRECT(ADDRESS(2,MATCH(INT(OFFSET(U62,ROW(U$2)-ROW(U62),-2)),$2:$2,0)) & ":" & ADDRESS(2,COLUMN(U62)-1),TRUE),"T",INDIRECT(ADDRESS(ROW(U62), MATCH(INT(OFFSET(U62,ROW(U$2)-ROW(U62),-2)),$2:$2,0)) & ":" & ADDRESS(ROW(U62),COLUMN(U62)-1),TRUE)),IF(OFFSET(U62,0,COLUMN($M62)-COLUMN(U62))="V",OFFSET(U62,0,-2)*OFFSET(U62,0,-1),"TOTAL"))) -> 0
A63: =IF(ISNUMBER(OFFSET(A63,0,12)),"START",IF(AND(OFFSET(A63,0,2)=0,OFFSET(A63,0,4)="GT"),"END",""))&OFFSET(A63,0,1) -> WP002 | B63: =IF(ISNUMBER(OFFSET(B63,0,11)),"WP" & TEXT(OFFSET(B63,0,11),"000"),OFFSET(B63,-1,0)) -> WP002 | C63: 7 | D63: WPRow.T | L63: T4 | M63: V | Q63: Consumables | T63: =IF(OFFSET(T63,ROW(T$2)-ROW(T63),0)="TT","TT",IF(OFFSET(T63,0,COLUMN($M63)-COLUMN(T63))="%",ROUND((OFFSET(T63,-2,0)-OFFSET(T63,-21,0))*0.07,2),IF(OFFSET(T63,0,COLUMN($M63)-COLUMN(T63))="V",ROUND(OFFSET(T63,0,-2)*OFFSET(T63,0,-1),2),SUMIF(INDIRECT(ADDRESS(MATCH("START"&OFFSET(T63,0,COLUMN($B63)-COLUMN(T63)),$A:$A,0),$C63+COLUMN($E63)+1)&":"&ADDRESS(MATCH("END"&OFFSET(T63,0,COLUMN($B63)-COLUMN(T63)),$A:$A,0),$C63+COLUMN($E63)+1),TRUE),INDIRECT(ADDRESS(ROW(T63),$C63+COLUMN($E63)),TRUE),INDIRECT(ADDRESS(MATCH("START"&OFFSET(T63,0,COLUMN($B63)-COLUMN(T63)),$A:$A,0),COLUMN(T63))&":"&ADDRESS(MATCH("END"&OFFSET(T63,0,COLUMN($B63)-COLUMN(T63)),$A:$A,0),COLUMN(T63)),TRUE))))) -> 0 | U63: =IF(OFFSET(U63,ROW(U$2)-ROW(U63),0)="TT",SUMIF(INDIRECT(ADDRESS(2,COLUMN($Q63)+1) & ":" & ADDRESS(2,COLUMN(U63)-1),TRUE),"TBE",INDIRECT(ADDRESS(ROW(U63), COLUMN($Q63)+1) & ":" & ADDRESS(ROW(U63),COLUMN(U63)-1),TRUE)),IF(OFFSET(U63,ROW(U$2)-ROW(U63),0)="TBE",SUMIF(INDIRECT(ADDRESS(2,MATCH(INT(OFFSET(U63,ROW(U$2)-ROW(U63),-2)),$2:$2,0)) & ":" & ADDRESS(2,COLUMN(U63)-1),TRUE),"T",INDIRECT(ADDRESS(ROW(U63), MATCH(INT(OFFSET(U63,ROW(U$2)-ROW(U63),-2)),$2:$2,0)) & ":" & ADDRESS(ROW(U63),COLUMN(U63)-1),TRUE)),IF(OFFSET(U63,0,COLUMN($M63)-COLUMN(U63))="V",OFFSET(U63,0,-2)*OFFSET(U63,0,-1),"TOTAL"))) -> 0
A64: =IF(ISNUMBER(OFFSET(A64,0,12)),"START",IF(AND(OFFSET(A64,0,2)=0,OFFSET(A64,0,4)="GT"),"END",""))&OFFSET(A64,0,1) -> WP002 | B64: =IF(ISNUMBER(OFFSET(B64,0,11)),"WP" & TEXT(OFFSET(B64,0,11),"000"),OFFSET(B64,-1,0)) -> WP002 | C64: 7 | D64: WPRow.U | L64: T4 | M64: V | Q64: Services for Meetings, Seminars | T64: =IF(OFFSET(T64,ROW(T$2)-ROW(T64),0)="TT","TT",IF(OFFSET(T64,0,COLUMN($M64)-COLUMN(T64))="%",ROUND((OFFSET(T64,-2,0)-OFFSET(T64,-21,0))*0.07,2),IF(OFFSET(T64,0,COLUMN($M64)-COLUMN(T64))="V",ROUND(OFFSET(T64,0,-2)*OFFSET(T64,0,-1),2),SUMIF(INDIRECT(ADDRESS(MATCH("START"&OFFSET(T64,0,COLUMN($B64)-COLUMN(T64)),$A:$A,0),$C64+COLUMN($E64)+1)&":"&ADDRESS(MATCH("END"&OFFSET(T64,0,COLUMN($B64)-COLUMN(T64)),$A:$A,0),$C64+COLUMN($E64)+1),TRUE),INDIRECT(ADDRESS(ROW(T64),$C64+COLUMN($E64)),TRUE),INDIRECT(ADDRESS(MATCH("START"&OFFSET(T64,0,COLUMN($B64)-COLUMN(T64)),$A:$A,0),COLUMN(T64))&":"&ADDRESS(MATCH("END"&OFFSET(T64,0,COLUMN($B64)-COLUMN(T64)),$A:$A,0),COLUMN(T64)),TRUE))))) -> 0 | U64: =IF(OFFSET(U64,ROW(U$2)-ROW(U64),0)="TT",SUMIF(INDIRECT(ADDRESS(2,COLUMN($Q64)+1) & ":" & ADDRESS(2,COLUMN(U64)-1),TRUE),"TBE",INDIRECT(ADDRESS(ROW(U64), COLUMN($Q64)+1) & ":" & ADDRESS(ROW(U64),COLUMN(U64)-1),TRUE)),IF(OFFSET(U64,ROW(U$2)-ROW(U64),0)="TBE",SUMIF(INDIRECT(ADDRESS(2,MATCH(INT(OFFSET(U64,ROW(U$2)-ROW(U64),-2)),$2:$2,0)) & ":" & ADDRESS(2,COLUMN(U64)-1),TRUE),"T",INDIRECT(ADDRESS(ROW(U64), MATCH(INT(OFFSET(U64,ROW(U$2)-ROW(U64),-2)),$2:$2,0)) & ":" & ADDRESS(ROW(U64),COLUMN(U64)-1),TRUE)),IF(OFFSET(U64,0,COLUMN($M64)-COLUMN(U64))="V",OFFSET(U64,0,-2)*OFFSET(U64,0,-1),"TOTAL"))) -> 0
A65: =IF(ISNUMBER(OFFSET(A65,0,12)),"START",IF(AND(OFFSET(A65,0,2)=0,OFFSET(A65,0,4)="GT"),"END",""))&OFFSET(A65,0,1) -> WP002 | B65: =IF(ISNUMBER(OFFSET(B65,0,11)),"WP" & TEXT(OFFSET(B65,0,11),"000"),OFFSET(B65,-1,0)) -> WP002 | C65: 7 | D65: WPRow.V | L65: T4 | M65: V | Q65: Services for communication/promotion/dissemination | T65: =IF(OFFSET(T65,ROW(T$2)-ROW(T65),0)="TT","TT",IF(OFFSET(T65,0,COLUMN($M65)-COLUMN(T65))="%",ROUND((OFFSET(T65,-2,0)-OFFSET(T65,-21,0))*0.07,2),IF(OFFSET(T65,0,COLUMN($M65)-COLUMN(T65))="V",ROUND(OFFSET(T65,0,-2)*OFFSET(T65,0,-1),2),SUMIF(INDIRECT(ADDRESS(MATCH("START"&OFFSET(T65,0,COLUMN($B65)-COLUMN(T65)),$A:$A,0),$C65+COLUMN($E65)+1)&":"&ADDRESS(MATCH("END"&OFFSET(T65,0,COLUMN($B65)-COLUMN(T65)),$A:$A,0),$C65+COLUMN($E65)+1),TRUE),INDIRECT(ADDRESS(ROW(T65),$C65+COLUMN($E65)),TRUE),INDIRECT(ADDRESS(MATCH("START"&OFFSET(T65,0,COLUMN($B65)-COLUMN(T65)),$A:$A,0),COLUMN(T65))&":"&ADDRESS(MATCH("END"&OFFSET(T65,0,COLUMN($B65)-COLUMN(T65)),$A:$A,0),COLUMN(T65)),TRUE))))) -> 0 | U65: =IF(OFFSET(U65,ROW(U$2)-ROW(U65),0)="TT",SUMIF(INDIRECT(ADDRESS(2,COLUMN($Q65)+1) & ":" & ADDRESS(2,COLUMN(U65)-1),TRUE),"TBE",INDIRECT(ADDRESS(ROW(U65), COLUMN($Q65)+1) & ":" & ADDRESS(ROW(U65),COLUMN(U65)-1),TRUE)),IF(OFFSET(U65,ROW(U$2)-ROW(U65),0)="TBE",SUMIF(INDIRECT(ADDRESS(2,MATCH(INT(OFFSET(U65,ROW(U$2)-ROW(U65),-2)),$2:$2,0)) & ":" & ADDRESS(2,COLUMN(U65)-1),TRUE),"T",INDIRECT(ADDRESS(ROW(U65), MATCH(INT(OFFSET(U65,ROW(U$2)-ROW(U65),-2)),$2:$2,0)) & ":" & ADDRESS(ROW(U65),COLUMN(U65)-1),TRUE)),IF(OFFSET(U65,0,COLUMN($M65)-COLUMN(U65))="V",OFFSET(U65,0,-2)*OFFSET(U65,0,-1),"TOTAL"))) -> 0
A66: =IF(ISNUMBER(OFFSET(A66,0,12)),"START",IF(AND(OFFSET(A66,0,2)=0,OFFSET(A66,0,4)="GT"),"END",""))&OFFSET(A66,0,1) -> WP002 | B66: =IF(ISNUMBER(OFFSET(B66,0,11)),"WP" & TEXT(OFFSET(B66,0,11),"000"),OFFSET(B66,-1,0)) -> WP002 | C66: 7 | D66: WPRow.W | L66: T4 | M66: V | Q66: Website | T66: =IF(OFFSET(T66,ROW(T$2)-ROW(T66),0)="TT","TT",IF(OFFSET(T66,0,COLUMN($M66)-COLUMN(T66))="%",ROUND((OFFSET(T66,-2,0)-OFFSET(T66,-21,0))*0.07,2),IF(OFFSET(T66,0,COLUMN($M66)-COLUMN(T66))="V",ROUND(OFFSET(T66,0,-2)*OFFSET(T66,0,-1),2),SUMIF(INDIRECT(ADDRESS(MATCH("START"&OFFSET(T66,0,COLUMN($B66)-COLUMN(T66)),$A:$A,0),$C66+COLUMN($E66)+1)&":"&ADDRESS(MATCH("END"&OFFSET(T66,0,COLUMN($B66)-COLUMN(T66)),$A:$A,0),$C66+COLUMN($E66)+1),TRUE),INDIRECT(ADDRESS(ROW(T66),$C66+COLUMN($E66)),TRUE),INDIRECT(ADDRESS(MATCH("START"&OFFSET(T66,0,COLUMN($B66)-COLUMN(T66)),$A:$A,0),COLUMN(T66))&":"&ADDRESS(MATCH("END"&OFFSET(T66,0,COLUMN($B66)-COLUMN(T66)),$A:$A,0),COLUMN(T66)),TRUE))))) -> 0 | U66: =IF(OFFSET(U66,ROW(U$2)-ROW(U66),0)="TT",SUMIF(INDIRECT(ADDRESS(2,COLUMN($Q66)+1) & ":" & ADDRESS(2,COLUMN(U66)-1),TRUE),"TBE",INDIRECT(ADDRESS(ROW(U66), COLUMN($Q66)+1) & ":" & ADDRESS(ROW(U66),COLUMN(U66)-1),TRUE)),IF(OFFSET(U66,ROW(U$2)-ROW(U66),0)="TBE",SUMIF(INDIRECT(ADDRESS(2,MATCH(INT(OFFSET(U66,ROW(U$2)-ROW(U66),-2)),$2:$2,0)) & ":" & ADDRESS(2,COLUMN(U66)-1),TRUE),"T",INDIRECT(ADDRESS(ROW(U66), MATCH(INT(OFFSET(U66,ROW(U$2)-ROW(U66),-2)),$2:$2,0)) & ":" & ADDRESS(ROW(U66),COLUMN(U66)-1),TRUE)),IF(OFFSET(U66,0,COLUMN($M66)-COLUMN(U66))="V",OFFSET(U66,0,-2)*OFFSET(U66,0,-1),"TOTAL"))) -> 0
A67: =IF(ISNUMBER(OFFSET(A67,0,12)),"START",IF(AND(OFFSET(A67,0,2)=0,OFFSET(A67,0,4)="GT"),"END",""))&OFFSET(A67,0,1) -> WP002 | B67: =IF(ISNUMBER(OFFSET(B67,0,11)),"WP" & TEXT(OFFSET(B67,0,11),"000"),OFFSET(B67,-1,0)) -> WP002 | C67: 7 | D67: WPRow.X | L67: T4 | M67: V | Q67: Artistic Fees | T67: =IF(OFFSET(T67,ROW(T$2)-ROW(T67),0)="TT","TT",IF(OFFSET(T67,0,COLUMN($M67)-COLUMN(T67))="%",ROUND((OFFSET(T67,-2,0)-OFFSET(T67,-21,0))*0.07,2),IF(OFFSET(T67,0,COLUMN($M67)-COLUMN(T67))="V",ROUND(OFFSET(T67,0,-2)*OFFSET(T67,0,-1),2),SUMIF(INDIRECT(ADDRESS(MATCH("START"&OFFSET(T67,0,COLUMN($B67)-COLUMN(T67)),$A:$A,0),$C67+COLUMN($E67)+1)&":"&ADDRESS(MATCH("END"&OFFSET(T67,0,COLUMN($B67)-COLUMN(T67)),$A:$A,0),$C67+COLUMN($E67)+1),TRUE),INDIRECT(ADDRESS(ROW(T67),$C67+COLUMN($E67)),TRUE),INDIRECT(ADDRESS(MATCH("START"&OFFSET(T67,0,COLUMN($B67)-COLUMN(T67)),$A:$A,0),COLUMN(T67))&":"&ADDRESS(MATCH("END"&OFFSET(T67,0,COLUMN($B67)-COLUMN(T67)),$A:$A,0),COLUMN(T67)),TRUE))))) -> 0 | U67: =IF(OFFSET(U67,ROW(U$2)-ROW(U67),0)="TT",SUMIF(INDIRECT(ADDRESS(2,COLUMN($Q67)+1) & ":" & ADDRESS(2,COLUMN(U67)-1),TRUE),"TBE",INDIRECT(ADDRESS(ROW(U67), COLUMN($Q67)+1) & ":" & ADDRESS(ROW(U67),COLUMN(U67)-1),TRUE)),IF(OFFSET(U67,ROW(U$2)-ROW(U67),0)="TBE",SUMIF(INDIRECT(ADDRESS(2,MATCH(INT(OFFSET(U67,ROW(U$2)-ROW(U67),-2)),$2:$2,0)) & ":" & ADDRESS(2,COLUMN(U67)-1),TRUE),"T",INDIRECT(ADDRESS(ROW(U67), MATCH(INT(OFFSET(U67,ROW(U$2)-ROW(U67),-2)),$2:$2,0)) & ":" & ADDRESS(ROW(U67),COLUMN(U67)-1),TRUE)),IF(OFFSET(U67,0,COLUMN($M67)-COLUMN(U67))="V",OFFSET(U67,0,-2)*OFFSET(U67,0,-1),"TOTAL"))) -> 0
A68: =IF(ISNUMBER(OFFSET(A68,0,12)),"START",IF(AND(OFFSET(A68,0,2)=0,OFFSET(A68,0,4)="GT"),"END",""))&OFFSET(A68,0,1) -> WP002 | B68: =IF(ISNUMBER(OFFSET(B68,0,11)),"WP" & TEXT(OFFSET(B68,0,11),"000"),OFFSET(B68,-1,0)) -> WP002 | C68: 7 | D68: WPRow.Y | L68: T4 | M68: V | Q68: Other (please specify details under worksheet "Comments") | T68: =IF(OFFSET(T68,ROW(T$2)-ROW(T68),0)="TT","TT",IF(OFFSET(T68,0,COLUMN($M68)-COLUMN(T68))="%",ROUND((OFFSET(T68,-2,0)-OFFSET(T68,-21,0))*0.07,2),IF(OFFSET(T68,0,COLUMN($M68)-COLUMN(T68))="V",ROUND(OFFSET(T68,0,-2)*OFFSET(T68,0,-1),2),SUMIF(INDIRECT(ADDRESS(MATCH("START"&OFFSET(T68,0,COLUMN($B68)-COLUMN(T68)),$A:$A,0),$C68+COLUMN($E68)+1)&":"&ADDRESS(MATCH("END"&OFFSET(T68,0,COLUMN($B68)-COLUMN(T68)),$A:$A,0),$C68+COLUMN($E68)+1),TRUE),INDIRECT(ADDRESS(ROW(T68),$C68+COLUMN($E68)),TRUE),INDIRECT(ADDRESS(MATCH("START"&OFFSET(T68,0,COLUMN($B68)-COLUMN(T68)),$A:$A,0),COLUMN(T68))&":"&ADDRESS(MATCH("END"&OFFSET(T68,0,COLUMN($B68)-COLUMN(T68)),$A:$A,0),COLUMN(T68)),TRUE))))) -> 0 | U68: =IF(OFFSET(U68,ROW(U$2)-ROW(U68),0)="TT",SUMIF(INDIRECT(ADDRESS(2,COLUMN($Q68)+1) & ":" & ADDRESS(2,COLUMN(U68)-1),TRUE),"TBE",INDIRECT(ADDRESS(ROW(U68), COLUMN($Q68)+1) & ":" & ADDRESS(ROW(U68),COLUMN(U68)-1),TRUE)),IF(OFFSET(U68,ROW(U$2)-ROW(U68),0)="TBE",SUMIF(INDIRECT(ADDRESS(2,MATCH(INT(OFFSET(U68,ROW(U$2)-ROW(U68),-2)),$2:$2,0)) & ":" & ADDRESS(2,COLUMN(U68)-1),TRUE),"T",INDIRECT(ADDRESS(ROW(U68), MATCH(INT(OFFSET(U68,ROW(U$2)-ROW(U68),-2)),$2:$2,0)) & ":" & ADDRESS(ROW(U68),COLUMN(U68)-1),TRUE)),IF(OFFSET(U68,0,COLUMN($M68)-COLUMN(U68))="V",OFFSET(U68,0,-2)*OFFSET(U68,0,-1),"TOTAL"))) -> 0
A69: =IF(ISNUMBER(OFFSET(A69,0,12)),"START",IF(AND(OFFSET(A69,0,2)=0,OFFSET(A69,0,4)="GT"),"END",""))&OFFSET(A69,0,1) -> WP002 | B69: =IF(ISNUMBER(OFFSET(B69,0,11)),"WP" & TEXT(OFFSET(B69,0,11),"000"),OFFSET(B69,-1,0)) -> WP002 | C69: 4 | D69: WPRow.Z | H69: TTA | I69: TD | M69: T | O69: D. Other cost categories | T69: =IF(OFFSET(T69,ROW(T$2)-ROW(T69),0)="TT","TT",IF(OFFSET(T69,0,COLUMN($M69)-COLUMN(T69))="%",ROUND((OFFSET(T69,-2,0)-OFFSET(T69,-21,0))*0.07,2),IF(OFFSET(T69,0,COLUMN($M69)-COLUMN(T69))="V",ROUND(OFFSET(T69,0,-2)*OFFSET(T69,0,-1),2),SUMIF(INDIRECT(ADDRESS(MATCH("START"&OFFSET(T69,0,COLUMN($B69)-COLUMN(T69)),$A:$A,0),$C69+COLUMN($E69)+1)&":"&ADDRESS(MATCH("END"&OFFSET(T69,0,COLUMN($B69)-COLUMN(T69)),$A:$A,0),$C69+COLUMN($E69)+1),TRUE),INDIRECT(ADDRESS(ROW(T69),$C69+COLUMN($E69)),TRUE),INDIRECT(ADDRESS(MATCH("START"&OFFSET(T69,0,COLUMN($B69)-COLUMN(T69)),$A:$A,0),COLUMN(T69))&":"&ADDRESS(MATCH("END"&OFFSET(T69,0,COLUMN($B69)-COLUMN(T69)),$A:$A,0),COLUMN(T69)),TRUE))))) -> 0 | U69: =IF(OFFSET(U69,ROW(U$2)-ROW(U69),0)="TT",SUMIF(INDIRECT(ADDRESS(2,COLUMN($Q69)+1) & ":" & ADDRESS(2,COLUMN(U69)-1),TRUE),"TBE",INDIRECT(ADDRESS(ROW(U69), COLUMN($Q69)+1) & ":" & ADDRESS(ROW(U69),COLUMN(U69)-1),TRUE)),IF(OFFSET(U69,ROW(U$2)-ROW(U69),0)="TBE",SUMIF(INDIRECT(ADDRESS(2,MATCH(INT(OFFSET(U69,ROW(U$2)-ROW(U69),-2)),$2:$2,0)) & ":" & ADDRESS(2,COLUMN(U69)-1),TRUE),"T",INDIRECT(ADDRESS(ROW(U69), MATCH(INT(OFFSET(U69,ROW(U$2)-ROW(U69),-2)),$2:$2,0)) & ":" & ADDRESS(ROW(U69),COLUMN(U69)-1),TRUE)),IF(OFFSET(U69,0,COLUMN($M69)-COLUMN(U69))="V",OFFSET(U69,0,-2)*OFFSET(U69,0,-1),"TOTAL"))) -> 0
A70: =IF(ISNUMBER(OFFSET(A70,0,12)),"START",IF(AND(OFFSET(A70,0,2)=0,OFFSET(A70,0,4)="GT"),"END",""))&OFFSET(A70,0,1) -> WP002 | B70: =IF(ISNUMBER(OFFSET(B70,0,11)),"WP" & TEXT(OFFSET(B70,0,11),"000"),OFFSET(B70,-1,0)) -> WP002 | C70: 5 | D70: WPRow.0 | J70: TD | M70: V | P70: D.1 Financial support to third parties | T70: =IF(OFFSET(T70,ROW(T$2)-ROW(T70),0)="TT","TT",IF(OFFSET(T70,0,COLUMN($M70)-COLUMN(T70))="%",ROUND((OFFSET(T70,-2,0)-OFFSET(T70,-21,0))*0.07,2),IF(OFFSET(T70,0,COLUMN($M70)-COLUMN(T70))="V",ROUND(OFFSET(T70,0,-2)*OFFSET(T70,0,-1),2),SUMIF(INDIRECT(ADDRESS(MATCH("START"&OFFSET(T70,0,COLUMN($B70)-COLUMN(T70)),$A:$A,0),$C70+COLUMN($E70)+1)&":"&ADDRESS(MATCH("END"&OFFSET(T70,0,COLUMN($B70)-COLUMN(T70)),$A:$A,0),$C70+COLUMN($E70)+1),TRUE),INDIRECT(ADDRESS(ROW(T70),$C70+COLUMN($E70)),TRUE),INDIRECT(ADDRESS(MATCH("START"&OFFSET(T70,0,COLUMN($B70)-COLUMN(T70)),$A:$A,0),COLUMN(T70))&":"&ADDRESS(MATCH("END"&OFFSET(T70,0,COLUMN($B70)-COLUMN(T70)),$A:$A,0),COLUMN(T70)),TRUE))))) -> 0 | U70: =IF(OFFSET(U70,ROW(U$2)-ROW(U70),0)="TT",SUMIF(INDIRECT(ADDRESS(2,COLUMN($Q70)+1) & ":" & ADDRESS(2,COLUMN(U70)-1),TRUE),"TBE",INDIRECT(ADDRESS(ROW(U70), COLUMN($Q70)+1) & ":" & ADDRESS(ROW(U70),COLUMN(U70)-1),TRUE)),IF(OFFSET(U70,ROW(U$2)-ROW(U70),0)="TBE",SUMIF(INDIRECT(ADDRESS(2,MATCH(INT(OFFSET(U70,ROW(U$2)-ROW(U70),-2)),$2:$2,0)) & ":" & ADDRESS(2,COLUMN(U70)-1),TRUE),"T",INDIRECT(ADDRESS(ROW(U70), MATCH(INT(OFFSET(U70,ROW(U$2)-ROW(U70),-2)),$2:$2,0)) & ":" & ADDRESS(ROW(U70),COLUMN(U70)-1),TRUE)),IF(OFFSET(U70,0,COLUMN($M70)-COLUMN(U70))="V",OFFSET(U70,0,-2)*OFFSET(U70,0,-1),"TOTAL"))) -> 0
A71: =IF(ISNUMBER(OFFSET(A71,0,12)),"START",IF(AND(OFFSET(A71,0,2)=0,OFFSET(A71,0,4)="GT"),"END",""))&OFFSET(A71,0,1) -> WP002 | B71: =IF(ISNUMBER(OFFSET(B71,0,11)),"WP" & TEXT(OFFSET(B71,0,11),"000"),OFFSET(B71,-1,0)) -> WP002 | C71: 2 | D71: WPRow.1 | F71: GT | G71: TTA | M71: T | O71: TOTAL DIRECT COSTS INCLUDING SUBCONTRACTING (A+B+C+D) | T71: =IF(OFFSET(T71,ROW(T$2)-ROW(T71),0)="TT","TT",IF(OFFSET(T71,0,COLUMN($M71)-COLUMN(T71))="%",ROUND((OFFSET(T71,-2,0)-OFFSET(T71,-21,0))*0.07,2),IF(OFFSET(T71,0,COLUMN($M71)-COLUMN(T71))="V",ROUND(OFFSET(T71,0,-2)*OFFSET(T71,0,-1),2),SUMIF(INDIRECT(ADDRESS(MATCH("START"&OFFSET(T71,0,COLUMN($B71)-COLUMN(T71)),$A:$A,0),$C71+COLUMN($E71)+1)&":"&ADDRESS(MATCH("END"&OFFSET(T71,0,COLUMN($B71)-COLUMN(T71)),$A:$A,0),$C71+COLUMN($E71)+1),TRUE),INDIRECT(ADDRESS(ROW(T71),$C71+COLUMN($E71)),TRUE),INDIRECT(ADDRESS(MATCH("START"&OFFSET(T71,0,COLUMN($B71)-COLUMN(T71)),$A:$A,0),COLUMN(T71))&":"&ADDRESS(MATCH("END"&OFFSET(T71,0,COLUMN($B71)-COLUMN(T71)),$A:$A,0),COLUMN(T71)),TRUE))))) -> 0 | U71: =IF(OFFSET(U71,ROW(U$2)-ROW(U71),0)="TT",SUMIF(INDIRECT(ADDRESS(2,COLUMN($Q71)+1) & ":" & ADDRESS(2,COLUMN(U71)-1),TRUE),"TBE",INDIRECT(ADDRESS(ROW(U71), COLUMN($Q71)+1) & ":" & ADDRESS(ROW(U71),COLUMN(U71)-1),TRUE)),IF(OFFSET(U71,ROW(U$2)-ROW(U71),0)="TBE",SUMIF(INDIRECT(ADDRESS(2,MATCH(INT(OFFSET(U71,ROW(U$2)-ROW(U71),-2)),$2:$2,0)) & ":" & ADDRESS(2,COLUMN(U71)-1),TRUE),"T",INDIRECT(ADDRESS(ROW(U71), MATCH(INT(OFFSET(U71,ROW(U$2)-ROW(U71),-2)),$2:$2,0)) & ":" & ADDRESS(ROW(U71),COLUMN(U71)-1),TRUE)),IF(OFFSET(U71,0,COLUMN($M71)-COLUMN(U71))="V",OFFSET(U71,0,-2)*OFFSET(U71,0,-1),"TOTAL"))) -> 0
A72: =IF(ISNUMBER(OFFSET(A72,0,12)),"START",IF(AND(OFFSET(A72,0,2)=0,OFFSET(A72,0,4)="GT"),"END",""))&OFFSET(A72,0,1) -> WP002 | B72: =IF(ISNUMBER(OFFSET(B72,0,11)),"WP" & TEXT(OFFSET(B72,0,11),"000"),OFFSET(B72,-1,0)) -> WP002 | C72: 1
A73: =IF(ISNUMBER(OFFSET(A73,0,12)),"START",IF(AND(OFFSET(A73,0,2)=0,OFFSET(A73,0,4)="GT"),"END",""))&OFFSET(A73,0,1) -> WP002 | B73: =IF(ISNUMBER(OFFSET(B73,0,11)),"WP" & TEXT(OFFSET(B73,0,11),"000"),OFFSET(B73,-1,0)) -> WP002 | C73: 2 | D73: WPRow.2 | F73: GT | M73: % | O73: E. Indirect costs 7% | T73: =IF(OFFSET(T73,ROW(T$2)-ROW(T73),0)="TT","TT",IF(OFFSET(T73,0,COLUMN($M73)-COLUMN(T73))="%",ROUND((OFFSET(T73,-2,0)-OFFSET(T73,-19,0))*0.07,2),IF(OFFSET(T73,0,COLUMN($M73)-COLUMN(T73))="V",ROUND(OFFSET(T73,0,-2)*OFFSET(T73,0,-1),2),SUMIF(INDIRECT(ADDRESS(MATCH("START"&OFFSET(T73,0,COLUMN($B73)-COLUMN(T73)),$A:$A,0),$C73+COLUMN($E73)+1)&":"&ADDRESS(MATCH("END"&OFFSET(T73,0,COLUMN($B73)-COLUMN(T73)),$A:$A,0),$C73+COLUMN($E73)+1),TRUE),INDIRECT(ADDRESS(ROW(T73),$C73+COLUMN($E73)),TRUE),INDIRECT(ADDRESS(MATCH("START"&OFFSET(T73,0,COLUMN($B73)-COLUMN(T73)),$A:$A,0),COLUMN(T73))&":"&ADDRESS(MATCH("END"&OFFSET(T73,0,COLUMN($B73)-COLUMN(T73)),$A:$A,0),COLUMN(T73)),TRUE))))) -> 0 | U73: =IF(OFFSET(U73,ROW(U$2)-ROW(U73),0)="TT",SUMIF(INDIRECT(ADDRESS(2,COLUMN($Q73)+1) & ":" & ADDRESS(2,COLUMN(U73)-1),TRUE),"TBE",INDIRECT(ADDRESS(ROW(U73), COLUMN($Q73)+1) & ":" & ADDRESS(ROW(U73),COLUMN(U73)-1),TRUE)),IF(OFFSET(U73,ROW(U$2)-ROW(U73),0)="TBE",SUMIF(INDIRECT(ADDRESS(2,MATCH(INT(OFFSET(U73,ROW(U$2)-ROW(U73),-2)),$2:$2,0)) & ":" & ADDRESS(2,COLUMN(U73)-1),TRUE),"T",INDIRECT(ADDRESS(ROW(U73), MATCH(INT(OFFSET(U73,ROW(U$2)-ROW(U73),-2)),$2:$2,0)) & ":" & ADDRESS(ROW(U73),COLUMN(U73)-1),TRUE)),IF(OFFSET(U73,0,COLUMN($M73)-COLUMN(U73))="V",OFFSET(U73,0,-2)*OFFSET(U73,0,-1),"TOTAL"))) -> 0
A74: =IF(ISNUMBER(OFFSET(A74,0,12)),"START",IF(AND(OFFSET(A74,0,2)=0,OFFSET(A74,0,4)="GT"),"END",""))&OFFSET(A74,0,1) -> WP002 | B74: =IF(ISNUMBER(OFFSET(B74,0,11)),"WP" & TEXT(OFFSET(B74,0,11),"000"),OFFSET(B74,-1,0)) -> WP002 | C74: 1
A75: =IF(ISNUMBER(OFFSET(A75,0,12)),"START",IF(AND(OFFSET(A75,0,2)=0,OFFSET(A75,0,4)="GT"),"END",""))&OFFSET(A75,0,1) -> ENDWP002 | B75: =IF(ISNUMBER(OFFSET(B75,0,11)),"WP" & TEXT(OFFSET(B75,0,11),"000"),OFFSET(B75,-1,0)) -> WP002 | C75: 0 | D75: WPRow.3 | E75: GT | M75: T | O75: ="TOTAL COSTS (A+B+C+D+E) - " & OFFSET(O75,-26,0) -> TOTAL COSTS (A+B+C+D+E) - | T75: =IF(OFFSET(T75,ROW(T$2)-ROW(T75),0)="TT","TT",IF(OFFSET(T75,0,COLUMN($M75)-COLUMN(T75))="%",ROUND((OFFSET(T75,-2,0)-OFFSET(T75,-21,0))*0.07,2),IF(OFFSET(T75,0,COLUMN($M75)-COLUMN(T75))="V",ROUND(OFFSET(T75,0,-2)*OFFSET(T75,0,-1),2),SUMIF(INDIRECT(ADDRESS(MATCH("START"&OFFSET(T75,0,COLUMN($B75)-COLUMN(T75)),$A:$A,0),$C75+COLUMN($E75)+1)&":"&ADDRESS(MATCH("END"&OFFSET(T75,0,COLUMN($B75)-COLUMN(T75)),$A:$A,0),$C75+COLUMN($E75)+1),TRUE),INDIRECT(ADDRESS(ROW(T75),$C75+COLUMN($E75)),TRUE),INDIRECT(ADDRESS(MATCH("START"&OFFSET(T75,0,COLUMN($B75)-COLUMN(T75)),$A:$A,0),COLUMN(T75))&":"&ADDRESS(MATCH("END"&OFFSET(T75,0,COLUMN($B75)-COLUMN(T75)),$A:$A,0),COLUMN(T75)),TRUE))))) -> 0 | U75: =IF(OFFSET(U75,ROW(U$2)-ROW(U75),0)="TT",SUMIF(INDIRECT(ADDRESS(2,COLUMN($Q75)+1) & ":" & ADDRESS(2,COLUMN(U75)-1),TRUE),"TBE",INDIRECT(ADDRESS(ROW(U75), COLUMN($Q75)+1) & ":" & ADDRESS(ROW(U75),COLUMN(U75)-1),TRUE)),IF(OFFSET(U75,ROW(U$2)-ROW(U75),0)="TBE",SUMIF(INDIRECT(ADDRESS(2,MATCH(INT(OFFSET(U75,ROW(U$2)-ROW(U75),-2)),$2:$2,0)) & ":" & ADDRESS(2,COLUMN(U75)-1),TRUE),"T",INDIRECT(ADDRESS(ROW(U75), MATCH(INT(OFFSET(U75,ROW(U$2)-ROW(U75),-2)),$2:$2,0)) & ":" & ADDRESS(ROW(U75),COLUMN(U75)-1),TRUE)),IF(OFFSET(U75,0,COLUMN($M75)-COLUMN(U75))="V",OFFSET(U75,0,-2)*OFFSET(U75,0,-1),"TOTAL"))) -> 0
A77: =IF(ISNUMBER(OFFSET(A77,0,13)),"START",IF(AND(OFFSET(A77,0,2)=0,OFFSET(A77,0,4)="GT"),"END",""))&OFFSET(A77,0,1) -> STARTWP003 | B77: =IF(ISNUMBER(OFFSET(B77,0,12)),"WP" & TEXT(OFFSET(B77,0,12),"000"),OFFSET(B77,-1,0)) -> WP003 | N77: 3 | O77: =""&VLOOKUP(OFFSET(N77,1,0),'Work Packages List'!A:B,2,FALSE)
A78: =IF(ISNUMBER(OFFSET(A78,0,12)),"START",IF(AND(OFFSET(A78,0,2)=0,OFFSET(A78,0,4)="GT"),"END",""))&OFFSET(A78,0,1) -> WP003 | B78: =IF(ISNUMBER(OFFSET(B78,0,11)),"WP" & TEXT(OFFSET(B78,0,11),"000"),OFFSET(B78,-1,0)) -> WP003 | C78: 4 | D78: WPRow.A | H78: TTA | I78: TA | M78: T | N78: ="WP " & TEXT(OFFSET(N78,-1,0),"000") -> WP 003 | O78: A. DIRECT PERSONNEL COSTS | R78: =IF(OFFSET(R78,ROW(R$2)-ROW(R78),0)="TT","TT",IF(OFFSET(R78,0,COLUMN($M78)-COLUMN(R78))="%",ROUND(OFFSET(R78,-2,0)*0.07,0),IF(OFFSET(R78,0,COLUMN($M78)-COLUMN(R78))="V","x",SUMIF(INDIRECT(ADDRESS(MATCH("START"&OFFSET(R78,0,COLUMN($B78)-COLUMN(R78)),$A:$A,0),$C78+COLUMN($E78)+1)&":"&ADDRESS(MATCH("END"&OFFSET(R78,0,COLUMN($B78)-COLUMN(R78)),$A:$A,0),$C78+COLUMN($E78)+1),TRUE),INDIRECT(ADDRESS(ROW(R78),$C78+COLUMN($E78)),TRUE),INDIRECT(ADDRESS(MATCH("START"&OFFSET(R78,0,COLUMN($B78)-COLUMN(R78)),$A:$A,0),COLUMN(R78))&":"&ADDRESS(MATCH("END"&OFFSET(R78,0,COLUMN($B78)-COLUMN(R78)),$A:$A,0),COLUMN(R78)),TRUE))))) -> 0 | T78: =IF(OFFSET(T78,ROW(T$2)-ROW(T78),0)="TT","TT",IF(OFFSET(T78,0,COLUMN($M78)-COLUMN(T78))="%",ROUND((OFFSET(T78,-2,0)-OFFSET(T78,-21,0))*0.07,2),IF(OFFSET(T78,0,COLUMN($M78)-COLUMN(T78))="V",ROUND(OFFSET(T78,0,-2)*OFFSET(T78,0,-1),2),SUMIF(INDIRECT(ADDRESS(MATCH("START"&OFFSET(T78,0,COLUMN($B78)-COLUMN(T78)),$A:$A,0),$C78+COLUMN($E78)+1)&":"&ADDRESS(MATCH("END"&OFFSET(T78,0,COLUMN($B78)-COLUMN(T78)),$A:$A,0),$C78+COLUMN($E78)+1),TRUE),INDIRECT(ADDRESS(ROW(T78),$C78+COLUMN($E78)),TRUE),INDIRECT(ADDRESS(MATCH("START"&OFFSET(T78,0,COLUMN($B78)-COLUMN(T78)),$A:$A,0),COLUMN(T78))&":"&ADDRESS(MATCH("END"&OFFSET(T78,0,COLUMN($B78)-COLUMN(T78)),$A:$A,0),COLUMN(T78)),TRUE))))) -> 0 | U78: =IF(OFFSET(U78,ROW(U$2)-ROW(U78),0)="TT",SUMIF(INDIRECT(ADDRESS(2,COLUMN($Q78)+1) & ":" & ADDRESS(2,COLUMN(U78)-1),TRUE),"TBE",INDIRECT(ADDRESS(ROW(U78), COLUMN($Q78)+1) & ":" & ADDRESS(ROW(U78),COLUMN(U78)-1),TRUE)),IF(OFFSET(U78,ROW(U$2)-ROW(U78),0)="TBE",SUMIF(INDIRECT(ADDRESS(2,MATCH(INT(OFFSET(U78,ROW(U$2)-ROW(U78),-2)),$2:$2,0)) & ":" & ADDRESS(2,COLUMN(U78)-1),TRUE),"T",INDIRECT(ADDRESS(ROW(U78), MATCH(INT(OFFSET(U78,ROW(U$2)-ROW(U78),-2)),$2:$2,0)) & ":" & ADDRESS(ROW(U78),COLUMN(U78)-1),TRUE)),IF(OFFSET(U78,0,COLUMN($M78)-COLUMN(U78))="V",OFFSET(U78,0,-2)*OFFSET(U78,0,-1),"TOTAL"))) -> 0
A79: =IF(ISNUMBER(OFFSET(A79,0,12)),"START",IF(AND(OFFSET(A79,0,2)=0,OFFSET(A79,0,4)="GT"),"END",""))&OFFSET(A79,0,1) -> WP003 | B79: =IF(ISNUMBER(OFFSET(B79,0,11)),"WP" & TEXT(OFFSET(B79,0,11),"000"),OFFSET(B79,-1,0)) -> WP003 | C79: 6 | D79: WPRow.B | J79: TA | K79: T1 | M79: T | P79: A1. Employees (or equivalent) person months | R79: =IF(OFFSET(R79,ROW(R$2)-ROW(R79),0)="TT","TT",IF(OFFSET(R79,0,COLUMN($M79)-COLUMN(R79))="%",ROUND(OFFSET(R79,-2,0)*0.07,0),IF(OFFSET(R79,0,COLUMN($M79)-COLUMN(R79))="V","x",SUMIF(INDIRECT(ADDRESS(MATCH("START"&OFFSET(R79,0,COLUMN($B79)-COLUMN(R79)),$A:$A,0),$C79+COLUMN($E79)+1)&":"&ADDRESS(MATCH("END"&OFFSET(R79,0,COLUMN($B79)-COLUMN(R79)),$A:$A,0),$C79+COLUMN($E79)+1),TRUE),INDIRECT(ADDRESS(ROW(R79),$C79+COLUMN($E79)),TRUE),INDIRECT(ADDRESS(MATCH("START"&OFFSET(R79,0,COLUMN($B79)-COLUMN(R79)),$A:$A,0),COLUMN(R79))&":"&ADDRESS(MATCH("END"&OFFSET(R79,0,COLUMN($B79)-COLUMN(R79)),$A:$A,0),COLUMN(R79)),TRUE))))) -> 0 | T79: =IF(OFFSET(T79,ROW(T$2)-ROW(T79),0)="TT","TT",IF(OFFSET(T79,0,COLUMN($M79)-COLUMN(T79))="%",ROUND((OFFSET(T79,-2,0)-OFFSET(T79,-21,0))*0.07,2),IF(OFFSET(T79,0,COLUMN($M79)-COLUMN(T79))="V",ROUND(OFFSET(T79,0,-2)*OFFSET(T79,0,-1),2),SUMIF(INDIRECT(ADDRESS(MATCH("START"&OFFSET(T79,0,COLUMN($B79)-COLUMN(T79)),$A:$A,0),$C79+COLUMN($E79)+1)&":"&ADDRESS(MATCH("END"&OFFSET(T79,0,COLUMN($B79)-COLUMN(T79)),$A:$A,0),$C79+COLUMN($E79)+1),TRUE),INDIRECT(ADDRESS(ROW(T79),$C79+COLUMN($E79)),TRUE),INDIRECT(ADDRESS(MATCH("START"&OFFSET(T79,0,COLUMN($B79)-COLUMN(T79)),$A:$A,0),COLUMN(T79))&":"&ADDRESS(MATCH("END"&OFFSET(T79,0,COLUMN($B79)-COLUMN(T79)),$A:$A,0),COLUMN(T79)),TRUE))))) -> 0 | U79: =IF(OFFSET(U79,ROW(U$2)-ROW(U79),0)="TT",SUMIF(INDIRECT(ADDRESS(2,COLUMN($Q79)+1) & ":" & ADDRESS(2,COLUMN(U79)-1),TRUE),"TBE",INDIRECT(ADDRESS(ROW(U79), COLUMN($Q79)+1) & ":" & ADDRESS(ROW(U79),COLUMN(U79)-1),TRUE)),IF(OFFSET(U79,ROW(U$2)-ROW(U79),0)="TBE",SUMIF(INDIRECT(ADDRESS(2,MATCH(INT(OFFSET(U79,ROW(U$2)-ROW(U79),-2)),$2:$2,0)) & ":" & ADDRESS(2,COLUMN(U79)-1),TRUE),"T",INDIRECT(ADDRESS(ROW(U79), MATCH(INT(OFFSET(U79,ROW(U$2)-ROW(U79),-2)),$2:$2,0)) & ":" & ADDRESS(ROW(U79),COLUMN(U79)-1),TRUE)),IF(OFFSET(U79,0,COLUMN($M79)-COLUMN(U79))="V",OFFSET(U79,0,-2)*OFFSET(U79,0,-1),"TOTAL"))) -> 0
A80: =IF(ISNUMBER(OFFSET(A80,0,12)),"START",IF(AND(OFFSET(A80,0,2)=0,OFFSET(A80,0,4)="GT"),"END",""))&OFFSET(A80,0,1) -> WP003 | B80: =IF(ISNUMBER(OFFSET(B80,0,11)),"WP" & TEXT(OFFSET(B80,0,11),"000"),OFFSET(B80,-1,0)) -> WP003 | C80: 7 | D80: WPRow.C | L80: T1 | M80: V | Q80: =EMP_TYPE1 -> Type 1 | T80: =IF(OFFSET(T80,ROW(T$2)-ROW(T80),0)="TT","TT",IF(OFFSET(T80,0,COLUMN($M80)-COLUMN(T80))="%",ROUND((OFFSET(T80,-2,0)-OFFSET(T80,-21,0))*0.07,2),IF(OFFSET(T80,0,COLUMN($M80)-COLUMN(T80))="V",ROUND(OFFSET(T80,0,-2)*OFFSET(T80,0,-1),2),SUMIF(INDIRECT(ADDRESS(MATCH("START"&OFFSET(T80,0,COLUMN($B80)-COLUMN(T80)),$A:$A,0),$C80+COLUMN($E80)+1)&":"&ADDRESS(MATCH("END"&OFFSET(T80,0,COLUMN($B80)-COLUMN(T80)),$A:$A,0),$C80+COLUMN($E80)+1),TRUE),INDIRECT(ADDRESS(ROW(T80),$C80+COLUMN($E80)),TRUE),INDIRECT(ADDRESS(MATCH("START"&OFFSET(T80,0,COLUMN($B80)-COLUMN(T80)),$A:$A,0),COLUMN(T80))&":"&ADDRESS(MATCH("END"&OFFSET(T80,0,COLUMN($B80)-COLUMN(T80)),$A:$A,0),COLUMN(T80)),TRUE))))) -> 0 | U80: =IF(OFFSET(U80,ROW(U$2)-ROW(U80),0)="TT",SUMIF(INDIRECT(ADDRESS(2,COLUMN($Q80)+1) & ":" & ADDRESS(2,COLUMN(U80)-1),TRUE),"TBE",INDIRECT(ADDRESS(ROW(U80), COLUMN($Q80)+1) & ":" & ADDRESS(ROW(U80),COLUMN(U80)-1),TRUE)),IF(OFFSET(U80,ROW(U$2)-ROW(U80),0)="TBE",SUMIF(INDIRECT(ADDRESS(2,MATCH(INT(OFFSET(U80,ROW(U$2)-ROW(U80),-2)),$2:$2,0)) & ":" & ADDRESS(2,COLUMN(U80)-1),TRUE),"T",INDIRECT(ADDRESS(ROW(U80), MATCH(INT(OFFSET(U80,ROW(U$2)-ROW(U80),-2)),$2:$2,0)) & ":" & ADDRESS(ROW(U80),COLUMN(U80)-1),TRUE)),IF(OFFSET(U80,0,COLUMN($M80)-COLUMN(U80))="V",OFFSET(U80,0,-2)*OFFSET(U80,0,-1),"TOTAL"))) -> 0
A81: =IF(ISNUMBER(OFFSET(A81,0,12)),"START",IF(AND(OFFSET(A81,0,2)=0,OFFSET(A81,0,4)="GT"),"END",""))&OFFSET(A81,0,1) -> WP003 | B81: =IF(ISNUMBER(OFFSET(B81,0,11)),"WP" & TEXT(OFFSET(B81,0,11),"000"),OFFSET(B81,-1,0)) -> WP003 | C81: 7 | D81: WPRow.D | L81: T1 | M81: V | Q81: =EMP_TYPE2 -> Type 2 | T81: =IF(OFFSET(T81,ROW(T$2)-ROW(T81),0)="TT","TT",IF(OFFSET(T81,0,COLUMN($M81)-COLUMN(T81))="%",ROUND((OFFSET(T81,-2,0)-OFFSET(T81,-21,0))*0.07,2),IF(OFFSET(T81,0,COLUMN($M81)-COLUMN(T81))="V",ROUND(OFFSET(T81,0,-2)*OFFSET(T81,0,-1),2),SUMIF(INDIRECT(ADDRESS(MATCH("START"&OFFSET(T81,0,COLUMN($B81)-COLUMN(T81)),$A:$A,0),$C81+COLUMN($E81)+1)&":"&ADDRESS(MATCH("END"&OFFSET(T81,0,COLUMN($B81)-COLUMN(T81)),$A:$A,0),$C81+COLUMN($E81)+1),TRUE),INDIRECT(ADDRESS(ROW(T81),$C81+COLUMN($E81)),TRUE),INDIRECT(ADDRESS(MATCH("START"&OFFSET(T81,0,COLUMN($B81)-COLUMN(T81)),$A:$A,0),COLUMN(T81))&":"&ADDRESS(MATCH("END"&OFFSET(T81,0,COLUMN($B81)-COLUMN(T81)),$A:$A,0),COLUMN(T81)),TRUE))))) -> 0 | U81: =IF(OFFSET(U81,ROW(U$2)-ROW(U81),0)="TT",SUMIF(INDIRECT(ADDRESS(2,COLUMN($Q81)+1) & ":" & ADDRESS(2,COLUMN(U81)-1),TRUE),"TBE",INDIRECT(ADDRESS(ROW(U81), COLUMN($Q81)+1) & ":" & ADDRESS(ROW(U81),COLUMN(U81)-1),TRUE)),IF(OFFSET(U81,ROW(U$2)-ROW(U81),0)="TBE",SUMIF(INDIRECT(ADDRESS(2,MATCH(INT(OFFSET(U81,ROW(U$2)-ROW(U81),-2)),$2:$2,0)) & ":" & ADDRESS(2,COLUMN(U81)-1),TRUE),"T",INDIRECT(ADDRESS(ROW(U81), MATCH(INT(OFFSET(U81,ROW(U$2)-ROW(U81),-2)),$2:$2,0)) & ":" & ADDRESS(ROW(U81),COLUMN(U81)-1),TRUE)),IF(OFFSET(U81,0,COLUMN($M81)-COLUMN(U81))="V",OFFSET(U81,0,-2)*OFFSET(U81,0,-1),"TOTAL"))) -> 0
A82: =IF(ISNUMBER(OFFSET(A82,0,12)),"START",IF(AND(OFFSET(A82,0,2)=0,OFFSET(A82,0,4)="GT"),"END",""))&OFFSET(A82,0,1) -> WP003 | B82: =IF(ISNUMBER(OFFSET(B82,0,11)),"WP" & TEXT(OFFSET(B82,0,11),"000"),OFFSET(B82,-1,0)) -> WP003 | C82: 7 | D82: WPRow.E | L82: T1 | M82: V | Q82: =EMP_TYPE3 -> Type 3 | T82: =IF(OFFSET(T82,ROW(T$2)-ROW(T82),0)="TT","TT",IF(OFFSET(T82,0,COLUMN($M82)-COLUMN(T82))="%",ROUND((OFFSET(T82,-2,0)-OFFSET(T82,-21,0))*0.07,2),IF(OFFSET(T82,0,COLUMN($M82)-COLUMN(T82))="V",ROUND(OFFSET(T82,0,-2)*OFFSET(T82,0,-1),2),SUMIF(INDIRECT(ADDRESS(MATCH("START"&OFFSET(T82,0,COLUMN($B82)-COLUMN(T82)),$A:$A,0),$C82+COLUMN($E82)+1)&":"&ADDRESS(MATCH("END"&OFFSET(T82,0,COLUMN($B82)-COLUMN(T82)),$A:$A,0),$C82+COLUMN($E82)+1),TRUE),INDIRECT(ADDRESS(ROW(T82),$C82+COLUMN($E82)),TRUE),INDIRECT(ADDRESS(MATCH("START"&OFFSET(T82,0,COLUMN($B82)-COLUMN(T82)),$A:$A,0),COLUMN(T82))&":"&ADDRESS(MATCH("END"&OFFSET(T82,0,COLUMN($B82)-COLUMN(T82)),$A:$A,0),COLUMN(T82)),TRUE))))) -> 0 | U82: =IF(OFFSET(U82,ROW(U$2)-ROW(U82),0)="TT",SUMIF(INDIRECT(ADDRESS(2,COLUMN($Q82)+1) & ":" & ADDRESS(2,COLUMN(U82)-1),TRUE),"TBE",INDIRECT(ADDRESS(ROW(U82), COLUMN($Q82)+1) & ":" & ADDRESS(ROW(U82),COLUMN(U82)-1),TRUE)),IF(OFFSET(U82,ROW(U$2)-ROW(U82),0)="TBE",SUMIF(INDIRECT(ADDRESS(2,MATCH(INT(OFFSET(U82,ROW(U$2)-ROW(U82),-2)),$2:$2,0)) & ":" & ADDRESS(2,COLUMN(U82)-1),TRUE),"T",INDIRECT(ADDRESS(ROW(U82), MATCH(INT(OFFSET(U82,ROW(U$2)-ROW(U82),-2)),$2:$2,0)) & ":" & ADDRESS(ROW(U82),COLUMN(U82)-1),TRUE)),IF(OFFSET(U82,0,COLUMN($M82)-COLUMN(U82))="V",OFFSET(U82,0,-2)*OFFSET(U82,0,-1),"TOTAL"))) -> 0
A83: =IF(ISNUMBER(OFFSET(A83,0,12)),"START",IF(AND(OFFSET(A83,0,2)=0,OFFSET(A83,0,4)="GT"),"END",""))&OFFSET(A83,0,1) -> WP003 | B83: =IF(ISNUMBER(OFFSET(B83,0,11)),"WP" & TEXT(OFFSET(B83,0,11),"000"),OFFSET(B83,-1,0)) -> WP003 | C83: 7 | D83: WPRow.F | L83: T1 | M83: V | Q83: =EMP_TYPE4 -> Type 4 | T83: =IF(OFFSET(T83,ROW(T$2)-ROW(T83),0)="TT","TT",IF(OFFSET(T83,0,COLUMN($M83)-COLUMN(T83))="%",ROUND((OFFSET(T83,-2,0)-OFFSET(T83,-21,0))*0.07,2),IF(OFFSET(T83,0,COLUMN($M83)-COLUMN(T83))="V",ROUND(OFFSET(T83,0,-2)*OFFSET(T83,0,-1),2),SUMIF(INDIRECT(ADDRESS(MATCH("START"&OFFSET(T83,0,COLUMN($B83)-COLUMN(T83)),$A:$A,0),$C83+COLUMN($E83)+1)&":"&ADDRESS(MATCH("END"&OFFSET(T83,0,COLUMN($B83)-COLUMN(T83)),$A:$A,0),$C83+COLUMN($E83)+1),TRUE),INDIRECT(ADDRESS(ROW(T83),$C83+COLUMN($E83)),TRUE),INDIRECT(ADDRESS(MATCH("START"&OFFSET(T83,0,COLUMN($B83)-COLUMN(T83)),$A:$A,0),COLUMN(T83))&":"&ADDRESS(MATCH("END"&OFFSET(T83,0,COLUMN($B83)-COLUMN(T83)),$A:$A,0),COLUMN(T83)),TRUE))))) -> 0 | U83: =IF(OFFSET(U83,ROW(U$2)-ROW(U83),0)="TT",SUMIF(INDIRECT(ADDRESS(2,COLUMN($Q83)+1) & ":" & ADDRESS(2,COLUMN(U83)-1),TRUE),"TBE",INDIRECT(ADDRESS(ROW(U83), COLUMN($Q83)+1) & ":" & ADDRESS(ROW(U83),COLUMN(U83)-1),TRUE)),IF(OFFSET(U83,ROW(U$2)-ROW(U83),0)="TBE",SUMIF(INDIRECT(ADDRESS(2,MATCH(INT(OFFSET(U83,ROW(U$2)-ROW(U83),-2)),$2:$2,0)) & ":" & ADDRESS(2,COLUMN(U83)-1),TRUE),"T",INDIRECT(ADDRESS(ROW(U83), MATCH(INT(OFFSET(U83,ROW(U$2)-ROW(U83),-2)),$2:$2,0)) & ":" & ADDRESS(ROW(U83),COLUMN(U83)-1),TRUE)),IF(OFFSET(U83,0,COLUMN($M83)-COLUMN(U83))="V",OFFSET(U83,0,-2)*OFFSET(U83,0,-1),"TOTAL"))) -> 0
A84: =IF(ISNUMBER(OFFSET(A84,0,12)),"START",IF(AND(OFFSET(A84,0,2)=0,OFFSET(A84,0,4)="GT"),"END",""))&OFFSET(A84,0,1) -> WP003 | B84: =IF(ISNUMBER(OFFSET(B84,0,11)),"WP" & TEXT(OFFSET(B84,0,11),"000"),OFFSET(B84,-1,0)) -> WP003 | C84: 7 | D84: WPRow.G | L84: T1 | M84: V | Q84: =EMP_OTHER -> Type 5 | T84: =IF(OFFSET(T84,ROW(T$2)-ROW(T84),0)="TT","TT",IF(OFFSET(T84,0,COLUMN($M84)-COLUMN(T84))="%",ROUND((OFFSET(T84,-2,0)-OFFSET(T84,-21,0))*0.07,2),IF(OFFSET(T84,0,COLUMN($M84)-COLUMN(T84))="V",ROUND(OFFSET(T84,0,-2)*OFFSET(T84,0,-1),2),SUMIF(INDIRECT(ADDRESS(MATCH("START"&OFFSET(T84,0,COLUMN($B84)-COLUMN(T84)),$A:$A,0),$C84+COLUMN($E84)+1)&":"&ADDRESS(MATCH("END"&OFFSET(T84,0,COLUMN($B84)-COLUMN(T84)),$A:$A,0),$C84+COLUMN($E84)+1),TRUE),INDIRECT(ADDRESS(ROW(T84),$C84+COLUMN($E84)),TRUE),INDIRECT(ADDRESS(MATCH("START"&OFFSET(T84,0,COLUMN($B84)-COLUMN(T84)),$A:$A,0),COLUMN(T84))&":"&ADDRESS(MATCH("END"&OFFSET(T84,0,COLUMN($B84)-COLUMN(T84)),$A:$A,0),COLUMN(T84)),TRUE))))) -> 0 | U84: =IF(OFFSET(U84,ROW(U$2)-ROW(U84),0)="TT",SUMIF(INDIRECT(ADDRESS(2,COLUMN($Q84)+1) & ":" & ADDRESS(2,COLUMN(U84)-1),TRUE),"TBE",INDIRECT(ADDRESS(ROW(U84), COLUMN($Q84)+1) & ":" & ADDRESS(ROW(U84),COLUMN(U84)-1),TRUE)),IF(OFFSET(U84,ROW(U$2)-ROW(U84),0)="TBE",SUMIF(INDIRECT(ADDRESS(2,MATCH(INT(OFFSET(U84,ROW(U$2)-ROW(U84),-2)),$2:$2,0)) & ":" & ADDRESS(2,COLUMN(U84)-1),TRUE),"T",INDIRECT(ADDRESS(ROW(U84), MATCH(INT(OFFSET(U84,ROW(U$2)-ROW(U84),-2)),$2:$2,0)) & ":" & ADDRESS(ROW(U84),COLUMN(U84)-1),TRUE)),IF(OFFSET(U84,0,COLUMN($M84)-COLUMN(U84))="V",OFFSET(U84,0,-2)*OFFSET(U84,0,-1),"TOTAL"))) -> 0
A85: =IF(ISNUMBER(OFFSET(A85,0,12)),"START",IF(AND(OFFSET(A85,0,2)=0,OFFSET(A85,0,4)="GT"),"END",""))&OFFSET(A85,0,1) -> WP003 | B85: =IF(ISNUMBER(OFFSET(B85,0,11)),"WP" & TEXT(OFFSET(B85,0,11),"000"),OFFSET(B85,-1,0)) -> WP003 | C85: 6 | D85: WPRow.H | J85: TA | M85: V | P85: A.2 Natural persons under direct contract | T85: =IF(OFFSET(T85,ROW(T$2)-ROW(T85),0)="TT","TT",IF(OFFSET(T85,0,COLUMN($M85)-COLUMN(T85))="%",ROUND((OFFSET(T85,-2,0)-OFFSET(T85,-21,0))*0.07,2),IF(OFFSET(T85,0,COLUMN($M85)-COLUMN(T85))="V",ROUND(OFFSET(T85,0,-2)*OFFSET(T85,0,-1),2),SUMIF(INDIRECT(ADDRESS(MATCH("START"&OFFSET(T85,0,COLUMN($B85)-COLUMN(T85)),$A:$A,0),$C85+COLUMN($E85)+1)&":"&ADDRESS(MATCH("END"&OFFSET(T85,0,COLUMN($B85)-COLUMN(T85)),$A:$A,0),$C85+COLUMN($E85)+1),TRUE),INDIRECT(ADDRESS(ROW(T85),$C85+COLUMN($E85)),TRUE),INDIRECT(ADDRESS(MATCH("START"&OFFSET(T85,0,COLUMN($B85)-COLUMN(T85)),$A:$A,0),COLUMN(T85))&":"&ADDRESS(MATCH("END"&OFFSET(T85,0,COLUMN($B85)-COLUMN(T85)),$A:$A,0),COLUMN(T85)),TRUE))))) -> 0 | U85: =IF(OFFSET(U85,ROW(U$2)-ROW(U85),0)="TT",SUMIF(INDIRECT(ADDRESS(2,COLUMN($Q85)+1) & ":" & ADDRESS(2,COLUMN(U85)-1),TRUE),"TBE",INDIRECT(ADDRESS(ROW(U85), COLUMN($Q85)+1) & ":" & ADDRESS(ROW(U85),COLUMN(U85)-1),TRUE)),IF(OFFSET(U85,ROW(U$2)-ROW(U85),0)="TBE",SUMIF(INDIRECT(ADDRESS(2,MATCH(INT(OFFSET(U85,ROW(U$2)-ROW(U85),-2)),$2:$2,0)) & ":" & ADDRESS(2,COLUMN(U85)-1),TRUE),"T",INDIRECT(ADDRESS(ROW(U85), MATCH(INT(OFFSET(U85,ROW(U$2)-ROW(U85),-2)),$2:$2,0)) & ":" & ADDRESS(ROW(U85),COLUMN(U85)-1),TRUE)),IF(OFFSET(U85,0,COLUMN($M85)-COLUMN(U85))="V",OFFSET(U85,0,-2)*OFFSET(U85,0,-1),"TOTAL"))) -> 0
A86: =IF(ISNUMBER(OFFSET(A86,0,12)),"START",IF(AND(OFFSET(A86,0,2)=0,OFFSET(A86,0,4)="GT"),"END",""))&OFFSET(A86,0,1) -> WP003 | B86: =IF(ISNUMBER(OFFSET(B86,0,11)),"WP" & TEXT(OFFSET(B86,0,11),"000"),OFFSET(B86,-1,0)) -> WP003 | C86: 6 | D86: WPRow.I | J86: TA | M86: V | P86: A.3 Seconded persons | T86: =IF(OFFSET(T86,ROW(T$2)-ROW(T86),0)="TT","TT",IF(OFFSET(T86,0,COLUMN($M86)-COLUMN(T86))="%",ROUND((OFFSET(T86,-2,0)-OFFSET(T86,-21,0))*0.07,2),IF(OFFSET(T86,0,COLUMN($M86)-COLUMN(T86))="V",ROUND(OFFSET(T86,0,-2)*OFFSET(T86,0,-1),2),SUMIF(INDIRECT(ADDRESS(MATCH("START"&OFFSET(T86,0,COLUMN($B86)-COLUMN(T86)),$A:$A,0),$C86+COLUMN($E86)+1)&":"&ADDRESS(MATCH("END"&OFFSET(T86,0,COLUMN($B86)-COLUMN(T86)),$A:$A,0),$C86+COLUMN($E86)+1),TRUE),INDIRECT(ADDRESS(ROW(T86),$C86+COLUMN($E86)),TRUE),INDIRECT(ADDRESS(MATCH("START"&OFFSET(T86,0,COLUMN($B86)-COLUMN(T86)),$A:$A,0),COLUMN(T86))&":"&ADDRESS(MATCH("END"&OFFSET(T86,0,COLUMN($B86)-COLUMN(T86)),$A:$A,0),COLUMN(T86)),TRUE))))) -> 0 | U86: =IF(OFFSET(U86,ROW(U$2)-ROW(U86),0)="TT",SUMIF(INDIRECT(ADDRESS(2,COLUMN($Q86)+1) & ":" & ADDRESS(2,COLUMN(U86)-1),TRUE),"TBE",INDIRECT(ADDRESS(ROW(U86), COLUMN($Q86)+1) & ":" & ADDRESS(ROW(U86),COLUMN(U86)-1),TRUE)),IF(OFFSET(U86,ROW(U$2)-ROW(U86),0)="TBE",SUMIF(INDIRECT(ADDRESS(2,MATCH(INT(OFFSET(U86,ROW(U$2)-ROW(U86),-2)),$2:$2,0)) & ":" & ADDRESS(2,COLUMN(U86)-1),TRUE),"T",INDIRECT(ADDRESS(ROW(U86), MATCH(INT(OFFSET(U86,ROW(U$2)-ROW(U86),-2)),$2:$2,0)) & ":" & ADDRESS(ROW(U86),COLUMN(U86)-1),TRUE)),IF(OFFSET(U86,0,COLUMN($M86)-COLUMN(U86))="V",OFFSET(U86,0,-2)*OFFSET(U86,0,-1),"TOTAL"))) -> 0
A87: =IF(ISNUMBER(OFFSET(A87,0,12)),"START",IF(AND(OFFSET(A87,0,2)=0,OFFSET(A87,0,4)="GT"),"END",""))&OFFSET(A87,0,1) -> WP003 | B87: =IF(ISNUMBER(OFFSET(B87,0,11)),"WP" & TEXT(OFFSET(B87,0,11),"000"),OFFSET(B87,-1,0)) -> WP003 | C87: 6 | D87: WPRow.J | J87: TA | M87: V | P87: A.4 SME Owners without salary | T87: =IF(OFFSET(T87,ROW(T$2)-ROW(T87),0)="TT","TT",IF(OFFSET(T87,0,COLUMN($M87)-COLUMN(T87))="%",ROUND((OFFSET(T87,-2,0)-OFFSET(T87,-21,0))*0.07,2),IF(OFFSET(T87,0,COLUMN($M87)-COLUMN(T87))="V",ROUND(OFFSET(T87,0,-2)*OFFSET(T87,0,-1),2),SUMIF(INDIRECT(ADDRESS(MATCH("START"&OFFSET(T87,0,COLUMN($B87)-COLUMN(T87)),$A:$A,0),$C87+COLUMN($E87)+1)&":"&ADDRESS(MATCH("END"&OFFSET(T87,0,COLUMN($B87)-COLUMN(T87)),$A:$A,0),$C87+COLUMN($E87)+1),TRUE),INDIRECT(ADDRESS(ROW(T87),$C87+COLUMN($E87)),TRUE),INDIRECT(ADDRESS(MATCH("START"&OFFSET(T87,0,COLUMN($B87)-COLUMN(T87)),$A:$A,0),COLUMN(T87))&":"&ADDRESS(MATCH("END"&OFFSET(T87,0,COLUMN($B87)-COLUMN(T87)),$A:$A,0),COLUMN(T87)),TRUE))))) -> 0 | U87: =IF(OFFSET(U87,ROW(U$2)-ROW(U87),0)="TT",SUMIF(INDIRECT(ADDRESS(2,COLUMN($Q87)+1) & ":" & ADDRESS(2,COLUMN(U87)-1),TRUE),"TBE",INDIRECT(ADDRESS(ROW(U87), COLUMN($Q87)+1) & ":" & ADDRESS(ROW(U87),COLUMN(U87)-1),TRUE)),IF(OFFSET(U87,ROW(U$2)-ROW(U87),0)="TBE",SUMIF(INDIRECT(ADDRESS(2,MATCH(INT(OFFSET(U87,ROW(U$2)-ROW(U87),-2)),$2:$2,0)) & ":" & ADDRESS(2,COLUMN(U87)-1),TRUE),"T",INDIRECT(ADDRESS(ROW(U87), MATCH(INT(OFFSET(U87,ROW(U$2)-ROW(U87),-2)),$2:$2,0)) & ":" & ADDRESS(ROW(U87),COLUMN(U87)-1),TRUE)),IF(OFFSET(U87,0,COLUMN($M87)-COLUMN(U87))="V",OFFSET(U87,0,-2)*OFFSET(U87,0,-1),"TOTAL"))) -> 0
A88: =IF(ISNUMBER(OFFSET(A88,0,12)),"START",IF(AND(OFFSET(A88,0,2)=0,OFFSET(A88,0,4)="GT"),"END",""))&OFFSET(A88,0,1) -> WP003 | B88: =IF(ISNUMBER(OFFSET(B88,0,11)),"WP" & TEXT(OFFSET(B88,0,11),"000"),OFFSET(B88,-1,0)) -> WP003 | C88: 6 | D88: WPRow.K | J88: TA | M88: V | P88: A.5 Volunteers | T88: =IF(OFFSET(T88,ROW(T$2)-ROW(T88),0)="TT","TT",IF(OFFSET(T88,0,COLUMN($M88)-COLUMN(T88))="%",ROUND((OFFSET(T88,-2,0)-OFFSET(T88,-21,0))*0.07,2),IF(OFFSET(T88,0,COLUMN($M88)-COLUMN(T88))="V",ROUND(OFFSET(T88,0,-2)*OFFSET(T88,0,-1),2),SUMIF(INDIRECT(ADDRESS(MATCH("START"&OFFSET(T88,0,COLUMN($B88)-COLUMN(T88)),$A:$A,0),$C88+COLUMN($E88)+1)&":"&ADDRESS(MATCH("END"&OFFSET(T88,0,COLUMN($B88)-COLUMN(T88)),$A:$A,0),$C88+COLUMN($E88)+1),TRUE),INDIRECT(ADDRESS(ROW(T88),$C88+COLUMN($E88)),TRUE),INDIRECT(ADDRESS(MATCH("START"&OFFSET(T88,0,COLUMN($B88)-COLUMN(T88)),$A:$A,0),COLUMN(T88))&":"&ADDRESS(MATCH("END"&OFFSET(T88,0,COLUMN($B88)-COLUMN(T88)),$A:$A,0),COLUMN(T88)),TRUE))))) -> 0 | U88: =IF(OFFSET(U88,ROW(U$2)-ROW(U88),0)="TT",SUMIF(INDIRECT(ADDRESS(2,COLUMN($Q88)+1) & ":" & ADDRESS(2,COLUMN(U88)-1),TRUE),"TBE",INDIRECT(ADDRESS(ROW(U88), COLUMN($Q88)+1) & ":" & ADDRESS(ROW(U88),COLUMN(U88)-1),TRUE)),IF(OFFSET(U88,ROW(U$2)-ROW(U88),0)="TBE",SUMIF(INDIRECT(ADDRESS(2,MATCH(INT(OFFSET(U88,ROW(U$2)-ROW(U88),-2)),$2:$2,0)) & ":" & ADDRESS(2,COLUMN(U88)-1),TRUE),"T",INDIRECT(ADDRESS(ROW(U88), MATCH(INT(OFFSET(U88,ROW(U$2)-ROW(U88),-2)),$2:$2,0)) & ":" & ADDRESS(ROW(U88),COLUMN(U88)-1),TRUE)),IF(OFFSET(U88,0,COLUMN($M88)-COLUMN(U88))="V",OFFSET(U88,0,-2)*OFFSET(U88,0,-1),"TOTAL"))) -> 0
A89: =IF(ISNUMBER(OFFSET(A89,0,12)),"START",IF(AND(OFFSET(A89,0,2)=0,OFFSET(A89,0,4)="GT"),"END",""))&OFFSET(A89,0,1) -> WP003 | B89: =IF(ISNUMBER(OFFSET(B89,0,11)),"WP" & TEXT(OFFSET(B89,0,11),"000"),OFFSET(B89,-1,0)) -> WP003 | C89: 4 | D89: WPRow.L | H89: TTA | I89: TB | M89: V | O89: B. Subcontracting costs (please specify details under worksheet "Comments") | T89: =IF(OFFSET(T89,ROW(T$2)-ROW(T89),0)="TT","TT",IF(OFFSET(T89,0,COLUMN($M89)-COLUMN(T89))="%",ROUND((OFFSET(T89,-2,0)-OFFSET(T89,-21,0))*0.07,2),IF(OFFSET(T89,0,COLUMN($M89)-COLUMN(T89))="V",ROUND(OFFSET(T89,0,-2)*OFFSET(T89,0,-1),2),SUMIF(INDIRECT(ADDRESS(MATCH("START"&OFFSET(T89,0,COLUMN($B89)-COLUMN(T89)),$A:$A,0),$C89+COLUMN($E89)+1)&":"&ADDRESS(MATCH("END"&OFFSET(T89,0,COLUMN($B89)-COLUMN(T89)),$A:$A,0),$C89+COLUMN($E89)+1),TRUE),INDIRECT(ADDRESS(ROW(T89),$C89+COLUMN($E89)),TRUE),INDIRECT(ADDRESS(MATCH("START"&OFFSET(T89,0,COLUMN($B89)-COLUMN(T89)),$A:$A,0),COLUMN(T89))&":"&ADDRESS(MATCH("END"&OFFSET(T89,0,COLUMN($B89)-COLUMN(T89)),$A:$A,0),COLUMN(T89)),TRUE))))) -> 0 | U89: =IF(OFFSET(U89,ROW(U$2)-ROW(U89),0)="TT",SUMIF(INDIRECT(ADDRESS(2,COLUMN($Q89)+1) & ":" & ADDRESS(2,COLUMN(U89)-1),TRUE),"TBE",INDIRECT(ADDRESS(ROW(U89), COLUMN($Q89)+1) & ":" & ADDRESS(ROW(U89),COLUMN(U89)-1),TRUE)),IF(OFFSET(U89,ROW(U$2)-ROW(U89),0)="TBE",SUMIF(INDIRECT(ADDRESS(2,MATCH(INT(OFFSET(U89,ROW(U$2)-ROW(U89),-2)),$2:$2,0)) & ":" & ADDRESS(2,COLUMN(U89)-1),TRUE),"T",INDIRECT(ADDRESS(ROW(U89), MATCH(INT(OFFSET(U89,ROW(U$2)-ROW(U89),-2)),$2:$2,0)) & ":" & ADDRESS(ROW(U89),COLUMN(U89)-1),TRUE)),IF(OFFSET(U89,0,COLUMN($M89)-COLUMN(U89))="V",OFFSET(U89,0,-2)*OFFSET(U89,0,-1),"TOTAL"))) -> 0
A90: =IF(ISNUMBER(OFFSET(A90,0,12)),"START",IF(AND(OFFSET(A90,0,2)=0,OFFSET(A90,0,4)="GT"),"END",""))&OFFSET(A90,0,1) -> WP003 | B90: =IF(ISNUMBER(OFFSET(B90,0,11)),"WP" & TEXT(OFFSET(B90,0,11),"000"),OFFSET(B90,-1,0)) -> WP003 | C90: 4 | D90: WPRow.M | H90: TTA | I90: TC | M90: T | O90: C. Purchase costs | T90: =IF(OFFSET(T90,ROW(T$2)-ROW(T90),0)="TT","TT",IF(OFFSET(T90,0,COLUMN($M90)-COLUMN(T90))="%",ROUND((OFFSET(T90,-2,0)-OFFSET(T90,-21,0))*0.07,2),IF(OFFSET(T90,0,COLUMN($M90)-COLUMN(T90))="V",ROUND(OFFSET(T90,0,-2)*OFFSET(T90,0,-1),2),SUMIF(INDIRECT(ADDRESS(MATCH("START"&OFFSET(T90,0,COLUMN($B90)-COLUMN(T90)),$A:$A,0),$C90+COLUMN($E90)+1)&":"&ADDRESS(MATCH("END"&OFFSET(T90,0,COLUMN($B90)-COLUMN(T90)),$A:$A,0),$C90+COLUMN($E90)+1),TRUE),INDIRECT(ADDRESS(ROW(T90),$C90+COLUMN($E90)),TRUE),INDIRECT(ADDRESS(MATCH("START"&OFFSET(T90,0,COLUMN($B90)-COLUMN(T90)),$A:$A,0),COLUMN(T90))&":"&ADDRESS(MATCH("END"&OFFSET(T90,0,COLUMN($B90)-COLUMN(T90)),$A:$A,0),COLUMN(T90)),TRUE))))) -> 0 | U90: =IF(OFFSET(U90,ROW(U$2)-ROW(U90),0)="TT",SUMIF(INDIRECT(ADDRESS(2,COLUMN($Q90)+1) & ":" & ADDRESS(2,COLUMN(U90)-1),TRUE),"TBE",INDIRECT(ADDRESS(ROW(U90), COLUMN($Q90)+1) & ":" & ADDRESS(ROW(U90),COLUMN(U90)-1),TRUE)),IF(OFFSET(U90,ROW(U$2)-ROW(U90),0)="TBE",SUMIF(INDIRECT(ADDRESS(2,MATCH(INT(OFFSET(U90,ROW(U$2)-ROW(U90),-2)),$2:$2,0)) & ":" & ADDRESS(2,COLUMN(U90)-1),TRUE),"T",INDIRECT(ADDRESS(ROW(U90), MATCH(INT(OFFSET(U90,ROW(U$2)-ROW(U90),-2)),$2:$2,0)) & ":" & ADDRESS(ROW(U90),COLUMN(U90)-1),TRUE)),IF(OFFSET(U90,0,COLUMN($M90)-COLUMN(U90))="V",OFFSET(U90,0,-2)*OFFSET(U90,0,-1),"TOTAL"))) -> 0
A91: =IF(ISNUMBER(OFFSET(A91,0,12)),"START",IF(AND(OFFSET(A91,0,2)=0,OFFSET(A91,0,4)="GT"),"END",""))&OFFSET(A91,0,1) -> WP003 | B91: =IF(ISNUMBER(OFFSET(B91,0,11)),"WP" & TEXT(OFFSET(B91,0,11),"000"),OFFSET(B91,-1,0)) -> WP003 | C91: 6 | D91: WPRow.N | J91: TC | K91: T3 | M91: T | P91: C.1 Travel and subsistence per travel or day | T91: =IF(OFFSET(T91,ROW(T$2)-ROW(T91),0)="TT","TT",IF(OFFSET(T91,0,COLUMN($M91)-COLUMN(T91))="%",ROUND((OFFSET(T91,-2,0)-OFFSET(T91,-21,0))*0.07,2),IF(OFFSET(T91,0,COLUMN($M91)-COLUMN(T91))="V",ROUND(OFFSET(T91,0,-2)*OFFSET(T91,0,-1),2),SUMIF(INDIRECT(ADDRESS(MATCH("START"&OFFSET(T91,0,COLUMN($B91)-COLUMN(T91)),$A:$A,0),$C91+COLUMN($E91)+1)&":"&ADDRESS(MATCH("END"&OFFSET(T91,0,COLUMN($B91)-COLUMN(T91)),$A:$A,0),$C91+COLUMN($E91)+1),TRUE),INDIRECT(ADDRESS(ROW(T91),$C91+COLUMN($E91)),TRUE),INDIRECT(ADDRESS(MATCH("START"&OFFSET(T91,0,COLUMN($B91)-COLUMN(T91)),$A:$A,0),COLUMN(T91))&":"&ADDRESS(MATCH("END"&OFFSET(T91,0,COLUMN($B91)-COLUMN(T91)),$A:$A,0),COLUMN(T91)),TRUE))))) -> 0 | U91: =IF(OFFSET(U91,ROW(U$2)-ROW(U91),0)="TT",SUMIF(INDIRECT(ADDRESS(2,COLUMN($Q91)+1) & ":" & ADDRESS(2,COLUMN(U91)-1),TRUE),"TBE",INDIRECT(ADDRESS(ROW(U91), COLUMN($Q91)+1) & ":" & ADDRESS(ROW(U91),COLUMN(U91)-1),TRUE)),IF(OFFSET(U91,ROW(U$2)-ROW(U91),0)="TBE",SUMIF(INDIRECT(ADDRESS(2,MATCH(INT(OFFSET(U91,ROW(U$2)-ROW(U91),-2)),$2:$2,0)) & ":" & ADDRESS(2,COLUMN(U91)-1),TRUE),"T",INDIRECT(ADDRESS(ROW(U91), MATCH(INT(OFFSET(U91,ROW(U$2)-ROW(U91),-2)),$2:$2,0)) & ":" & ADDRESS(ROW(U91),COLUMN(U91)-1),TRUE)),IF(OFFSET(U91,0,COLUMN($M91)-COLUMN(U91))="V",OFFSET(U91,0,-2)*OFFSET(U91,0,-1),"TOTAL"))) -> 0
A92: =IF(ISNUMBER(OFFSET(A92,0,12)),"START",IF(AND(OFFSET(A92,0,2)=0,OFFSET(A92,0,4)="GT"),"END",""))&OFFSET(A92,0,1) -> WP003 | B92: =IF(ISNUMBER(OFFSET(B92,0,11)),"WP" & TEXT(OFFSET(B92,0,11),"000"),OFFSET(B92,-1,0)) -> WP003 | C92: 7 | D92: WPRow.O | L92: T3 | M92: V | Q92: Travel | T92: =IF(OFFSET(T92,ROW(T$2)-ROW(T92),0)="TT","TT",IF(OFFSET(T92,0,COLUMN($M92)-COLUMN(T92))="%",ROUND((OFFSET(T92,-2,0)-OFFSET(T92,-21,0))*0.07,2),IF(OFFSET(T92,0,COLUMN($M92)-COLUMN(T92))="V",ROUND(OFFSET(T92,0,-2)*OFFSET(T92,0,-1),2),SUMIF(INDIRECT(ADDRESS(MATCH("START"&OFFSET(T92,0,COLUMN($B92)-COLUMN(T92)),$A:$A,0),$C92+COLUMN($E92)+1)&":"&ADDRESS(MATCH("END"&OFFSET(T92,0,COLUMN($B92)-COLUMN(T92)),$A:$A,0),$C92+COLUMN($E92)+1),TRUE),INDIRECT(ADDRESS(ROW(T92),$C92+COLUMN($E92)),TRUE),INDIRECT(ADDRESS(MATCH("START"&OFFSET(T92,0,COLUMN($B92)-COLUMN(T92)),$A:$A,0),COLUMN(T92))&":"&ADDRESS(MATCH("END"&OFFSET(T92,0,COLUMN($B92)-COLUMN(T92)),$A:$A,0),COLUMN(T92)),TRUE))))) -> 0 | U92: =IF(OFFSET(U92,ROW(U$2)-ROW(U92),0)="TT",SUMIF(INDIRECT(ADDRESS(2,COLUMN($Q92)+1) & ":" & ADDRESS(2,COLUMN(U92)-1),TRUE),"TBE",INDIRECT(ADDRESS(ROW(U92), COLUMN($Q92)+1) & ":" & ADDRESS(ROW(U92),COLUMN(U92)-1),TRUE)),IF(OFFSET(U92,ROW(U$2)-ROW(U92),0)="TBE",SUMIF(INDIRECT(ADDRESS(2,MATCH(INT(OFFSET(U92,ROW(U$2)-ROW(U92),-2)),$2:$2,0)) & ":" & ADDRESS(2,COLUMN(U92)-1),TRUE),"T",INDIRECT(ADDRESS(ROW(U92), MATCH(INT(OFFSET(U92,ROW(U$2)-ROW(U92),-2)),$2:$2,0)) & ":" & ADDRESS(ROW(U92),COLUMN(U92)-1),TRUE)),IF(OFFSET(U92,0,COLUMN($M92)-COLUMN(U92))="V",OFFSET(U92,0,-2)*OFFSET(U92,0,-1),"TOTAL"))) -> 0
A93: =IF(ISNUMBER(OFFSET(A93,0,12)),"START",IF(AND(OFFSET(A93,0,2)=0,OFFSET(A93,0,4)="GT"),"END",""))&OFFSET(A93,0,1) -> WP003 | B93: =IF(ISNUMBER(OFFSET(B93,0,11)),"WP" & TEXT(OFFSET(B93,0,11),"000"),OFFSET(B93,-1,0)) -> WP003 | C93: 7 | D93: WPRow.P | L93: T3 | M93: V | Q93: Accommodation | T93: =IF(OFFSET(T93,ROW(T$2)-ROW(T93),0)="TT","TT",IF(OFFSET(T93,0,COLUMN($M93)-COLUMN(T93))="%",ROUND((OFFSET(T93,-2,0)-OFFSET(T93,-21,0))*0.07,2),IF(OFFSET(T93,0,COLUMN($M93)-COLUMN(T93))="V",ROUND(OFFSET(T93,0,-2)*OFFSET(T93,0,-1),2),SUMIF(INDIRECT(ADDRESS(MATCH("START"&OFFSET(T93,0,COLUMN($B93)-COLUMN(T93)),$A:$A,0),$C93+COLUMN($E93)+1)&":"&ADDRESS(MATCH("END"&OFFSET(T93,0,COLUMN($B93)-COLUMN(T93)),$A:$A,0),$C93+COLUMN($E93)+1),TRUE),INDIRECT(ADDRESS(ROW(T93),$C93+COLUMN($E93)),TRUE),INDIRECT(ADDRESS(MATCH("START"&OFFSET(T93,0,COLUMN($B93)-COLUMN(T93)),$A:$A,0),COLUMN(T93))&":"&ADDRESS(MATCH("END"&OFFSET(T93,0,COLUMN($B93)-COLUMN(T93)),$A:$A,0),COLUMN(T93)),TRUE))))) -> 0 | U93: =IF(OFFSET(U93,ROW(U$2)-ROW(U93),0)="TT",SUMIF(INDIRECT(ADDRESS(2,COLUMN($Q93)+1) & ":" & ADDRESS(2,COLUMN(U93)-1),TRUE),"TBE",INDIRECT(ADDRESS(ROW(U93), COLUMN($Q93)+1) & ":" & ADDRESS(ROW(U93),COLUMN(U93)-1),TRUE)),IF(OFFSET(U93,ROW(U$2)-ROW(U93),0)="TBE",SUMIF(INDIRECT(ADDRESS(2,MATCH(INT(OFFSET(U93,ROW(U$2)-ROW(U93),-2)),$2:$2,0)) & ":" & ADDRESS(2,COLUMN(U93)-1),TRUE),"T",INDIRECT(ADDRESS(ROW(U93), MATCH(INT(OFFSET(U93,ROW(U$2)-ROW(U93),-2)),$2:$2,0)) & ":" & ADDRESS(ROW(U93),COLUMN(U93)-1),TRUE)),IF(OFFSET(U93,0,COLUMN($M93)-COLUMN(U93))="V",OFFSET(U93,0,-2)*OFFSET(U93,0,-1),"TOTAL"))) -> 0
A94: =IF(ISNUMBER(OFFSET(A94,0,12)),"START",IF(AND(OFFSET(A94,0,2)=0,OFFSET(A94,0,4)="GT"),"END",""))&OFFSET(A94,0,1) -> WP003 | B94: =IF(ISNUMBER(OFFSET(B94,0,11)),"WP" & TEXT(OFFSET(B94,0,11),"000"),OFFSET(B94,-1,0)) -> WP003 | C94: 7 | D94: WPRow.Q | L94: T3 | M94: V | Q94: Subsistence | T94: =IF(OFFSET(T94,ROW(T$2)-ROW(T94),0)="TT","TT",IF(OFFSET(T94,0,COLUMN($M94)-COLUMN(T94))="%",ROUND((OFFSET(T94,-2,0)-OFFSET(T94,-21,0))*0.07,2),IF(OFFSET(T94,0,COLUMN($M94)-COLUMN(T94))="V",ROUND(OFFSET(T94,0,-2)*OFFSET(T94,0,-1),2),SUMIF(INDIRECT(ADDRESS(MATCH("START"&OFFSET(T94,0,COLUMN($B94)-COLUMN(T94)),$A:$A,0),$C94+COLUMN($E94)+1)&":"&ADDRESS(MATCH("END"&OFFSET(T94,0,COLUMN($B94)-COLUMN(T94)),$A:$A,0),$C94+COLUMN($E94)+1),TRUE),INDIRECT(ADDRESS(ROW(T94),$C94+COLUMN($E94)),TRUE),INDIRECT(ADDRESS(MATCH("START"&OFFSET(T94,0,COLUMN($B94)-COLUMN(T94)),$A:$A,0),COLUMN(T94))&":"&ADDRESS(MATCH("END"&OFFSET(T94,0,COLUMN($B94)-COLUMN(T94)),$A:$A,0),COLUMN(T94)),TRUE))))) -> 0 | U94: =IF(OFFSET(U94,ROW(U$2)-ROW(U94),0)="TT",SUMIF(INDIRECT(ADDRESS(2,COLUMN($Q94)+1) & ":" & ADDRESS(2,COLUMN(U94)-1),TRUE),"TBE",INDIRECT(ADDRESS(ROW(U94), COLUMN($Q94)+1) & ":" & ADDRESS(ROW(U94),COLUMN(U94)-1),TRUE)),IF(OFFSET(U94,ROW(U$2)-ROW(U94),0)="TBE",SUMIF(INDIRECT(ADDRESS(2,MATCH(INT(OFFSET(U94,ROW(U$2)-ROW(U94),-2)),$2:$2,0)) & ":" & ADDRESS(2,COLUMN(U94)-1),TRUE),"T",INDIRECT(ADDRESS(ROW(U94), MATCH(INT(OFFSET(U94,ROW(U$2)-ROW(U94),-2)),$2:$2,0)) & ":" & ADDRESS(ROW(U94),COLUMN(U94)-1),TRUE)),IF(OFFSET(U94,0,COLUMN($M94)-COLUMN(U94))="V",OFFSET(U94,0,-2)*OFFSET(U94,0,-1),"TOTAL"))) -> 0
A95: =IF(ISNUMBER(OFFSET(A95,0,12)),"START",IF(AND(OFFSET(A95,0,2)=0,OFFSET(A95,0,4)="GT"),"END",""))&OFFSET(A95,0,1) -> WP003 | B95: =IF(ISNUMBER(OFFSET(B95,0,11)),"WP" & TEXT(OFFSET(B95,0,11),"000"),OFFSET(B95,-1,0)) -> WP003 | C95: 5 | D95: WPRow.R | J95: TC | M95: V | P95: C.2 Equipment (please refer to the Depreciation Cost sheet) | T95: =IF(OFFSET(T95,ROW(T$2)-ROW(T95),0)="TT","TT",IF(OFFSET(T95,0,COLUMN($M95)-COLUMN(T95))="%",ROUND((OFFSET(T95,-2,0)-OFFSET(T95,-21,0))*0.07,2),IF(OFFSET(T95,0,COLUMN($M95)-COLUMN(T95))="V",ROUND(OFFSET(T95,0,-2)*OFFSET(T95,0,-1),2),SUMIF(INDIRECT(ADDRESS(MATCH("START"&OFFSET(T95,0,COLUMN($B95)-COLUMN(T95)),$A:$A,0),$C95+COLUMN($E95)+1)&":"&ADDRESS(MATCH("END"&OFFSET(T95,0,COLUMN($B95)-COLUMN(T95)),$A:$A,0),$C95+COLUMN($E95)+1),TRUE),INDIRECT(ADDRESS(ROW(T95),$C95+COLUMN($E95)),TRUE),INDIRECT(ADDRESS(MATCH("START"&OFFSET(T95,0,COLUMN($B95)-COLUMN(T95)),$A:$A,0),COLUMN(T95))&":"&ADDRESS(MATCH("END"&OFFSET(T95,0,COLUMN($B95)-COLUMN(T95)),$A:$A,0),COLUMN(T95)),TRUE))))) -> 0 | U95: =IF(OFFSET(U95,ROW(U$2)-ROW(U95),0)="TT",SUMIF(INDIRECT(ADDRESS(2,COLUMN($Q95)+1) & ":" & ADDRESS(2,COLUMN(U95)-1),TRUE),"TBE",INDIRECT(ADDRESS(ROW(U95), COLUMN($Q95)+1) & ":" & ADDRESS(ROW(U95),COLUMN(U95)-1),TRUE)),IF(OFFSET(U95,ROW(U$2)-ROW(U95),0)="TBE",SUMIF(INDIRECT(ADDRESS(2,MATCH(INT(OFFSET(U95,ROW(U$2)-ROW(U95),-2)),$2:$2,0)) & ":" & ADDRESS(2,COLUMN(U95)-1),TRUE),"T",INDIRECT(ADDRESS(ROW(U95), MATCH(INT(OFFSET(U95,ROW(U$2)-ROW(U95),-2)),$2:$2,0)) & ":" & ADDRESS(ROW(U95),COLUMN(U95)-1),TRUE)),IF(OFFSET(U95,0,COLUMN($M95)-COLUMN(U95))="V",OFFSET(U95,0,-2)*OFFSET(U95,0,-1),"TOTAL"))) -> 0
A96: =IF(ISNUMBER(OFFSET(A96,0,12)),"START",IF(AND(OFFSET(A96,0,2)=0,OFFSET(A96,0,4)="GT"),"END",""))&OFFSET(A96,0,1) -> WP003 | B96: =IF(ISNUMBER(OFFSET(B96,0,11)),"WP" & TEXT(OFFSET(B96,0,11),"000"),OFFSET(B96,-1,0)) -> WP003 | C96: 6 | D96: WPRow.S | J96: TC | K96: T4 | M96: T | P96: C.3 Other goods, works and services | T96: =IF(OFFSET(T96,ROW(T$2)-ROW(T96),0)="TT","TT",IF(OFFSET(T96,0,COLUMN($M96)-COLUMN(T96))="%",ROUND((OFFSET(T96,-2,0)-OFFSET(T96,-21,0))*0.07,2),IF(OFFSET(T96,0,COLUMN($M96)-COLUMN(T96))="V",ROUND(OFFSET(T96,0,-2)*OFFSET(T96,0,-1),2),SUMIF(INDIRECT(ADDRESS(MATCH("START"&OFFSET(T96,0,COLUMN($B96)-COLUMN(T96)),$A:$A,0),$C96+COLUMN($E96)+1)&":"&ADDRESS(MATCH("END"&OFFSET(T96,0,COLUMN($B96)-COLUMN(T96)),$A:$A,0),$C96+COLUMN($E96)+1),TRUE),INDIRECT(ADDRESS(ROW(T96),$C96+COLUMN($E96)),TRUE),INDIRECT(ADDRESS(MATCH("START"&OFFSET(T96,0,COLUMN($B96)-COLUMN(T96)),$A:$A,0),COLUMN(T96))&":"&ADDRESS(MATCH("END"&OFFSET(T96,0,COLUMN($B96)-COLUMN(T96)),$A:$A,0),COLUMN(T96)),TRUE))))) -> 0 | U96: =IF(OFFSET(U96,ROW(U$2)-ROW(U96),0)="TT",SUMIF(INDIRECT(ADDRESS(2,COLUMN($Q96)+1) & ":" & ADDRESS(2,COLUMN(U96)-1),TRUE),"TBE",INDIRECT(ADDRESS(ROW(U96), COLUMN($Q96)+1) & ":" & ADDRESS(ROW(U96),COLUMN(U96)-1),TRUE)),IF(OFFSET(U96,ROW(U$2)-ROW(U96),0)="TBE",SUMIF(INDIRECT(ADDRESS(2,MATCH(INT(OFFSET(U96,ROW(U$2)-ROW(U96),-2)),$2:$2,0)) & ":" & ADDRESS(2,COLUMN(U96)-1),TRUE),"T",INDIRECT(ADDRESS(ROW(U96), MATCH(INT(OFFSET(U96,ROW(U$2)-ROW(U96),-2)),$2:$2,0)) & ":" & ADDRESS(ROW(U96),COLUMN(U96)-1),TRUE)),IF(OFFSET(U96,0,COLUMN($M96)-COLUMN(U96))="V",OFFSET(U96,0,-2)*OFFSET(U96,0,-1),"TOTAL"))) -> 0
A97: =IF(ISNUMBER(OFFSET(A97,0,12)),"START",IF(AND(OFFSET(A97,0,2)=0,OFFSET(A97,0,4)="GT"),"END",""))&OFFSET(A97,0,1) -> WP003 | B97: =IF(ISNUMBER(OFFSET(B97,0,11)),"WP" & TEXT(OFFSET(B97,0,11),"000"),OFFSET(B97,-1,0)) -> WP003 | C97: 7 | D97: WPRow.T | L97: T4 | M97: V | Q97: Consumables | T97: =IF(OFFSET(T97,ROW(T$2)-ROW(T97),0)="TT","TT",IF(OFFSET(T97,0,COLUMN($M97)-COLUMN(T97))="%",ROUND((OFFSET(T97,-2,0)-OFFSET(T97,-21,0))*0.07,2),IF(OFFSET(T97,0,COLUMN($M97)-COLUMN(T97))="V",ROUND(OFFSET(T97,0,-2)*OFFSET(T97,0,-1),2),SUMIF(INDIRECT(ADDRESS(MATCH("START"&OFFSET(T97,0,COLUMN($B97)-COLUMN(T97)),$A:$A,0),$C97+COLUMN($E97)+1)&":"&ADDRESS(MATCH("END"&OFFSET(T97,0,COLUMN($B97)-COLUMN(T97)),$A:$A,0),$C97+COLUMN($E97)+1),TRUE),INDIRECT(ADDRESS(ROW(T97),$C97+COLUMN($E97)),TRUE),INDIRECT(ADDRESS(MATCH("START"&OFFSET(T97,0,COLUMN($B97)-COLUMN(T97)),$A:$A,0),COLUMN(T97))&":"&ADDRESS(MATCH("END"&OFFSET(T97,0,COLUMN($B97)-COLUMN(T97)),$A:$A,0),COLUMN(T97)),TRUE))))) -> 0 | U97: =IF(OFFSET(U97,ROW(U$2)-ROW(U97),0)="TT",SUMIF(INDIRECT(ADDRESS(2,COLUMN($Q97)+1) & ":" & ADDRESS(2,COLUMN(U97)-1),TRUE),"TBE",INDIRECT(ADDRESS(ROW(U97), COLUMN($Q97)+1) & ":" & ADDRESS(ROW(U97),COLUMN(U97)-1),TRUE)),IF(OFFSET(U97,ROW(U$2)-ROW(U97),0)="TBE",SUMIF(INDIRECT(ADDRESS(2,MATCH(INT(OFFSET(U97,ROW(U$2)-ROW(U97),-2)),$2:$2,0)) & ":" & ADDRESS(2,COLUMN(U97)-1),TRUE),"T",INDIRECT(ADDRESS(ROW(U97), MATCH(INT(OFFSET(U97,ROW(U$2)-ROW(U97),-2)),$2:$2,0)) & ":" & ADDRESS(ROW(U97),COLUMN(U97)-1),TRUE)),IF(OFFSET(U97,0,COLUMN($M97)-COLUMN(U97))="V",OFFSET(U97,0,-2)*OFFSET(U97,0,-1),"TOTAL"))) -> 0
A98: =IF(ISNUMBER(OFFSET(A98,0,12)),"START",IF(AND(OFFSET(A98,0,2)=0,OFFSET(A98,0,4)="GT"),"END",""))&OFFSET(A98,0,1) -> WP003 | B98: =IF(ISNUMBER(OFFSET(B98,0,11)),"WP" & TEXT(OFFSET(B98,0,11),"000"),OFFSET(B98,-1,0)) -> WP003 | C98: 7 | D98: WPRow.U | L98: T4 | M98: V | Q98: Services for Meetings, Seminars | T98: =IF(OFFSET(T98,ROW(T$2)-ROW(T98),0)="TT","TT",IF(OFFSET(T98,0,COLUMN($M98)-COLUMN(T98))="%",ROUND((OFFSET(T98,-2,0)-OFFSET(T98,-21,0))*0.07,2),IF(OFFSET(T98,0,COLUMN($M98)-COLUMN(T98))="V",ROUND(OFFSET(T98,0,-2)*OFFSET(T98,0,-1),2),SUMIF(INDIRECT(ADDRESS(MATCH("START"&OFFSET(T98,0,COLUMN($B98)-COLUMN(T98)),$A:$A,0),$C98+COLUMN($E98)+1)&":"&ADDRESS(MATCH("END"&OFFSET(T98,0,COLUMN($B98)-COLUMN(T98)),$A:$A,0),$C98+COLUMN($E98)+1),TRUE),INDIRECT(ADDRESS(ROW(T98),$C98+COLUMN($E98)),TRUE),INDIRECT(ADDRESS(MATCH("START"&OFFSET(T98,0,COLUMN($B98)-COLUMN(T98)),$A:$A,0),COLUMN(T98))&":"&ADDRESS(MATCH("END"&OFFSET(T98,0,COLUMN($B98)-COLUMN(T98)),$A:$A,0),COLUMN(T98)),TRUE))))) -> 0 | U98: =IF(OFFSET(U98,ROW(U$2)-ROW(U98),0)="TT",SUMIF(INDIRECT(ADDRESS(2,COLUMN($Q98)+1) & ":" & ADDRESS(2,COLUMN(U98)-1),TRUE),"TBE",INDIRECT(ADDRESS(ROW(U98), COLUMN($Q98)+1) & ":" & ADDRESS(ROW(U98),COLUMN(U98)-1),TRUE)),IF(OFFSET(U98,ROW(U$2)-ROW(U98),0)="TBE",SUMIF(INDIRECT(ADDRESS(2,MATCH(INT(OFFSET(U98,ROW(U$2)-ROW(U98),-2)),$2:$2,0)) & ":" & ADDRESS(2,COLUMN(U98)-1),TRUE),"T",INDIRECT(ADDRESS(ROW(U98), MATCH(INT(OFFSET(U98,ROW(U$2)-ROW(U98),-2)),$2:$2,0)) & ":" & ADDRESS(ROW(U98),COLUMN(U98)-1),TRUE)),IF(OFFSET(U98,0,COLUMN($M98)-COLUMN(U98))="V",OFFSET(U98,0,-2)*OFFSET(U98,0,-1),"TOTAL"))) -> 0
A99: =IF(ISNUMBER(OFFSET(A99,0,12)),"START",IF(AND(OFFSET(A99,0,2)=0,OFFSET(A99,0,4)="GT"),"END",""))&OFFSET(A99,0,1) -> WP003 | B99: =IF(ISNUMBER(OFFSET(B99,0,11)),"WP" & TEXT(OFFSET(B99,0,11),"000"),OFFSET(B99,-1,0)) -> WP003 | C99: 7 | D99: WPRow.V | L99: T4 | M99: V | Q99: Services for communication/promotion/dissemination | T99: =IF(OFFSET(T99,ROW(T$2)-ROW(T99),0)="TT","TT",IF(OFFSET(T99,0,COLUMN($M99)-COLUMN(T99))="%",ROUND((OFFSET(T99,-2,0)-OFFSET(T99,-21,0))*0.07,2),IF(OFFSET(T99,0,COLUMN($M99)-COLUMN(T99))="V",ROUND(OFFSET(T99,0,-2)*OFFSET(T99,0,-1),2),SUMIF(INDIRECT(ADDRESS(MATCH("START"&OFFSET(T99,0,COLUMN($B99)-COLUMN(T99)),$A:$A,0),$C99+COLUMN($E99)+1)&":"&ADDRESS(MATCH("END"&OFFSET(T99,0,COLUMN($B99)-COLUMN(T99)),$A:$A,0),$C99+COLUMN($E99)+1),TRUE),INDIRECT(ADDRESS(ROW(T99),$C99+COLUMN($E99)),TRUE),INDIRECT(ADDRESS(MATCH("START"&OFFSET(T99,0,COLUMN($B99)-COLUMN(T99)),$A:$A,0),COLUMN(T99))&":"&ADDRESS(MATCH("END"&OFFSET(T99,0,COLUMN($B99)-COLUMN(T99)),$A:$A,0),COLUMN(T99)),TRUE))))) -> 0 | U99: =IF(OFFSET(U99,ROW(U$2)-ROW(U99),0)="TT",SUMIF(INDIRECT(ADDRESS(2,COLUMN($Q99)+1) & ":" & ADDRESS(2,COLUMN(U99)-1),TRUE),"TBE",INDIRECT(ADDRESS(ROW(U99), COLUMN($Q99)+1) & ":" & ADDRESS(ROW(U99),COLUMN(U99)-1),TRUE)),IF(OFFSET(U99,ROW(U$2)-ROW(U99),0)="TBE",SUMIF(INDIRECT(ADDRESS(2,MATCH(INT(OFFSET(U99,ROW(U$2)-ROW(U99),-2)),$2:$2,0)) & ":" & ADDRESS(2,COLUMN(U99)-1),TRUE),"T",INDIRECT(ADDRESS(ROW(U99), MATCH(INT(OFFSET(U99,ROW(U$2)-ROW(U99),-2)),$2:$2,0)) & ":" & ADDRESS(ROW(U99),COLUMN(U99)-1),TRUE)),IF(OFFSET(U99,0,COLUMN($M99)-COLUMN(U99))="V",OFFSET(U99,0,-2)*OFFSET(U99,0,-1),"TOTAL"))) -> 0
A100: =IF(ISNUMBER(OFFSET(A100,0,12)),"START",IF(AND(OFFSET(A100,0,2)=0,OFFSET(A100,0,4)="GT"),"END",""))&OFFSET(A100,0,1) -> WP003 | B100: =IF(ISNUMBER(OFFSET(B100,0,11)),"WP" & TEXT(OFFSET(B100,0,11),"000"),OFFSET(B100,-1,0)) -> WP003 | C100: 7 | D100: WPRow.W | L100: T4 | M100: V | Q100: Website | T100: =IF(OFFSET(T100,ROW(T$2)-ROW(T100),0)="TT","TT",IF(OFFSET(T100,0,COLUMN($M100)-COLUMN(T100))="%",ROUND((OFFSET(T100,-2,0)-OFFSET(T100,-21,0))*0.07,2),IF(OFFSET(T100,0,COLUMN($M100)-COLUMN(T100))="V",ROUND(OFFSET(T100,0,-2)*OFFSET(T100,0,-1),2),SUMIF(INDIRECT(ADDRESS(MATCH("START"&OFFSET(T100,0,COLUMN($B100)-COLUMN(T100)),$A:$A,0),$C100+COLUMN($E100)+1)&":"&ADDRESS(MATCH("END"&OFFSET(T100,0,COLUMN($B100)-COLUMN(T100)),$A:$A,0),$C100+COLUMN($E100)+1),TRUE),INDIRECT(ADDRESS(ROW(T100),$C100+COLUMN($E100)),TRUE),INDIRECT(ADDRESS(MATCH("START"&OFFSET(T100,0,COLUMN($B100)-COLUMN(T100)),$A:$A,0),COLUMN(T100))&":"&ADDRESS(MATCH("END"&OFFSET(T100,0,COLUMN($B100)-COLUMN(T100)),$A:$A,0),COLUMN(T100)),TRUE))))) -> 0 | U100: =IF(OFFSET(U100,ROW(U$2)-ROW(U100),0)="TT",SUMIF(INDIRECT(ADDRESS(2,COLUMN($Q100)+1) & ":" & ADDRESS(2,COLUMN(U100)-1),TRUE),"TBE",INDIRECT(ADDRESS(ROW(U100), COLUMN($Q100)+1) & ":" & ADDRESS(ROW(U100),COLUMN(U100)-1),TRUE)),IF(OFFSET(U100,ROW(U$2)-ROW(U100),0)="TBE",SUMIF(INDIRECT(ADDRESS(2,MATCH(INT(OFFSET(U100,ROW(U$2)-ROW(U100),-2)),$2:$2,0)) & ":" & ADDRESS(2,COLUMN(U100)-1),TRUE),"T",INDIRECT(ADDRESS(ROW(U100), MATCH(INT(OFFSET(U100,ROW(U$2)-ROW(U100),-2)),$2:$2,0)) & ":" & ADDRESS(ROW(U100),COLUMN(U100)-1),TRUE)),IF(OFFSET(U100,0,COLUMN($M100)-COLUMN(U100))="V",OFFSET(U100,0,-2)*OFFSET(U100,0,-1),"TOTAL"))) -> 0
A101: =IF(ISNUMBER(OFFSET(A101,0,12)),"START",IF(AND(OFFSET(A101,0,2)=0,OFFSET(A101,0,4)="GT"),"END",""))&OFFSET(A101,0,1) -> WP003 | B101: =IF(ISNUMBER(OFFSET(B101,0,11)),"WP" & TEXT(OFFSET(B101,0,11),"000"),OFFSET(B101,-1,0)) -> WP003 | C101: 7 | D101: WPRow.X | L101: T4 | M101: V | Q101: Artistic Fees | T101: =IF(OFFSET(T101,ROW(T$2)-ROW(T101),0)="TT","TT",IF(OFFSET(T101,0,COLUMN($M101)-COLUMN(T101))="%",ROUND((OFFSET(T101,-2,0)-OFFSET(T101,-21,0))*0.07,2),IF(OFFSET(T101,0,COLUMN($M101)-COLUMN(T101))="V",ROUND(OFFSET(T101,0,-2)*OFFSET(T101,0,-1),2),SUMIF(INDIRECT(ADDRESS(MATCH("START"&OFFSET(T101,0,COLUMN($B101)-COLUMN(T101)),$A:$A,0),$C101+COLUMN($E101)+1)&":"&ADDRESS(MATCH("END"&OFFSET(T101,0,COLUMN($B101)-COLUMN(T101)),$A:$A,0),$C101+COLUMN($E101)+1),TRUE),INDIRECT(ADDRESS(ROW(T101),$C101+COLUMN($E101)),TRUE),INDIRECT(ADDRESS(MATCH("START"&OFFSET(T101,0,COLUMN($B101)-COLUMN(T101)),$A:$A,0),COLUMN(T101))&":"&ADDRESS(MATCH("END"&OFFSET(T101,0,COLUMN($B101)-COLUMN(T101)),$A:$A,0),COLUMN(T101)),TRUE))))) -> 0 | U101: =IF(OFFSET(U101,ROW(U$2)-ROW(U101),0)="TT",SUMIF(INDIRECT(ADDRESS(2,COLUMN($Q101)+1) & ":" & ADDRESS(2,COLUMN(U101)-1),TRUE),"TBE",INDIRECT(ADDRESS(ROW(U101), COLUMN($Q101)+1) & ":" & ADDRESS(ROW(U101),COLUMN(U101)-1),TRUE)),IF(OFFSET(U101,ROW(U$2)-ROW(U101),0)="TBE",SUMIF(INDIRECT(ADDRESS(2,MATCH(INT(OFFSET(U101,ROW(U$2)-ROW(U101),-2)),$2:$2,0)) & ":" & ADDRESS(2,COLUMN(U101)-1),TRUE),"T",INDIRECT(ADDRESS(ROW(U101), MATCH(INT(OFFSET(U101,ROW(U$2)-ROW(U101),-2)),$2:$2,0)) & ":" & ADDRESS(ROW(U101),COLUMN(U101)-1),TRUE)),IF(OFFSET(U101,0,COLUMN($M101)-COLUMN(U101))="V",OFFSET(U101,0,-2)*OFFSET(U101,0,-1),"TOTAL"))) -> 0
A102: =IF(ISNUMBER(OFFSET(A102,0,12)),"START",IF(AND(OFFSET(A102,0,2)=0,OFFSET(A102,0,4)="GT"),"END",""))&OFFSET(A102,0,1) -> WP003 | B102: =IF(ISNUMBER(OFFSET(B102,0,11)),"WP" & TEXT(OFFSET(B102,0,11),"000"),OFFSET(B102,-1,0)) -> WP003 | C102: 7 | D102: WPRow.Y | L102: T4 | M102: V | Q102: Other (please specify details under worksheet "Comments") | T102: =IF(OFFSET(T102,ROW(T$2)-ROW(T102),0)="TT","TT",IF(OFFSET(T102,0,COLUMN($M102)-COLUMN(T102))="%",ROUND((OFFSET(T102,-2,0)-OFFSET(T102,-21,0))*0.07,2),IF(OFFSET(T102,0,COLUMN($M102)-COLUMN(T102))="V",ROUND(OFFSET(T102,0,-2)*OFFSET(T102,0,-1),2),SUMIF(INDIRECT(ADDRESS(MATCH("START"&OFFSET(T102,0,COLUMN($B102)-COLUMN(T102)),$A:$A,0),$C102+COLUMN($E102)+1)&":"&ADDRESS(MATCH("END"&OFFSET(T102,0,COLUMN($B102)-COLUMN(T102)),$A:$A,0),$C102+COLUMN($E102)+1),TRUE),INDIRECT(ADDRESS(ROW(T102),$C102+COLUMN($E102)),TRUE),INDIRECT(ADDRESS(MATCH("START"&OFFSET(T102,0,COLUMN($B102)-COLUMN(T102)),$A:$A,0),COLUMN(T102))&":"&ADDRESS(MATCH("END"&OFFSET(T102,0,COLUMN($B102)-COLUMN(T102)),$A:$A,0),COLUMN(T102)),TRUE))))) -> 0 | U102: =IF(OFFSET(U102,ROW(U$2)-ROW(U102),0)="TT",SUMIF(INDIRECT(ADDRESS(2,COLUMN($Q102)+1) & ":" & ADDRESS(2,COLUMN(U102)-1),TRUE),"TBE",INDIRECT(ADDRESS(ROW(U102), COLUMN($Q102)+1) & ":" & ADDRESS(ROW(U102),COLUMN(U102)-1),TRUE)),IF(OFFSET(U102,ROW(U$2)-ROW(U102),0)="TBE",SUMIF(INDIRECT(ADDRESS(2,MATCH(INT(OFFSET(U102,ROW(U$2)-ROW(U102),-2)),$2:$2,0)) & ":" & ADDRESS(2,COLUMN(U102)-1),TRUE),"T",INDIRECT(ADDRESS(ROW(U102), MATCH(INT(OFFSET(U102,ROW(U$2)-ROW(U102),-2)),$2:$2,0)) & ":" & ADDRESS(ROW(U102),COLUMN(U102)-1),TRUE)),IF(OFFSET(U102,0,COLUMN($M102)-COLUMN(U102))="V",OFFSET(U102,0,-2)*OFFSET(U102,0,-1),"TOTAL"))) -> 0
...

Sheet BE xxx
A1: 0 | B1: =IF(ISERROR(MATCH("STARTWP" & TEXT(A1,"000"),A:A,0)),"N",MATCH("STARTWP" & TEXT(A1,"000"),A:A,0)) -> N | C1: =COUNTIF(E:E,"GT") -> 1 | D1: =IF(ISERROR(MATCH("ENDWP" & TEXT(A1,"000"),A:A,0)),"N",MATCH("ENDWP" & TEXT(A1,"000"),A:A,0)) -> N | F1: =COUNTA(A:A) -> 42 | H1: TBE | I1: =MATCH(H1,2:2,0) -> 21 | J1: =MATCH("BE",2:2,0) -> 18 | K1: =COUNTIF(2:2,"TP") -> 0 | N1: C | O1: XX | P1: XX | Q1: B. Subcontracting costs (please specify details under worksheet "Comments") | R1: XX.XXX,XX | S1: XXXXXXXXX,XX | T1: XXXXXXXXXXX,XX | U1: XXXXXXXXXXXXXX,XX
A2: =INDIRECT("'"& MID(OFFSET(A2,ROW(A$3)-ROW(A2),IF(OFFSET(A2,ROW(A$2)-ROW(A2),2)="T",0,IF(OFFSET(A2,ROW(A$2)-ROW(A2),1)="T",-1,-2))),1,6) & "'!" & ADDRESS(ROW(A2),MATCH(INDIRECT(ADDRESS(2,COLUMN(A2)+IF(OFFSET(A2,ROW(A$2)-ROW(A2),2)="T",1,IF(OFFSET(A2,ROW(A$2)-ROW(A2),1)="T",0,-1))),TRUE),INDIRECT("'"& MID(OFFSET(A2,ROW(A$3)-ROW(A2),IF(OFFSET(A2,ROW(A$2)-ROW(A2),2)="T",0,IF(OFFSET(A2,ROW(A$2)-ROW(A2),1)="T",-1,-2))),1,6) & "'!2:2",TRUE),0)-IF(OFFSET(A2,ROW(A$2)-ROW(A2),2)="T",1,IF(OFFSET(A2,ROW(A$2)-ROW(A2),1)="T",0,-1))),TRUE) -> #REF! | N2: 99 | R2: =IF(OFFSET(R2,0,1)="","TT",IF(INT(OFFSET(R2,0,1))=OFFSET(R2,0,1),"BE","TP")) -> BE | S2: 0 | T2: =IF(OFFSET(T2,0,-2)="TT","E","T") -> T | U2: TBE
A3: X | Q3: =""&IF(OFFSET(Q3,-2,-3)="C","DETAILED",INDIRECT("'Beneficiaries List'!A" & MATCH(OFFSET(Q3,-2,-3),'Beneficiaries List'!$J:$J,0),TRUE)) -> DETAILED | R3: =""&INDIRECT("'Beneficiaries List'!A" & MATCH(OFFSET(R3,-1,1),'Beneficiaries List'!$K:$K,0),TRUE) -> #N/A | U3: =IF(U2="TBE","BE " & TEXT(INDIRECT(ADDRESS(2,MATCH(INT(OFFSET(U3,-1,-2)),2:2,0)),TRUE),"000"),"PROJECT") -> BE 000
A4: X | R4: =""&INDIRECT("'Beneficiaries List'!B" & MATCH(OFFSET(R4,-2,1),'Beneficiaries List'!$K:$K,0),TRUE) -> #N/A
A5: X | E5: 0 | F5: 1 | G5: 2 | H5: 3 | I5: 4 | J5: 5 | K5: 6 | L5: 7 | Q5: =""&IF(OFFSET(Q5,-4,-3)="C","CONSOLIDATION",INDIRECT("'Beneficiaries List'!B" & MATCH(OFFSET(Q5,-4,-3),'Beneficiaries List'!$J:$J,0),TRUE)) -> CONSOLIDATION | R5: =IF(OFFSET(R5,-3,0)="TT","BE+TP TOTAL COSTS","UNITS") -> UNITS | S5: =IF(OFFSET(S5,0,-1)="UNITS","COST PER UNIT","") -> COST PER UNIT | T5: =IF(OFFSET(T5,0,-2)="UNITS",IF(OFFSET(T5,-3,-2)="BE","BENEFICIARY","AFFILIATED ENTITY") & " TOTAL COSTS","") -> BENEFICIARY TOTAL COSTS | U5: BE+AE TOTAL COSTS
A6: X | R6: 0 | S6: -1 | T6: -2
A7: X | O7: Total WORK PACKAGES: | R7: =SUMIF($E:$E,"GT",R:R) -> 0 | T7: =SUMIF($E:$E,"GT",T:T) -> 0 | U7: =IF(OFFSET(U7,ROW(U$2)-ROW(U7),0)="TT",SUMIF(INDIRECT(ADDRESS(2,COLUMN($Q7)+1) & ":" & ADDRESS(2,COLUMN(U7)-1),TRUE),"TBE",INDIRECT(ADDRESS(ROW(U7), COLUMN($Q7)+1) & ":" & ADDRESS(ROW(U7),COLUMN(U7)-1),TRUE)),IF(OFFSET(U7,ROW(U$2)-ROW(U7),0)="TBE",SUMIF(INDIRECT(ADDRESS(2,MATCH(INT(OFFSET(U7,ROW(U$2)-ROW(U7),-2)),$2:$2,0)) & ":" & ADDRESS(2,COLUMN(U7)-1),TRUE),"T",INDIRECT(ADDRESS(ROW(U7), MATCH(INT(OFFSET(U7,ROW(U$2)-ROW(U7),-2)),$2:$2,0)) & ":" & ADDRESS(ROW(U7),COLUMN(U7)-1),TRUE)),IF(OFFSET(U7,0,COLUMN($M7)-COLUMN(U7))="V",OFFSET(U7,0,-2)*OFFSET(U7,0,-1),"TOTAL"))) -> 0
A8: X
A9: =IF(ISNUMBER(OFFSET(A9,0,13)),"START",IF(AND(OFFSET(A9,0,2)=0,OFFSET(A9,0,4)="GT"),"END",""))&OFFSET(A9,0,1) -> STARTWP001 | B9: =IF(ISNUMBER(OFFSET(B9,0,12)),"WP" & TEXT(OFFSET(B9,0,12),"000"),OFFSET(B9,-1,0)) -> WP001 | N9: 1 | O9: =""&VLOOKUP(OFFSET(N9,1,0),'Work Packages List'!A:B,2,FALSE)
A10: =IF(ISNUMBER(OFFSET(A10,0,12)),"START",IF(AND(OFFSET(A10,0,2)=0,OFFSET(A10,0,4)="GT"),"END",""))&OFFSET(A10,0,1) -> WP001 | B10: =IF(ISNUMBER(OFFSET(B10,0,11)),"WP" & TEXT(OFFSET(B10,0,11),"000"),OFFSET(B10,-1,0)) -> WP001 | C10: 4 | D10: WPRow.A | H10: TTA | I10: TA | M10: T | N10: ="WP " & TEXT(OFFSET(N10,-1,0),"000") -> WP 001 | O10: A. DIRECT PERSONNEL COSTS | R10: =IF(OFFSET(R10,ROW(R$2)-ROW(R10),0)="TT","TT",IF(OFFSET(R10,0,COLUMN($M10)-COLUMN(R10))="%",ROUND(OFFSET(R10,-2,0)*0.07,0),IF(OFFSET(R10,0,COLUMN($M10)-COLUMN(R10))="V","x",SUMIF(INDIRECT(ADDRESS(MATCH("START"&OFFSET(R10,0,COLUMN($B10)-COLUMN(R10)),$A:$A,0),$C10+COLUMN($E10)+1)&":"&ADDRESS(MATCH("END"&OFFSET(R10,0,COLUMN($B10)-COLUMN(R10)),$A:$A,0),$C10+COLUMN($E10)+1),TRUE),INDIRECT(ADDRESS(ROW(R10),$C10+COLUMN($E10)),TRUE),INDIRECT(ADDRESS(MATCH("START"&OFFSET(R10,0,COLUMN($B10)-COLUMN(R10)),$A:$A,0),COLUMN(R10))&":"&ADDRESS(MATCH("END"&OFFSET(R10,0,COLUMN($B10)-COLUMN(R10)),$A:$A,0),COLUMN(R10)),TRUE))))) -> 0 | T10: =IF(OFFSET(T10,ROW(T$2)-ROW(T10),0)="TT","TT",IF(OFFSET(T10,0,COLUMN($M10)-COLUMN(T10))="%",ROUND((OFFSET(T10,-2,0)-OFFSET(T10,-21,0))*0.07,2),IF(OFFSET(T10,0,COLUMN($M10)-COLUMN(T10))="V",ROUND(OFFSET(T10,0,-2)*OFFSET(T10,0,-1),2),SUMIF(INDIRECT(ADDRESS(MATCH("START"&OFFSET(T10,0,COLUMN($B10)-COLUMN(T10)),$A:$A,0),$C10+COLUMN($E10)+1)&":"&ADDRESS(MATCH("END"&OFFSET(T10,0,COLUMN($B10)-COLUMN(T10)),$A:$A,0),$C10+COLUMN($E10)+1),TRUE),INDIRECT(ADDRESS(ROW(T10),$C10+COLUMN($E10)),TRUE),INDIRECT(ADDRESS(MATCH("START"&OFFSET(T10,0,COLUMN($B10)-COLUMN(T10)),$A:$A,0),COLUMN(T10))&":"&ADDRESS(MATCH("END"&OFFSET(T10,0,COLUMN($B10)-COLUMN(T10)),$A:$A,0),COLUMN(T10)),TRUE))))) -> 0 | U10: =IF(OFFSET(U10,ROW(U$2)-ROW(U10),0)="TT",SUMIF(INDIRECT(ADDRESS(2,COLUMN($Q10)+1) & ":" & ADDRESS(2,COLUMN(U10)-1),TRUE),"TBE",INDIRECT(ADDRESS(ROW(U10), COLUMN($Q10)+1) & ":" & ADDRESS(ROW(U10),COLUMN(U10)-1),TRUE)),IF(OFFSET(U10,ROW(U$2)-ROW(U10),0)="TBE",SUMIF(INDIRECT(ADDRESS(2,MATCH(INT(OFFSET(U10,ROW(U$2)-ROW(U10),-2)),$2:$2,0)) & ":" & ADDRESS(2,COLUMN(U10)-1),TRUE),"T",INDIRECT(ADDRESS(ROW(U10), MATCH(INT(OFFSET(U10,ROW(U$2)-ROW(U10),-2)),$2:$2,0)) & ":" & ADDRESS(ROW(U10),COLUMN(U10)-1),TRUE)),IF(OFFSET(U10,0,COLUMN($M10)-COLUMN(U10))="V",OFFSET(U10,0,-2)*OFFSET(U10,0,-1),"TOTAL"))) -> 0
A11: =IF(ISNUMBER(OFFSET(A11,0,12)),"START",IF(AND(OFFSET(A11,0,2)=0,OFFSET(A11,0,4)="GT"),"END",""))&OFFSET(A11,0,1) -> WP001 | B11: =IF(ISNUMBER(OFFSET(B11,0,11)),"WP" & TEXT(OFFSET(B11,0,11),"000"),OFFSET(B11,-1,0)) -> WP001 | C11: 6 | D11: WPRow.B | J11: TA | K11: T1 | M11: T | P11: A1. Employees (or equivalent) person months | R11: =IF(OFFSET(R11,ROW(R$2)-ROW(R11),0)="TT","TT",IF(OFFSET(R11,0,COLUMN($M11)-COLUMN(R11))="%",ROUND(OFFSET(R11,-2,0)*0.07,0),IF(OFFSET(R11,0,COLUMN($M11)-COLUMN(R11))="V","x",SUMIF(INDIRECT(ADDRESS(MATCH("START"&OFFSET(R11,0,COLUMN($B11)-COLUMN(R11)),$A:$A,0),$C11+COLUMN($E11)+1)&":"&ADDRESS(MATCH("END"&OFFSET(R11,0,COLUMN($B11)-COLUMN(R11)),$A:$A,0),$C11+COLUMN($E11)+1),TRUE),INDIRECT(ADDRESS(ROW(R11),$C11+COLUMN($E11)),TRUE),INDIRECT(ADDRESS(MATCH("START"&OFFSET(R11,0,COLUMN($B11)-COLUMN(R11)),$A:$A,0),COLUMN(R11))&":"&ADDRESS(MATCH("END"&OFFSET(R11,0,COLUMN($B11)-COLUMN(R11)),$A:$A,0),COLUMN(R11)),TRUE))))) -> 0 | T11: =IF(OFFSET(T11,ROW(T$2)-ROW(T11),0)="TT","TT",IF(OFFSET(T11,0,COLUMN($M11)-COLUMN(T11))="%",ROUND((OFFSET(T11,-2,0)-OFFSET(T11,-21,0))*0.07,2),IF(OFFSET(T11,0,COLUMN($M11)-COLUMN(T11))="V",ROUND(OFFSET(T11,0,-2)*OFFSET(T11,0,-1),2),SUMIF(INDIRECT(ADDRESS(MATCH("START"&OFFSET(T11,0,COLUMN($B11)-COLUMN(T11)),$A:$A,0),$C11+COLUMN($E11)+1)&":"&ADDRESS(MATCH("END"&OFFSET(T11,0,COLUMN($B11)-COLUMN(T11)),$A:$A,0),$C11+COLUMN($E11)+1),TRUE),INDIRECT(ADDRESS(ROW(T11),$C11+COLUMN($E11)),TRUE),INDIRECT(ADDRESS(MATCH("START"&OFFSET(T11,0,COLUMN($B11)-COLUMN(T11)),$A:$A,0),COLUMN(T11))&":"&ADDRESS(MATCH("END"&OFFSET(T11,0,COLUMN($B11)-COLUMN(T11)),$A:$A,0),COLUMN(T11)),TRUE))))) -> 0 | U11: =IF(OFFSET(U11,ROW(U$2)-ROW(U11),0)="TT",SUMIF(INDIRECT(ADDRESS(2,COLUMN($Q11)+1) & ":" & ADDRESS(2,COLUMN(U11)-1),TRUE),"TBE",INDIRECT(ADDRESS(ROW(U11), COLUMN($Q11)+1) & ":" & ADDRESS(ROW(U11),COLUMN(U11)-1),TRUE)),IF(OFFSET(U11,ROW(U$2)-ROW(U11),0)="TBE",SUMIF(INDIRECT(ADDRESS(2,MATCH(INT(OFFSET(U11,ROW(U$2)-ROW(U11),-2)),$2:$2,0)) & ":" & ADDRESS(2,COLUMN(U11)-1),TRUE),"T",INDIRECT(ADDRESS(ROW(U11), MATCH(INT(OFFSET(U11,ROW(U$2)-ROW(U11),-2)),$2:$2,0)) & ":" & ADDRESS(ROW(U11),COLUMN(U11)-1),TRUE)),IF(OFFSET(U11,0,COLUMN($M11)-COLUMN(U11))="V",OFFSET(U11,0,-2)*OFFSET(U11,0,-1),"TOTAL"))) -> 0
A12: =IF(ISNUMBER(OFFSET(A12,0,12)),"START",IF(AND(OFFSET(A12,0,2)=0,OFFSET(A12,0,4)="GT"),"END",""))&OFFSET(A12,0,1) -> WP001 | B12: =IF(ISNUMBER(OFFSET(B12,0,11)),"WP" & TEXT(OFFSET(B12,0,11),"000"),OFFSET(B12,-1,0)) -> WP001 | C12: 7 | D12: WPRow.C | L12: T1 | M12: V | Q12: =EMP_TYPE1 -> Type 1 | T12: =IF(OFFSET(T12,ROW(T$2)-ROW(T12),0)="TT","TT",IF(OFFSET(T12,0,COLUMN($M12)-COLUMN(T12))="%",ROUND((OFFSET(T12,-2,0)-OFFSET(T12,-21,0))*0.07,2),IF(OFFSET(T12,0,COLUMN($M12)-COLUMN(T12))="V",ROUND(OFFSET(T12,0,-2)*OFFSET(T12,0,-1),2),SUMIF(INDIRECT(ADDRESS(MATCH("START"&OFFSET(T12,0,COLUMN($B12)-COLUMN(T12)),$A:$A,0),$C12+COLUMN($E12)+1)&":"&ADDRESS(MATCH("END"&OFFSET(T12,0,COLUMN($B12)-COLUMN(T12)),$A:$A,0),$C12+COLUMN($E12)+1),TRUE),INDIRECT(ADDRESS(ROW(T12),$C12+COLUMN($E12)),TRUE),INDIRECT(ADDRESS(MATCH("START"&OFFSET(T12,0,COLUMN($B12)-COLUMN(T12)),$A:$A,0),COLUMN(T12))&":"&ADDRESS(MATCH("END"&OFFSET(T12,0,COLUMN($B12)-COLUMN(T12)),$A:$A,0),COLUMN(T12)),TRUE))))) -> 0 | U12: =IF(OFFSET(U12,ROW(U$2)-ROW(U12),0)="TT",SUMIF(INDIRECT(ADDRESS(2,COLUMN($Q12)+1) & ":" & ADDRESS(2,COLUMN(U12)-1),TRUE),"TBE",INDIRECT(ADDRESS(ROW(U12), COLUMN($Q12)+1) & ":" & ADDRESS(ROW(U12),COLUMN(U12)-1),TRUE)),IF(OFFSET(U12,ROW(U$2)-ROW(U12),0)="TBE",SUMIF(INDIRECT(ADDRESS(2,MATCH(INT(OFFSET(U12,ROW(U$2)-ROW(U12),-2)),$2:$2,0)) & ":" & ADDRESS(2,COLUMN(U12)-1),TRUE),"T",INDIRECT(ADDRESS(ROW(U12), MATCH(INT(OFFSET(U12,ROW(U$2)-ROW(U12),-2)),$2:$2,0)) & ":" & ADDRESS(ROW(U12),COLUMN(U12)-1),TRUE)),IF(OFFSET(U12,0,COLUMN($M12)-COLUMN(U12))="V",OFFSET(U12,0,-2)*OFFSET(U12,0,-1),"TOTAL"))) -> 0
A13: =IF(ISNUMBER(OFFSET(A13,0,12)),"START",IF(AND(OFFSET(A13,0,2)=0,OFFSET(A13,0,4)="GT"),"END",""))&OFFSET(A13,0,1) -> WP001 | B13: =IF(ISNUMBER(OFFSET(B13,0,11)),"WP" & TEXT(OFFSET(B13,0,11),"000"),OFFSET(B13,-1,0)) -> WP001 | C13: 7 | D13: WPRow.D | L13: T1 | M13: V | Q13: =EMP_TYPE2 -> Type 2 | T13: =IF(OFFSET(T13,ROW(T$2)-ROW(T13),0)="TT","TT",IF(OFFSET(T13,0,COLUMN($M13)-COLUMN(T13))="%",ROUND((OFFSET(T13,-2,0)-OFFSET(T13,-21,0))*0.07,2),IF(OFFSET(T13,0,COLUMN($M13)-COLUMN(T13))="V",ROUND(OFFSET(T13,0,-2)*OFFSET(T13,0,-1),2),SUMIF(INDIRECT(ADDRESS(MATCH("START"&OFFSET(T13,0,COLUMN($B13)-COLUMN(T13)),$A:$A,0),$C13+COLUMN($E13)+1)&":"&ADDRESS(MATCH("END"&OFFSET(T13,0,COLUMN($B13)-COLUMN(T13)),$A:$A,0),$C13+COLUMN($E13)+1),TRUE),INDIRECT(ADDRESS(ROW(T13),$C13+COLUMN($E13)),TRUE),INDIRECT(ADDRESS(MATCH("START"&OFFSET(T13,0,COLUMN($B13)-COLUMN(T13)),$A:$A,0),COLUMN(T13))&":"&ADDRESS(MATCH("END"&OFFSET(T13,0,COLUMN($B13)-COLUMN(T13)),$A:$A,0),COLUMN(T13)),TRUE))))) -> 0 | U13: =IF(OFFSET(U13,ROW(U$2)-ROW(U13),0)="TT",SUMIF(INDIRECT(ADDRESS(2,COLUMN($Q13)+1) & ":" & ADDRESS(2,COLUMN(U13)-1),TRUE),"TBE",INDIRECT(ADDRESS(ROW(U13), COLUMN($Q13)+1) & ":" & ADDRESS(ROW(U13),COLUMN(U13)-1),TRUE)),IF(OFFSET(U13,ROW(U$2)-ROW(U13),0)="TBE",SUMIF(INDIRECT(ADDRESS(2,MATCH(INT(OFFSET(U13,ROW(U$2)-ROW(U13),-2)),$2:$2,0)) & ":" & ADDRESS(2,COLUMN(U13)-1),TRUE),"T",INDIRECT(ADDRESS(ROW(U13), MATCH(INT(OFFSET(U13,ROW(U$2)-ROW(U13),-2)),$2:$2,0)) & ":" & ADDRESS(ROW(U13),COLUMN(U13)-1),TRUE)),IF(OFFSET(U13,0,COLUMN($M13)-COLUMN(U13))="V",OFFSET(U13,0,-2)*OFFSET(U13,0,-1),"TOTAL"))) -> 0
A14: =IF(ISNUMBER(OFFSET(A14,0,12)),"START",IF(AND(OFFSET(A14,0,2)=0,OFFSET(A14,0,4)="GT"),"END",""))&OFFSET(A14,0,1) -> WP001 | B14: =IF(ISNUMBER(OFFSET(B14,0,11)),"WP" & TEXT(OFFSET(B14,0,11),"000"),OFFSET(B14,-1,0)) -> WP001 | C14: 7 | D14: WPRow.E | L14: T1 | M14: V | Q14: =EMP_TYPE3 -> Type 3 | T14: =IF(OFFSET(T14,ROW(T$2)-ROW(T14),0)="TT","TT",IF(OFFSET(T14,0,COLUMN($M14)-COLUMN(T14))="%",ROUND((OFFSET(T14,-2,0)-OFFSET(T14,-21,0))*0.07,2),IF(OFFSET(T14,0,COLUMN($M14)-COLUMN(T14))="V",ROUND(OFFSET(T14,0,-2)*OFFSET(T14,0,-1),2),SUMIF(INDIRECT(ADDRESS(MATCH("START"&OFFSET(T14,0,COLUMN($B14)-COLUMN(T14)),$A:$A,0),$C14+COLUMN($E14)+1)&":"&ADDRESS(MATCH("END"&OFFSET(T14,0,COLUMN($B14)-COLUMN(T14)),$A:$A,0),$C14+COLUMN($E14)+1),TRUE),INDIRECT(ADDRESS(ROW(T14),$C14+COLUMN($E14)),TRUE),INDIRECT(ADDRESS(MATCH("START"&OFFSET(T14,0,COLUMN($B14)-COLUMN(T14)),$A:$A,0),COLUMN(T14))&":"&ADDRESS(MATCH("END"&OFFSET(T14,0,COLUMN($B14)-COLUMN(T14)),$A:$A,0),COLUMN(T14)),TRUE))))) -> 0 | U14: =IF(OFFSET(U14,ROW(U$2)-ROW(U14),0)="TT",SUMIF(INDIRECT(ADDRESS(2,COLUMN($Q14)+1) & ":" & ADDRESS(2,COLUMN(U14)-1),TRUE),"TBE",INDIRECT(ADDRESS(ROW(U14), COLUMN($Q14)+1) & ":" & ADDRESS(ROW(U14),COLUMN(U14)-1),TRUE)),IF(OFFSET(U14,ROW(U$2)-ROW(U14),0)="TBE",SUMIF(INDIRECT(ADDRESS(2,MATCH(INT(OFFSET(U14,ROW(U$2)-ROW(U14),-2)),$2:$2,0)) & ":" & ADDRESS(2,COLUMN(U14)-1),TRUE),"T",INDIRECT(ADDRESS(ROW(U14), MATCH(INT(OFFSET(U14,ROW(U$2)-ROW(U14),-2)),$2:$2,0)) & ":" & ADDRESS(ROW(U14),COLUMN(U14)-1),TRUE)),IF(OFFSET(U14,0,COLUMN($M14)-COLUMN(U14))="V",OFFSET(U14,0,-2)*OFFSET(U14,0,-1),"TOTAL"))) -> 0
A15: =IF(ISNUMBER(OFFSET(A15,0,12)),"START",IF(AND(OFFSET(A15,0,2)=0,OFFSET(A15,0,4)="GT"),"END",""))&OFFSET(A15,0,1) -> WP001 | B15: =IF(ISNUMBER(OFFSET(B15,0,11)),"WP" & TEXT(OFFSET(B15,0,11),"000"),OFFSET(B15,-1,0)) -> WP001 | C15: 7 | D15: WPRow.F | L15: T1 | M15: V | Q15: =EMP_TYPE4 -> Type 4 | T15: =IF(OFFSET(T15,ROW(T$2)-ROW(T15),0)="TT","TT",IF(OFFSET(T15,0,COLUMN($M15)-COLUMN(T15))="%",ROUND((OFFSET(T15,-2,0)-OFFSET(T15,-21,0))*0.07,2),IF(OFFSET(T15,0,COLUMN($M15)-COLUMN(T15))="V",ROUND(OFFSET(T15,0,-2)*OFFSET(T15,0,-1),2),SUMIF(INDIRECT(ADDRESS(MATCH("START"&OFFSET(T15,0,COLUMN($B15)-COLUMN(T15)),$A:$A,0),$C15+COLUMN($E15)+1)&":"&ADDRESS(MATCH("END"&OFFSET(T15,0,COLUMN($B15)-COLUMN(T15)),$A:$A,0),$C15+COLUMN($E15)+1),TRUE),INDIRECT(ADDRESS(ROW(T15),$C15+COLUMN($E15)),TRUE),INDIRECT(ADDRESS(MATCH("START"&OFFSET(T15,0,COLUMN($B15)-COLUMN(T15)),$A:$A,0),COLUMN(T15))&":"&ADDRESS(MATCH("END"&OFFSET(T15,0,COLUMN($B15)-COLUMN(T15)),$A:$A,0),COLUMN(T15)),TRUE))))) -> 0 | U15: =IF(OFFSET(U15,ROW(U$2)-ROW(U15),0)="TT",SUMIF(INDIRECT(ADDRESS(2,COLUMN($Q15)+1) & ":" & ADDRESS(2,COLUMN(U15)-1),TRUE),"TBE",INDIRECT(ADDRESS(ROW(U15), COLUMN($Q15)+1) & ":" & ADDRESS(ROW(U15),COLUMN(U15)-1),TRUE)),IF(OFFSET(U15,ROW(U$2)-ROW(U15),0)="TBE",SUMIF(INDIRECT(ADDRESS(2,MATCH(INT(OFFSET(U15,ROW(U$2)-ROW(U15),-2)),$2:$2,0)) & ":" & ADDRESS(2,COLUMN(U15)-1),TRUE),"T",INDIRECT(ADDRESS(ROW(U15), MATCH(INT(OFFSET(U15,ROW(U$2)-ROW(U15),-2)),$2:$2,0)) & ":" & ADDRESS(ROW(U15),COLUMN(U15)-1),TRUE)),IF(OFFSET(U15,0,COLUMN($M15)-COLUMN(U15))="V",OFFSET(U15,0,-2)*OFFSET(U15,0,-1),"TOTAL"))) -> 0
A16: =IF(ISNUMBER(OFFSET(A16,0,12)),"START",IF(AND(OFFSET(A16,0,2)=0,OFFSET(A16,0,4)="GT"),"END",""))&OFFSET(A16,0,1) -> WP001 | B16: =IF(ISNUMBER(OFFSET(B16,0,11)),"WP" & TEXT(OFFSET(B16,0,11),"000"),OFFSET(B16,-1,0)) -> WP001 | C16: 7 | D16: WPRow.G | L16: T1 | M16: V | Q16: =EMP_OTHER -> Type 5 | T16: =IF(OFFSET(T16,ROW(T$2)-ROW(T16),0)="TT","TT",IF(OFFSET(T16,0,COLUMN($M16)-COLUMN(T16))="%",ROUND((OFFSET(T16,-2,0)-OFFSET(T16,-21,0))*0.07,2),IF(OFFSET(T16,0,COLUMN($M16)-COLUMN(T16))="V",ROUND(OFFSET(T16,0,-2)*OFFSET(T16,0,-1),2),SUMIF(INDIRECT(ADDRESS(MATCH("START"&OFFSET(T16,0,COLUMN($B16)-COLUMN(T16)),$A:$A,0),$C16+COLUMN($E16)+1)&":"&ADDRESS(MATCH("END"&OFFSET(T16,0,COLUMN($B16)-COLUMN(T16)),$A:$A,0),$C16+COLUMN($E16)+1),TRUE),INDIRECT(ADDRESS(ROW(T16),$C16+COLUMN($E16)),TRUE),INDIRECT(ADDRESS(MATCH("START"&OFFSET(T16,0,COLUMN($B16)-COLUMN(T16)),$A:$A,0),COLUMN(T16))&":"&ADDRESS(MATCH("END"&OFFSET(T16,0,COLUMN($B16)-COLUMN(T16)),$A:$A,0),COLUMN(T16)),TRUE))))) -> 0 | U16: =IF(OFFSET(U16,ROW(U$2)-ROW(U16),0)="TT",SUMIF(INDIRECT(ADDRESS(2,COLUMN($Q16)+1) & ":" & ADDRESS(2,COLUMN(U16)-1),TRUE),"TBE",INDIRECT(ADDRESS(ROW(U16), COLUMN($Q16)+1) & ":" & ADDRESS(ROW(U16),COLUMN(U16)-1),TRUE)),IF(OFFSET(U16,ROW(U$2)-ROW(U16),0)="TBE",SUMIF(INDIRECT(ADDRESS(2,MATCH(INT(OFFSET(U16,ROW(U$2)-ROW(U16),-2)),$2:$2,0)) & ":" & ADDRESS(2,COLUMN(U16)-1),TRUE),"T",INDIRECT(ADDRESS(ROW(U16), MATCH(INT(OFFSET(U16,ROW(U$2)-ROW(U16),-2)),$2:$2,0)) & ":" & ADDRESS(ROW(U16),COLUMN(U16)-1),TRUE)),IF(OFFSET(U16,0,COLUMN($M16)-COLUMN(U16))="V",OFFSET(U16,0,-2)*OFFSET(U16,0,-1),"TOTAL"))) -> 0
A17: =IF(ISNUMBER(OFFSET(A17,0,12)),"START",IF(AND(OFFSET(A17,0,2)=0,OFFSET(A17,0,4)="GT"),"END",""))&OFFSET(A17,0,1) -> WP001 | B17: =IF(ISNUMBER(OFFSET(B17,0,11)),"WP" & TEXT(OFFSET(B17,0,11),"000"),OFFSET(B17,-1,0)) -> WP001 | C17: 6 | D17: WPRow.H | J17: TA | M17: V | P17: A.2 Natural persons under direct contract | T17: =IF(OFFSET(T17,ROW(T$2)-ROW(T17),0)="TT","TT",IF(OFFSET(T17,0,COLUMN($M17)-COLUMN(T17))="%",ROUND((OFFSET(T17,-2,0)-OFFSET(T17,-21,0))*0.07,2),IF(OFFSET(T17,0,COLUMN($M17)-COLUMN(T17))="V",ROUND(OFFSET(T17,0,-2)*OFFSET(T17,0,-1),2),SUMIF(INDIRECT(ADDRESS(MATCH("START"&OFFSET(T17,0,COLUMN($B17)-COLUMN(T17)),$A:$A,0),$C17+COLUMN($E17)+1)&":"&ADDRESS(MATCH("END"&OFFSET(T17,0,COLUMN($B17)-COLUMN(T17)),$A:$A,0),$C17+COLUMN($E17)+1),TRUE),INDIRECT(ADDRESS(ROW(T17),$C17+COLUMN($E17)),TRUE),INDIRECT(ADDRESS(MATCH("START"&OFFSET(T17,0,COLUMN($B17)-COLUMN(T17)),$A:$A,0),COLUMN(T17))&":"&ADDRESS(MATCH("END"&OFFSET(T17,0,COLUMN($B17)-COLUMN(T17)),$A:$A,0),COLUMN(T17)),TRUE))))) -> 0 | U17: =IF(OFFSET(U17,ROW(U$2)-ROW(U17),0)="TT",SUMIF(INDIRECT(ADDRESS(2,COLUMN($Q17)+1) & ":" & ADDRESS(2,COLUMN(U17)-1),TRUE),"TBE",INDIRECT(ADDRESS(ROW(U17), COLUMN($Q17)+1) & ":" & ADDRESS(ROW(U17),COLUMN(U17)-1),TRUE)),IF(OFFSET(U17,ROW(U$2)-ROW(U17),0)="TBE",SUMIF(INDIRECT(ADDRESS(2,MATCH(INT(OFFSET(U17,ROW(U$2)-ROW(U17),-2)),$2:$2,0)) & ":" & ADDRESS(2,COLUMN(U17)-1),TRUE),"T",INDIRECT(ADDRESS(ROW(U17), MATCH(INT(OFFSET(U17,ROW(U$2)-ROW(U17),-2)),$2:$2,0)) & ":" & ADDRESS(ROW(U17),COLUMN(U17)-1),TRUE)),IF(OFFSET(U17,0,COLUMN($M17)-COLUMN(U17))="V",OFFSET(U17,0,-2)*OFFSET(U17,0,-1),"TOTAL"))) -> 0
A18: =IF(ISNUMBER(OFFSET(A18,0,12)),"START",IF(AND(OFFSET(A18,0,2)=0,OFFSET(A18,0,4)="GT"),"END",""))&OFFSET(A18,0,1) -> WP001 | B18: =IF(ISNUMBER(OFFSET(B18,0,11)),"WP" & TEXT(OFFSET(B18,0,11),"000"),OFFSET(B18,-1,0)) -> WP001 | C18: 6 | D18: WPRow.I | J18: TA | M18: V | P18: A.3 Seconded persons | T18: =IF(OFFSET(T18,ROW(T$2)-ROW(T18),0)="TT","TT",IF(OFFSET(T18,0,COLUMN($M18)-COLUMN(T18))="%",ROUND((OFFSET(T18,-2,0)-OFFSET(T18,-21,0))*0.07,2),IF(OFFSET(T18,0,COLUMN($M18)-COLUMN(T18))="V",ROUND(OFFSET(T18,0,-2)*OFFSET(T18,0,-1),2),SUMIF(INDIRECT(ADDRESS(MATCH("START"&OFFSET(T18,0,COLUMN($B18)-COLUMN(T18)),$A:$A,0),$C18+COLUMN($E18)+1)&":"&ADDRESS(MATCH("END"&OFFSET(T18,0,COLUMN($B18)-COLUMN(T18)),$A:$A,0),$C18+COLUMN($E18)+1),TRUE),INDIRECT(ADDRESS(ROW(T18),$C18+COLUMN($E18)),TRUE),INDIRECT(ADDRESS(MATCH("START"&OFFSET(T18,0,COLUMN($B18)-COLUMN(T18)),$A:$A,0),COLUMN(T18))&":"&ADDRESS(MATCH("END"&OFFSET(T18,0,COLUMN($B18)-COLUMN(T18)),$A:$A,0),COLUMN(T18)),TRUE))))) -> 0 | U18: =IF(OFFSET(U18,ROW(U$2)-ROW(U18),0)="TT",SUMIF(INDIRECT(ADDRESS(2,COLUMN($Q18)+1) & ":" & ADDRESS(2,COLUMN(U18)-1),TRUE),"TBE",INDIRECT(ADDRESS(ROW(U18), COLUMN($Q18)+1) & ":" & ADDRESS(ROW(U18),COLUMN(U18)-1),TRUE)),IF(OFFSET(U18,ROW(U$2)-ROW(U18),0)="TBE",SUMIF(INDIRECT(ADDRESS(2,MATCH(INT(OFFSET(U18,ROW(U$2)-ROW(U18),-2)),$2:$2,0)) & ":" & ADDRESS(2,COLUMN(U18)-1),TRUE),"T",INDIRECT(ADDRESS(ROW(U18), MATCH(INT(OFFSET(U18,ROW(U$2)-ROW(U18),-2)),$2:$2,0)) & ":" & ADDRESS(ROW(U18),COLUMN(U18)-1),TRUE)),IF(OFFSET(U18,0,COLUMN($M18)-COLUMN(U18))="V",OFFSET(U18,0,-2)*OFFSET(U18,0,-1),"TOTAL"))) -> 0
A19: =IF(ISNUMBER(OFFSET(A19,0,12)),"START",IF(AND(OFFSET(A19,0,2)=0,OFFSET(A19,0,4)="GT"),"END",""))&OFFSET(A19,0,1) -> WP001 | B19: =IF(ISNUMBER(OFFSET(B19,0,11)),"WP" & TEXT(OFFSET(B19,0,11),"000"),OFFSET(B19,-1,0)) -> WP001 | C19: 6 | D19: WPRow.J | J19: TA | M19: V | P19: A.4 SME Owners without salary | T19: =IF(OFFSET(T19,ROW(T$2)-ROW(T19),0)="TT","TT",IF(OFFSET(T19,0,COLUMN($M19)-COLUMN(T19))="%",ROUND((OFFSET(T19,-2,0)-OFFSET(T19,-21,0))*0.07,2),IF(OFFSET(T19,0,COLUMN($M19)-COLUMN(T19))="V",ROUND(OFFSET(T19,0,-2)*OFFSET(T19,0,-1),2),SUMIF(INDIRECT(ADDRESS(MATCH("START"&OFFSET(T19,0,COLUMN($B19)-COLUMN(T19)),$A:$A,0),$C19+COLUMN($E19)+1)&":"&ADDRESS(MATCH("END"&OFFSET(T19,0,COLUMN($B19)-COLUMN(T19)),$A:$A,0),$C19+COLUMN($E19)+1),TRUE),INDIRECT(ADDRESS(ROW(T19),$C19+COLUMN($E19)),TRUE),INDIRECT(ADDRESS(MATCH("START"&OFFSET(T19,0,COLUMN($B19)-COLUMN(T19)),$A:$A,0),COLUMN(T19))&":"&ADDRESS(MATCH("END"&OFFSET(T19,0,COLUMN($B19)-COLUMN(T19)),$A:$A,0),COLUMN(T19)),TRUE))))) -> 0 | U19: =IF(OFFSET(U19,ROW(U$2)-ROW(U19),0)="TT",SUMIF(INDIRECT(ADDRESS(2,COLUMN($Q19)+1) & ":" & ADDRESS(2,COLUMN(U19)-1),TRUE),"TBE",INDIRECT(ADDRESS(ROW(U19), COLUMN($Q19)+1) & ":" & ADDRESS(ROW(U19),COLUMN(U19)-1),TRUE)),IF(OFFSET(U19,ROW(U$2)-ROW(U19),0)="TBE",SUMIF(INDIRECT(ADDRESS(2,MATCH(INT(OFFSET(U19,ROW(U$2)-ROW(U19),-2)),$2:$2,0)) & ":" & ADDRESS(2,COLUMN(U19)-1),TRUE),"T",INDIRECT(ADDRESS(ROW(U19), MATCH(INT(OFFSET(U19,ROW(U$2)-ROW(U19),-2)),$2:$2,0)) & ":" & ADDRESS(ROW(U19),COLUMN(U19)-1),TRUE)),IF(OFFSET(U19,0,COLUMN($M19)-COLUMN(U19))="V",OFFSET(U19,0,-2)*OFFSET(U19,0,-1),"TOTAL"))) -> 0
A20: =IF(ISNUMBER(OFFSET(A20,0,12)),"START",IF(AND(OFFSET(A20,0,2)=0,OFFSET(A20,0,4)="GT"),"END",""))&OFFSET(A20,0,1) -> WP001 | B20: =IF(ISNUMBER(OFFSET(B20,0,11)),"WP" & TEXT(OFFSET(B20,0,11),"000"),OFFSET(B20,-1,0)) -> WP001 | C20: 6 | D20: WPRow.K | J20: TA | M20: V | P20: A.5 Volunteers | T20: =IF(OFFSET(T20,ROW(T$2)-ROW(T20),0)="TT","TT",IF(OFFSET(T20,0,COLUMN($M20)-COLUMN(T20))="%",ROUND((OFFSET(T20,-2,0)-OFFSET(T20,-21,0))*0.07,2),IF(OFFSET(T20,0,COLUMN($M20)-COLUMN(T20))="V",ROUND(OFFSET(T20,0,-2)*OFFSET(T20,0,-1),2),SUMIF(INDIRECT(ADDRESS(MATCH("START"&OFFSET(T20,0,COLUMN($B20)-COLUMN(T20)),$A:$A,0),$C20+COLUMN($E20)+1)&":"&ADDRESS(MATCH("END"&OFFSET(T20,0,COLUMN($B20)-COLUMN(T20)),$A:$A,0),$C20+COLUMN($E20)+1),TRUE),INDIRECT(ADDRESS(ROW(T20),$C20+COLUMN($E20)),TRUE),INDIRECT(ADDRESS(MATCH("START"&OFFSET(T20,0,COLUMN($B20)-COLUMN(T20)),$A:$A,0),COLUMN(T20))&":"&ADDRESS(MATCH("END"&OFFSET(T20,0,COLUMN($B20)-COLUMN(T20)),$A:$A,0),COLUMN(T20)),TRUE))))) -> 0 | U20: =IF(OFFSET(U20,ROW(U$2)-ROW(U20),0)="TT",SUMIF(INDIRECT(ADDRESS(2,COLUMN($Q20)+1) & ":" & ADDRESS(2,COLUMN(U20)-1),TRUE),"TBE",INDIRECT(ADDRESS(ROW(U20), COLUMN($Q20)+1) & ":" & ADDRESS(ROW(U20),COLUMN(U20)-1),TRUE)),IF(OFFSET(U20,ROW(U$2)-ROW(U20),0)="TBE",SUMIF(INDIRECT(ADDRESS(2,MATCH(INT(OFFSET(U20,ROW(U$2)-ROW(U20),-2)),$2:$2,0)) & ":" & ADDRESS(2,COLUMN(U20)-1),TRUE),"T",INDIRECT(ADDRESS(ROW(U20), MATCH(INT(OFFSET(U20,ROW(U$2)-ROW(U20),-2)),$2:$2,0)) & ":" & ADDRESS(ROW(U20),COLUMN(U20)-1),TRUE)),IF(OFFSET(U20,0,COLUMN($M20)-COLUMN(U20))="V",OFFSET(U20,0,-2)*OFFSET(U20,0,-1),"TOTAL"))) -> 0
A21: =IF(ISNUMBER(OFFSET(A21,0,12)),"START",IF(AND(OFFSET(A21,0,2)=0,OFFSET(A21,0,4)="GT"),"END",""))&OFFSET(A21,0,1) -> WP001 | B21: =IF(ISNUMBER(OFFSET(B21,0,11)),"WP" & TEXT(OFFSET(B21,0,11),"000"),OFFSET(B21,-1,0)) -> WP001 | C21: 4 | D21: WPRow.L | H21: TTA | I21: TB | M21: V | O21: B. Subcontracting costs (please specify details under worksheet "Comments") | T21: =IF(OFFSET(T21,ROW(T$2)-ROW(T21),0)="TT","TT",IF(OFFSET(T21,0,COLUMN($M21)-COLUMN(T21))="%",ROUND((OFFSET(T21,-2,0)-OFFSET(T21,-21,0))*0.07,2),IF(OFFSET(T21,0,COLUMN($M21)-COLUMN(T21))="V",ROUND(OFFSET(T21,0,-2)*OFFSET(T21,0,-1),2),SUMIF(INDIRECT(ADDRESS(MATCH("START"&OFFSET(T21,0,COLUMN($B21)-COLUMN(T21)),$A:$A,0),$C21+COLUMN($E21)+1)&":"&ADDRESS(MATCH("END"&OFFSET(T21,0,COLUMN($B21)-COLUMN(T21)),$A:$A,0),$C21+COLUMN($E21)+1),TRUE),INDIRECT(ADDRESS(ROW(T21),$C21+COLUMN($E21)),TRUE),INDIRECT(ADDRESS(MATCH("START"&OFFSET(T21,0,COLUMN($B21)-COLUMN(T21)),$A:$A,0),COLUMN(T21))&":"&ADDRESS(MATCH("END"&OFFSET(T21,0,COLUMN($B21)-COLUMN(T21)),$A:$A,0),COLUMN(T21)),TRUE))))) -> 0 | U21: =IF(OFFSET(U21,ROW(U$2)-ROW(U21),0)="TT",SUMIF(INDIRECT(ADDRESS(2,COLUMN($Q21)+1) & ":" & ADDRESS(2,COLUMN(U21)-1),TRUE),"TBE",INDIRECT(ADDRESS(ROW(U21), COLUMN($Q21)+1) & ":" & ADDRESS(ROW(U21),COLUMN(U21)-1),TRUE)),IF(OFFSET(U21,ROW(U$2)-ROW(U21),0)="TBE",SUMIF(INDIRECT(ADDRESS(2,MATCH(INT(OFFSET(U21,ROW(U$2)-ROW(U21),-2)),$2:$2,0)) & ":" & ADDRESS(2,COLUMN(U21)-1),TRUE),"T",INDIRECT(ADDRESS(ROW(U21), MATCH(INT(OFFSET(U21,ROW(U$2)-ROW(U21),-2)),$2:$2,0)) & ":" & ADDRESS(ROW(U21),COLUMN(U21)-1),TRUE)),IF(OFFSET(U21,0,COLUMN($M21)-COLUMN(U21))="V",OFFSET(U21,0,-2)*OFFSET(U21,0,-1),"TOTAL"))) -> 0
A22: =IF(ISNUMBER(OFFSET(A22,0,12)),"START",IF(AND(OFFSET(A22,0,2)=0,OFFSET(A22,0,4)="GT"),"END",""))&OFFSET(A22,0,1) -> WP001 | B22: =IF(ISNUMBER(OFFSET(B22,0,11)),"WP" & TEXT(OFFSET(B22,0,11),"000"),OFFSET(B22,-1,0)) -> WP001 | C22: 4 | D22: WPRow.M | H22: TTA | I22: TC | M22: T | O22: C. Purchase costs | T22: =IF(OFFSET(T22,ROW(T$2)-ROW(T22),0)="TT","TT",IF(OFFSET(T22,0,COLUMN($M22)-COLUMN(T22))="%",ROUND((OFFSET(T22,-2,0)-OFFSET(T22,-21,0))*0.07,2),IF(OFFSET(T22,0,COLUMN($M22)-COLUMN(T22))="V",ROUND(OFFSET(T22,0,-2)*OFFSET(T22,0,-1),2),SUMIF(INDIRECT(ADDRESS(MATCH("START"&OFFSET(T22,0,COLUMN($B22)-COLUMN(T22)),$A:$A,0),$C22+COLUMN($E22)+1)&":"&ADDRESS(MATCH("END"&OFFSET(T22,0,COLUMN($B22)-COLUMN(T22)),$A:$A,0),$C22+COLUMN($E22)+1),TRUE),INDIRECT(ADDRESS(ROW(T22),$C22+COLUMN($E22)),TRUE),INDIRECT(ADDRESS(MATCH("START"&OFFSET(T22,0,COLUMN($B22)-COLUMN(T22)),$A:$A,0),COLUMN(T22))&":"&ADDRESS(MATCH("END"&OFFSET(T22,0,COLUMN($B22)-COLUMN(T22)),$A:$A,0),COLUMN(T22)),TRUE))))) -> 0 | U22: =IF(OFFSET(U22,ROW(U$2)-ROW(U22),0)="TT",SUMIF(INDIRECT(ADDRESS(2,COLUMN($Q22)+1) & ":" & ADDRESS(2,COLUMN(U22)-1),TRUE),"TBE",INDIRECT(ADDRESS(ROW(U22), COLUMN($Q22)+1) & ":" & ADDRESS(ROW(U22),COLUMN(U22)-1),TRUE)),IF(OFFSET(U22,ROW(U$2)-ROW(U22),0)="TBE",SUMIF(INDIRECT(ADDRESS(2,MATCH(INT(OFFSET(U22,ROW(U$2)-ROW(U22),-2)),$2:$2,0)) & ":" & ADDRESS(2,COLUMN(U22)-1),TRUE),"T",INDIRECT(ADDRESS(ROW(U22), MATCH(INT(OFFSET(U22,ROW(U$2)-ROW(U22),-2)),$2:$2,0)) & ":" & ADDRESS(ROW(U22),COLUMN(U22)-1),TRUE)),IF(OFFSET(U22,0,COLUMN($M22)-COLUMN(U22))="V",OFFSET(U22,0,-2)*OFFSET(U22,0,-1),"TOTAL"))) -> 0
A23: =IF(ISNUMBER(OFFSET(A23,0,12)),"START",IF(AND(OFFSET(A23,0,2)=0,OFFSET(A23,0,4)="GT"),"END",""))&OFFSET(A23,0,1) -> WP001 | B23: =IF(ISNUMBER(OFFSET(B23,0,11)),"WP" & TEXT(OFFSET(B23,0,11),"000"),OFFSET(B23,-1,0)) -> WP001 | C23: 6 | D23: WPRow.N | J23: TC | K23: T3 | M23: T | P23: C.1 Travel and subsistence per travel or day | T23: =IF(OFFSET(T23,ROW(T$2)-ROW(T23),0)="TT","TT",IF(OFFSET(T23,0,COLUMN($M23)-COLUMN(T23))="%",ROUND((OFFSET(T23,-2,0)-OFFSET(T23,-21,0))*0.07,2),IF(OFFSET(T23,0,COLUMN($M23)-COLUMN(T23))="V",ROUND(OFFSET(T23,0,-2)*OFFSET(T23,0,-1),2),SUMIF(INDIRECT(ADDRESS(MATCH("START"&OFFSET(T23,0,COLUMN($B23)-COLUMN(T23)),$A:$A,0),$C23+COLUMN($E23)+1)&":"&ADDRESS(MATCH("END"&OFFSET(T23,0,COLUMN($B23)-COLUMN(T23)),$A:$A,0),$C23+COLUMN($E23)+1),TRUE),INDIRECT(ADDRESS(ROW(T23),$C23+COLUMN($E23)),TRUE),INDIRECT(ADDRESS(MATCH("START"&OFFSET(T23,0,COLUMN($B23)-COLUMN(T23)),$A:$A,0),COLUMN(T23))&":"&ADDRESS(MATCH("END"&OFFSET(T23,0,COLUMN($B23)-COLUMN(T23)),$A:$A,0),COLUMN(T23)),TRUE))))) -> 0 | U23: =IF(OFFSET(U23,ROW(U$2)-ROW(U23),0)="TT",SUMIF(INDIRECT(ADDRESS(2,COLUMN($Q23)+1) & ":" & ADDRESS(2,COLUMN(U23)-1),TRUE),"TBE",INDIRECT(ADDRESS(ROW(U23), COLUMN($Q23)+1) & ":" & ADDRESS(ROW(U23),COLUMN(U23)-1),TRUE)),IF(OFFSET(U23,ROW(U$2)-ROW(U23),0)="TBE",SUMIF(INDIRECT(ADDRESS(2,MATCH(INT(OFFSET(U23,ROW(U$2)-ROW(U23),-2)),$2:$2,0)) & ":" & ADDRESS(2,COLUMN(U23)-1),TRUE),"T",INDIRECT(ADDRESS(ROW(U23), MATCH(INT(OFFSET(U23,ROW(U$2)-ROW(U23),-2)),$2:$2,0)) & ":" & ADDRESS(ROW(U23),COLUMN(U23)-1),TRUE)),IF(OFFSET(U23,0,COLUMN($M23)-COLUMN(U23))="V",OFFSET(U23,0,-2)*OFFSET(U23,0,-1),"TOTAL"))) -> 0
A24: =IF(ISNUMBER(OFFSET(A24,0,12)),"START",IF(AND(OFFSET(A24,0,2)=0,OFFSET(A24,0,4)="GT"),"END",""))&OFFSET(A24,0,1) -> WP001 | B24: =IF(ISNUMBER(OFFSET(B24,0,11)),"WP" & TEXT(OFFSET(B24,0,11),"000"),OFFSET(B24,-1,0)) -> WP001 | C24: 7 | D24: WPRow.O | L24: T3 | M24: V | Q24: Travel | T24: =IF(OFFSET(T24,ROW(T$2)-ROW(T24),0)="TT","TT",IF(OFFSET(T24,0,COLUMN($M24)-COLUMN(T24))="%",ROUND((OFFSET(T24,-2,0)-OFFSET(T24,-21,0))*0.07,2),IF(OFFSET(T24,0,COLUMN($M24)-COLUMN(T24))="V",ROUND(OFFSET(T24,0,-2)*OFFSET(T24,0,-1),2),SUMIF(INDIRECT(ADDRESS(MATCH("START"&OFFSET(T24,0,COLUMN($B24)-COLUMN(T24)),$A:$A,0),$C24+COLUMN($E24)+1)&":"&ADDRESS(MATCH("END"&OFFSET(T24,0,COLUMN($B24)-COLUMN(T24)),$A:$A,0),$C24+COLUMN($E24)+1),TRUE),INDIRECT(ADDRESS(ROW(T24),$C24+COLUMN($E24)),TRUE),INDIRECT(ADDRESS(MATCH("START"&OFFSET(T24,0,COLUMN($B24)-COLUMN(T24)),$A:$A,0),COLUMN(T24))&":"&ADDRESS(MATCH("END"&OFFSET(T24,0,COLUMN($B24)-COLUMN(T24)),$A:$A,0),COLUMN(T24)),TRUE))))) -> 0 | U24: =IF(OFFSET(U24,ROW(U$2)-ROW(U24),0)="TT",SUMIF(INDIRECT(ADDRESS(2,COLUMN($Q24)+1) & ":" & ADDRESS(2,COLUMN(U24)-1),TRUE),"TBE",INDIRECT(ADDRESS(ROW(U24), COLUMN($Q24)+1) & ":" & ADDRESS(ROW(U24),COLUMN(U24)-1),TRUE)),IF(OFFSET(U24,ROW(U$2)-ROW(U24),0)="TBE",SUMIF(INDIRECT(ADDRESS(2,MATCH(INT(OFFSET(U24,ROW(U$2)-ROW(U24),-2)),$2:$2,0)) & ":" & ADDRESS(2,COLUMN(U24)-1),TRUE),"T",INDIRECT(ADDRESS(ROW(U24), MATCH(INT(OFFSET(U24,ROW(U$2)-ROW(U24),-2)),$2:$2,0)) & ":" & ADDRESS(ROW(U24),COLUMN(U24)-1),TRUE)),IF(OFFSET(U24,0,COLUMN($M24)-COLUMN(U24))="V",OFFSET(U24,0,-2)*OFFSET(U24,0,-1),"TOTAL"))) -> 0
A25: =IF(ISNUMBER(OFFSET(A25,0,12)),"START",IF(AND(OFFSET(A25,0,2)=0,OFFSET(A25,0,4)="GT"),"END",""))&OFFSET(A25,0,1) -> WP001 | B25: =IF(ISNUMBER(OFFSET(B25,0,11)),"WP" & TEXT(OFFSET(B25,0,11),"000"),OFFSET(B25,-1,0)) -> WP001 | C25: 7 | D25: WPRow.P | L25: T3 | M25: V | Q25: Accommodation | T25: =IF(OFFSET(T25,ROW(T$2)-ROW(T25),0)="TT","TT",IF(OFFSET(T25,0,COLUMN($M25)-COLUMN(T25))="%",ROUND((OFFSET(T25,-2,0)-OFFSET(T25,-21,0))*0.07,2),IF(OFFSET(T25,0,COLUMN($M25)-COLUMN(T25))="V",ROUND(OFFSET(T25,0,-2)*OFFSET(T25,0,-1),2),SUMIF(INDIRECT(ADDRESS(MATCH("START"&OFFSET(T25,0,COLUMN($B25)-COLUMN(T25)),$A:$A,0),$C25+COLUMN($E25)+1)&":"&ADDRESS(MATCH("END"&OFFSET(T25,0,COLUMN($B25)-COLUMN(T25)),$A:$A,0),$C25+COLUMN($E25)+1),TRUE),INDIRECT(ADDRESS(ROW(T25),$C25+COLUMN($E25)),TRUE),INDIRECT(ADDRESS(MATCH("START"&OFFSET(T25,0,COLUMN($B25)-COLUMN(T25)),$A:$A,0),COLUMN(T25))&":"&ADDRESS(MATCH("END"&OFFSET(T25,0,COLUMN($B25)-COLUMN(T25)),$A:$A,0),COLUMN(T25)),TRUE))))) -> 0 | U25: =IF(OFFSET(U25,ROW(U$2)-ROW(U25),0)="TT",SUMIF(INDIRECT(ADDRESS(2,COLUMN($Q25)+1) & ":" & ADDRESS(2,COLUMN(U25)-1),TRUE),"TBE",INDIRECT(ADDRESS(ROW(U25), COLUMN($Q25)+1) & ":" & ADDRESS(ROW(U25),COLUMN(U25)-1),TRUE)),IF(OFFSET(U25,ROW(U$2)-ROW(U25),0)="TBE",SUMIF(INDIRECT(ADDRESS(2,MATCH(INT(OFFSET(U25,ROW(U$2)-ROW(U25),-2)),$2:$2,0)) & ":" & ADDRESS(2,COLUMN(U25)-1),TRUE),"T",INDIRECT(ADDRESS(ROW(U25), MATCH(INT(OFFSET(U25,ROW(U$2)-ROW(U25),-2)),$2:$2,0)) & ":" & ADDRESS(ROW(U25),COLUMN(U25)-1),TRUE)),IF(OFFSET(U25,0,COLUMN($M25)-COLUMN(U25))="V",OFFSET(U25,0,-2)*OFFSET(U25,0,-1),"TOTAL"))) -> 0
A26: =IF(ISNUMBER(OFFSET(A26,0,12)),"START",IF(AND(OFFSET(A26,0,2)=0,OFFSET(A26,0,4)="GT"),"END",""))&OFFSET(A26,0,1) -> WP001 | B26: =IF(ISNUMBER(OFFSET(B26,0,11)),"WP" & TEXT(OFFSET(B26,0,11),"000"),OFFSET(B26,-1,0)) -> WP001 | C26: 7 | D26: WPRow.Q | L26: T3 | M26: V | Q26: Subsistence | T26: =IF(OFFSET(T26,ROW(T$2)-ROW(T26),0)="TT","TT",IF(OFFSET(T26,0,COLUMN($M26)-COLUMN(T26))="%",ROUND((OFFSET(T26,-2,0)-OFFSET(T26,-21,0))*0.07,2),IF(OFFSET(T26,0,COLUMN($M26)-COLUMN(T26))="V",ROUND(OFFSET(T26,0,-2)*OFFSET(T26,0,-1),2),SUMIF(INDIRECT(ADDRESS(MATCH("START"&OFFSET(T26,0,COLUMN($B26)-COLUMN(T26)),$A:$A,0),$C26+COLUMN($E26)+1)&":"&ADDRESS(MATCH("END"&OFFSET(T26,0,COLUMN($B26)-COLUMN(T26)),$A:$A,0),$C26+COLUMN($E26)+1),TRUE),INDIRECT(ADDRESS(ROW(T26),$C26+COLUMN($E26)),TRUE),INDIRECT(ADDRESS(MATCH("START"&OFFSET(T26,0,COLUMN($B26)-COLUMN(T26)),$A:$A,0),COLUMN(T26))&":"&ADDRESS(MATCH("END"&OFFSET(T26,0,COLUMN($B26)-COLUMN(T26)),$A:$A,0),COLUMN(T26)),TRUE))))) -> 0 | U26: =IF(OFFSET(U26,ROW(U$2)-ROW(U26),0)="TT",SUMIF(INDIRECT(ADDRESS(2,COLUMN($Q26)+1) & ":" & ADDRESS(2,COLUMN(U26)-1),TRUE),"TBE",INDIRECT(ADDRESS(ROW(U26), COLUMN($Q26)+1) & ":" & ADDRESS(ROW(U26),COLUMN(U26)-1),TRUE)),IF(OFFSET(U26,ROW(U$2)-ROW(U26),0)="TBE",SUMIF(INDIRECT(ADDRESS(2,MATCH(INT(OFFSET(U26,ROW(U$2)-ROW(U26),-2)),$2:$2,0)) & ":" & ADDRESS(2,COLUMN(U26)-1),TRUE),"T",INDIRECT(ADDRESS(ROW(U26), MATCH(INT(OFFSET(U26,ROW(U$2)-ROW(U26),-2)),$2:$2,0)) & ":" & ADDRESS(ROW(U26),COLUMN(U26)-1),TRUE)),IF(OFFSET(U26,0,COLUMN($M26)-COLUMN(U26))="V",OFFSET(U26,0,-2)*OFFSET(U26,0,-1),"TOTAL"))) -> 0
A27: =IF(ISNUMBER(OFFSET(A27,0,12)),"START",IF(AND(OFFSET(A27,0,2)=0,OFFSET(A27,0,4)="GT"),"END",""))&OFFSET(A27,0,1) -> WP001 | B27: =IF(ISNUMBER(OFFSET(B27,0,11)),"WP" & TEXT(OFFSET(B27,0,11),"000"),OFFSET(B27,-1,0)) -> WP001 | C27: 5 | D27: WPRow.R | J27: TC | M27: V | P27: C.2 Equipment (please refer to the Depreciation Cost sheet) | T27: =IF(OFFSET(T27,ROW(T$2)-ROW(T27),0)="TT","TT",IF(OFFSET(T27,0,COLUMN($M27)-COLUMN(T27))="%",ROUND((OFFSET(T27,-2,0)-OFFSET(T27,-21,0))*0.07,2),IF(OFFSET(T27,0,COLUMN($M27)-COLUMN(T27))="V",ROUND(OFFSET(T27,0,-2)*OFFSET(T27,0,-1),2),SUMIF(INDIRECT(ADDRESS(MATCH("START"&OFFSET(T27,0,COLUMN($B27)-COLUMN(T27)),$A:$A,0),$C27+COLUMN($E27)+1)&":"&ADDRESS(MATCH("END"&OFFSET(T27,0,COLUMN($B27)-COLUMN(T27)),$A:$A,0),$C27+COLUMN($E27)+1),TRUE),INDIRECT(ADDRESS(ROW(T27),$C27+COLUMN($E27)),TRUE),INDIRECT(ADDRESS(MATCH("START"&OFFSET(T27,0,COLUMN($B27)-COLUMN(T27)),$A:$A,0),COLUMN(T27))&":"&ADDRESS(MATCH("END"&OFFSET(T27,0,COLUMN($B27)-COLUMN(T27)),$A:$A,0),COLUMN(T27)),TRUE))))) -> 0 | U27: =IF(OFFSET(U27,ROW(U$2)-ROW(U27),0)="TT",SUMIF(INDIRECT(ADDRESS(2,COLUMN($Q27)+1) & ":" & ADDRESS(2,COLUMN(U27)-1),TRUE),"TBE",INDIRECT(ADDRESS(ROW(U27), COLUMN($Q27)+1) & ":" & ADDRESS(ROW(U27),COLUMN(U27)-1),TRUE)),IF(OFFSET(U27,ROW(U$2)-ROW(U27),0)="TBE",SUMIF(INDIRECT(ADDRESS(2,MATCH(INT(OFFSET(U27,ROW(U$2)-ROW(U27),-2)),$2:$2,0)) & ":" & ADDRESS(2,COLUMN(U27)-1),TRUE),"T",INDIRECT(ADDRESS(ROW(U27), MATCH(INT(OFFSET(U27,ROW(U$2)-ROW(U27),-2)),$2:$2,0)) & ":" & ADDRESS(ROW(U27),COLUMN(U27)-1),TRUE)),IF(OFFSET(U27,0,COLUMN($M27)-COLUMN(U27))="V",OFFSET(U27,0,-2)*OFFSET(U27,0,-1),"TOTAL"))) -> 0
A28: =IF(ISNUMBER(OFFSET(A28,0,12)),"START",IF(AND(OFFSET(A28,0,2)=0,OFFSET(A28,0,4)="GT"),"END",""))&OFFSET(A28,0,1) -> WP001 | B28: =IF(ISNUMBER(OFFSET(B28,0,11)),"WP" & TEXT(OFFSET(B28,0,11),"000"),OFFSET(B28,-1,0)) -> WP001 | C28: 6 | D28: WPRow.S | J28: TC | K28: T4 | M28: T | P28: C.3 Other goods, works and services | T28: =IF(OFFSET(T28,ROW(T$2)-ROW(T28),0)="TT","TT",IF(OFFSET(T28,0,COLUMN($M28)-COLUMN(T28))="%",ROUND((OFFSET(T28,-2,0)-OFFSET(T28,-21,0))*0.07,2),IF(OFFSET(T28,0,COLUMN($M28)-COLUMN(T28))="V",ROUND(OFFSET(T28,0,-2)*OFFSET(T28,0,-1),2),SUMIF(INDIRECT(ADDRESS(MATCH("START"&OFFSET(T28,0,COLUMN($B28)-COLUMN(T28)),$A:$A,0),$C28+COLUMN($E28)+1)&":"&ADDRESS(MATCH("END"&OFFSET(T28,0,COLUMN($B28)-COLUMN(T28)),$A:$A,0),$C28+COLUMN($E28)+1),TRUE),INDIRECT(ADDRESS(ROW(T28),$C28+COLUMN($E28)),TRUE),INDIRECT(ADDRESS(MATCH("START"&OFFSET(T28,0,COLUMN($B28)-COLUMN(T28)),$A:$A,0),COLUMN(T28))&":"&ADDRESS(MATCH("END"&OFFSET(T28,0,COLUMN($B28)-COLUMN(T28)),$A:$A,0),COLUMN(T28)),TRUE))))) -> 0 | U28: =IF(OFFSET(U28,ROW(U$2)-ROW(U28),0)="TT",SUMIF(INDIRECT(ADDRESS(2,COLUMN($Q28)+1) & ":" & ADDRESS(2,COLUMN(U28)-1),TRUE),"TBE",INDIRECT(ADDRESS(ROW(U28), COLUMN($Q28)+1) & ":" & ADDRESS(ROW(U28),COLUMN(U28)-1),TRUE)),IF(OFFSET(U28,ROW(U$2)-ROW(U28),0)="TBE",SUMIF(INDIRECT(ADDRESS(2,MATCH(INT(OFFSET(U28,ROW(U$2)-ROW(U28),-2)),$2:$2,0)) & ":" & ADDRESS(2,COLUMN(U28)-1),TRUE),"T",INDIRECT(ADDRESS(ROW(U28), MATCH(INT(OFFSET(U28,ROW(U$2)-ROW(U28),-2)),$2:$2,0)) & ":" & ADDRESS(ROW(U28),COLUMN(U28)-1),TRUE)),IF(OFFSET(U28,0,COLUMN($M28)-COLUMN(U28))="V",OFFSET(U28,0,-2)*OFFSET(U28,0,-1),"TOTAL"))) -> 0
